Workbook

Sheet Legend
B2: Sheet recap
B4: Name | C4: Description
B5: RAW_CEIC | C5: Raw data extracted from CEIC
B6: WIDE_CEIC | C6: CEIC data with some correction of new provinces. The island of Papua is simplified into two provinces: Papua Barat and Papua. We also add Kalimantan Utara's export and import (2010-2011) as well as Maluku Utara's export and import (from GDP, 2010-2024) manually from BPS' publication.
B7: WIDE_IDD | C7: INDODAPOER data. New provinces are reconstructed using city-level data when available, or estimated using the historical trend of their share relative to the parent province.
B8: LONG_CEIC | C8: Long format of WIDE_CEIC
B9: LONG_IBS | C9: Long format of IBS data at the province level.
B10: LONG_ALL | C10: Combined LONG_CEIC and LONG_IBS
B12: Variable recap
B14: Indicator | C14: Description | D14: Sheet | E14: Unit | F14: Source | G14: First Year | H14: Last Year | I14: Kalimantan Utara | J14: Sulawesi Barat | K14: Papua Barat | L14: Kep. Riau | M14: Maluku Utara | N14: N
B15: gdpr_ceic | C15: Gross Domestic Product: SNA 2008: 2010p | D15: WIDE_CEIC | E15: IDR bn | F15: CEIC | G15: 2000 | H15: 2025 | I15: 2010 | J15: 2005 | K15: 2002 | L15: 2003 | M15: 2000 | N15: =34*25-(I15-2000)-(J15-2000)-(K15-2000)-(L15-2000)-(M15-2000) -> 830
B16: gfcr_ceic | C16: Gross Fixed Capital Formation: SNA 2008: 2010p | D16: WIDE_CEIC | E16: IDR bn | F16: CEIC | G16: 2000 | H16: 2025 | I16: 2010 | J16: 2004 | K16: 2002 | L16: 2003 | M16: 2000 | N16: =34*25-(I16-2000)-(J16-2000)-(K16-2000)-(L16-2000)-(M16-2000) -> 831
B17: agrr_ceic | C17: Agriculture, Forestry & Fisheries: SNA 2008: 2010p | D17: WIDE_CEIC | E17: IDR bn | F17: CEIC | G17: 2000 | H17: 2025 | I17: 2010 | J17: 2005 | K17: 2002 | L17: 2003 | M17: 2000 | N17: =34*25-(I17-2000)-(J17-2000)-(K17-2000)-(L17-2000)-(M17-2000) -> 830
B18: mnqr_ceic | C18: Mining & Quarrying: SNA 2008: 2010p | D18: WIDE_CEIC | E18: IDR bn | F18: CEIC | G18: 2000 | H18: 2025 | I18: 2010 | J18: 2005 | K18: 2002 | L18: 2003 | M18: 2000 | N18: =34*25-(I18-2000)-(J18-2000)-(K18-2000)-(L18-2000)-(M18-2000) -> 830
B19: mnfr_ceic | C19: Manufacturing Industry: SNA 2008: 2010p | D19: WIDE_CEIC | E19: IDR bn | F19: CEIC | G19: 2000 | H19: 2025 | I19: 2010 | J19: 2005 | K19: 2002 | L19: 2003 | M19: 2000 | N19: =34*25-(I19-2000)-(J19-2000)-(K19-2000)-(L19-2000)-(M19-2000) -> 830
B20: expr_ceic | C20: Export of Goods and Services: SNA 2008: 2010p | D20: WIDE_CEIC | E20: IDR bn | F20: CEIC | G20: 2000 | H20: 2024 | I20: 2010 | J20: 2004 | K20: 2002 | L20: 2003 | M20: 2010 | N20: =34*25-(I20-2000)-(J20-2000)-(K20-2000)-(L20-2000)-(M20-2000) -> 821
B21: impr_ceic | C21: Import of Goods and Services: SNA 2008: 2010p | D21: WIDE_CEIC | E21: IDR bn | F21: CEIC | G21: 2000 | H21: 2024 | I21: 2010 | J21: 2004 | K21: 2002 | L21: 2003 | M21: 2010 | N21: =34*25-(I21-2000)-(J21-2000)-(K21-2000)-(L21-2000)-(M21-2000) -> 821
B22: pprj_ceic | C22: BPS' population projection | D22: WIDE_CEIC | E22: 000 people | F22: CEIC | G22: 2000 | H22: 2025 | I22: 2010 | J22: 2004 | K22: 2002 | L22: 2003 | M22: 2010
B24: Gajadi dipake
B25: Indicator | C25: Description | D25: Sheet | E25: Unit | F25: Source | G25: First Year | H25: Last Year
B26: gdpn_ceic | C26: Gross Domestic Product: SNA 2008 | D26: WIDE_IDD | E26: IDR bn | F26: CEIC | G26: 2000 | H26: 2025
B27: gdpn_idd | C27: Total GDP including Oil and Gas (in IDR Million), Current Price | D27: WIDE_IDD | E27: IDR bn | F27: INDODAPOER | G27: 2000 | H27: 2013
B28: gfcn_idd | C28: GDP expenditure on gross fixed capital formation (in IDR Million), Current Price | D28: WIDE_IDD | E28: IDR bn | F28: INDODAPOER | G28: 2000 | H28: 2013
B29: expn_idd | C29: GDP expenditure on exports (in IDR Million) | D29: WIDE_IDD | E29: IDR bn | F29: INDODAPOER | G29: 2000 | H29: 2013
B30: impn_idd | C30: GDP expenditure on imports (in IDR Million) | D30: WIDE_IDD | E30: IDR bn | F30: INDODAPOER | G30: 2000 | H30: 2013
B32: prov | C32: provname | D32: prov
B33: 11 | C33: Aceh | D33: 11
B34: 51 | C34: Bali | D34: 51
B35: 36 | C35: Banten | D35: 36
B36: 17 | C36: Bengkulu | D36: 17
B37: 34 | C37: DI Yogyakarta | D37: 34
B38: 31 | C38: DKI Jakarta | D38: 31
B39: 75 | C39: Gorontalo | D39: 75
B40: 15 | C40: Jambi | D40: 15
B41: 32 | C41: Jawa Barat | D41: 32
B42: 33 | C42: Jawa Tengah | D42: 33
B43: 35 | C43: Jawa Timur | D43: 35
B44: 61 | C44: Kalimantan Barat | D44: 61
... B66: 12 | C66: Sumatera Utara | D66: 12

Sheet FIXING IMPORT
B2: Step 2: Calculate import to GDP
B4: provname | C4: indicator | D4: 2000 | E4: 2001 | F4: 2002 | G4: 2003 | H4: 2004 | I4: 2005 | J4: 2006 | K4: 2007 | L4: 2008 | M4: 2009 | N4: 2010 | O4: 2011 | P4: 2012 | Q4: 2013 | R4: 2014 | S4: 2015 | T4: 2016 | U4: 2017 | V4: 2018 | W4: 2019 | X4: 2020 | Y4: 2021 | Z4: 2022 | AA4: 2023 | AB4: 2024
B5: Aceh | C5: share | D5: =D78/D41 -> 0.42761293 | E5: =E78/E41 -> 0.48745762 | F5: =F78/F41 -> 0.077022653 | G5: =G78/G41 -> 0.13900632 | H5: =H78/H41 -> 0.098896087 | I5: =I78/I41 -> 0.8649862 | J5: =J78/J41 -> 0.06776372 | K5: =K78/K41 -> 0.42491019 | ... AB5: =AB78/AB41 -> 0.5804791
B6: Bali | C6: share | D6: =D79/D42 -> 0.050130701 | E6: =E79/E42 -> 0.048516289 | F6: =F79/F42 -> 0.048733343 | G6: =G79/G42 -> 0.049377864 | H6: =H79/H42 -> 0.084227239 | I6: =I79/I42 -> 0.092482286 | J6: =J79/J42 -> 0.078732321 | K6: =K79/K42 -> 0.093030644 | ... AB6: =AB79/AB42 -> 0.054160948
B7: Banten | C7: share | D7: =D80/D43 -> 0.72469539 | E7: =E80/E43 -> 0.67793069 | F7: =F80/F43 -> 0.72291111 | G7: =G80/G43 -> 0.7626953 | H7: =H80/H43 -> 0.80923964 | I7: =I80/I43 -> 0.83711333 | J7: =J80/J43 -> 0.88312921 | K7: =K80/K43 -> 0.89643627 | ... AB7: =AB80/AB43 -> 0.69557636
B8: Bengkulu | C8: share | D8: =D81/D44 -> 0.60686146 | E8: =E81/E44 -> 0.57884255 | F8: =F81/F44 -> 0.56673304 | G8: =G81/G44 -> 0.55139536 | H8: =H81/H44 -> 0.5830919 | I8: =I81/I44 -> 0.62613437 | J8: =J81/J44 -> 0.6222205 | K8: =K81/K44 -> 0.64407054 | ... AB8: =AB81/AB44 -> 0.62581161
B9: DI Yogyakarta | C9: share | D9: =D82/D45 -> 0.02140998 | E9: =E82/E45 -> 0.022312139 | F9: =F82/F45 -> 0.022645959 | G9: =G82/G45 -> 0.023444959 | H9: =H82/H45 -> 0.02338288 | I9: =I82/I45 -> 0.023302368 | J9: =J82/J45 -> 0.023433683 | K9: =K82/K45 -> 0.023602627 | ... AB9: =AB82/AB45 -> 0.036137638
B10: DKI Jakarta | C10: share | D10: =D83/D46 -> 0.51373676 | E10: =E83/E46 -> 0.38648251 | F10: =F83/F46 -> 0.36178596 | G10: =G83/G46 -> 0.41841376 | H10: =H83/H46 -> 0.49104245 | I10: =I83/I46 -> 0.54670984 | J10: =J83/J46 -> 0.54412099 | K10: =K83/K46 -> 0.57457246 | ... AB10: =AB83/AB46 -> 0.70875011
B11: Gorontalo | C11: share | D11: =D84/D47 -> 0.018836278 | E11: =E84/E47 -> 0.023150469 | F11: =F84/F47 -> 0.022464791 | G11: =G84/G47 -> 0.17585265 | H11: =H84/H47 -> 0.20176377 | I11: =I84/I47 -> 0.1145323 | J11: =J84/J47 -> 0.27375993 | K11: =K84/K47 -> 0.32373191 | ... AB11: =AB84/AB47 -> 0.34100451
B12: Jambi | C12: share | D12: =D85/D48 -> 0.35830935 | E12: =E85/E48 -> 0.38051619 | F12: =F85/F48 -> 0.36084876 | G12: =G85/G48 -> 0.38154804 | H12: =H85/H48 -> 0.39628764 | I12: =I85/I48 -> 0.44371658 | J12: =J85/J48 -> 0.47657423 | K12: =K85/K48 -> 0.52964101 | ... AB12: =AB85/AB48 -> 0.38840717
B13: Jawa Barat | C13: share | D13: =D86/D49 -> 0.3529103 | E13: =E86/E49 -> 0.44228306 | F13: =F86/F49 -> 0.62600645 | G13: =G86/G49 -> 0.62280743 | H13: =H86/H49 -> 0.67789956 | I13: =I86/I49 -> 0.65488218 | J13: =J86/J49 -> 0.55154179 | K13: =K86/K49 -> 0.47998071 | ... AB13: =AB86/AB49 -> 0.42999002
B14: Jawa Tengah | C14: share | D14: =D87/D50 -> 0.21649265 | E14: =E87/E50 -> 0.18680279 | F14: =F87/F50 -> 0.1728149 | G14: =G87/G50 -> 0.18270503 | H14: =H87/H50 -> 0.18232158 | I14: =I87/I50 -> 0.18990523 | J14: =J87/J50 -> 0.17428284 | K14: =K87/K50 -> 0.16725214 | ... AB14: =AB87/AB50 -> 0.15719542
B15: Jawa Timur | C15: share | D15: =D88/D51 -> 0.40325862 | E15: =E88/E51 -> 0.38049599 | F15: =F88/F51 -> 0.34706734 | G15: =G88/G51 -> 0.33749974 | H15: =H88/H51 -> 0.34597638 | I15: =I88/I51 -> 0.37283348 | J15: =J88/J51 -> 0.37435515 | K15: =K88/K51 -> 0.37084858 | ... AB15: =AB88/AB51 -> 0.48602219
B16: Kalimantan Barat | C16: share | D16: =D89/D52 -> 0.20516969 | E16: =E89/E52 -> 0.18525409 | F16: =F89/F52 -> 0.15910445 | G16: =G89/G52 -> 0.1689621 | H16: =H89/H52 -> 0.15977412 | I16: =I89/I52 -> 0.15661973 | J16: =J89/J52 -> 0.17607001 | K16: =K89/K52 -> 0.14580523 | ... AB16: =AB89/AB52 -> 0.14344349
... B19: Kalimantan Timur | C19: share | D19: =D92/D55 -> 0.38582013 | E19: =E92/E55 -> 0.4031418 | F19: =F92/F55 -> 0.39162042 | G19: =G92/G55 -> 0.42167338 | H19: =H92/H55 -> 0.46741642 | I19: =I92/I55 -> 0.53143522 | J19: =J92/J55 -> 0.57013057 | K19: =K92/K55 -> 0.58231853 | ... AB19: =AB92/AB55 -> 0.59686989
B20: Kalimantan Utara | C20: share | N20: =N93/N56 -> 0.45279992 | O20: =O93/O56 -> 0.44453237 | P20: =P93/P56 -> 0.448904 | Q20: =Q93/Q56 -> 0.448606 | R20: =R93/R56 -> 0.4529406 | S20: =S93/S56 -> 0.44359872 | T20: =T93/T56 -> 0.44575422 | U20: =U93/U56 -> 0.43518154 | ... AB20: =AB93/AB56 -> 0.55716261
B21: Kep. Bangka Belitung | C21: share | D21: =D94/D57 -> 0.24576445 | E21: =E94/E57 -> 0.28153057 | F21: =F94/F57 -> 0.24136502 | G21: =G94/G57 -> 0.23802515 | H21: =H94/H57 -> 0.50005072 | I21: =I94/I57 -> 0.5578309 | J21: =J94/J57 -> 0.55675633 | K21: =K94/K57 -> 0.5281956 | ... AB21: =AB94/AB57 -> 0.24169882
B22: Kep. Riau | C22: share | G22: =G95/G58 -> 0.64534568 | H22: =H95/H58 -> 0.89525311 | I22: =I95/I58 -> 1.044989 | J22: =J95/J58 -> 0.99891127 | K22: =K95/K58 -> 1.0881082 | L22: =L95/L58 -> 1.2032722 | M22: =M95/M58 -> 1.2516054 | N22: =N95/N58 -> 1.3278403 | ... AB22: =AB95/AB58 -> 1.418459
B23: Lampung | C23: share | D23: =D96/D59 -> 0.42927958 | E23: =E96/E59 -> 0.40022736 | F23: =F96/F59 -> 0.4304018 | G23: =G96/G59 -> 0.43129792 | H23: =H96/H59 -> 0.32348493 | I23: =I96/I59 -> 0.34186891 | J23: =J96/J59 -> 0.34813772 | K23: =K96/K59 -> 0.33995117 | ... AB23: =AB96/AB59 -> 0.53193431
B24: Maluku | C24: share | D24: =D97/D60 -> 0.44976657 | E24: =E97/E60 -> 0.61154851 | F24: =F97/F60 -> 0.61771438 | G24: =G97/G60 -> 0.59696848 | H24: =H97/H60 -> 0.56576607 | I24: =I97/I60 -> 0.54641945 | J24: =J97/J60 -> 0.56957142 | K24: =K97/K60 -> 0.57745868 | ... AB24: =AB97/AB60 -> 0.15723409
B25: Maluku Utara | C25: share | D25: =D98/D61 -> 0.5084237 | E25: =E98/E61 -> 0.38778618 | F25: =F98/F61 -> 0.41613068 | G25: =G98/G61 -> 0.38325338 | H25: =H98/H61 -> 0.43719309 | I25: =I98/I61 -> 0.44797299 | J25: =J98/J61 -> 0.46643479 | K25: =K98/K61 -> 0.36887581 | ... AB25: =AB98/AB61 -> 2.5370906
B26: Nusa Tenggara Barat | C26: share | D26: =D99/D62 -> 0.54487114 | E26: =E99/E62 -> 0.51174561 | F26: =F99/F62 -> 0.50970572 | G26: =G99/G62 -> 0.49488789 | H26: =H99/H62 -> 0.51041466 | I26: =I99/I62 -> 0.56322056 | J26: =J99/J62 -> 0.57686099 | K26: =K99/K62 -> 0.57796961 | ... AB26: =AB99/AB62 -> 0.41265728
B27: Nusa Tenggara Timur | C27: share | D27: =D100/D63 -> 0.3084738 | E27: =E100/E63 -> 0.34898538 | F27: =F100/F63 -> 0.36683717 | G27: =G100/G63 -> 0.35037946 | H27: =H100/H63 -> 0.39949558 | I27: =I100/I63 -> 0.44576877 | J27: =J100/J63 -> 0.47438564 | K27: =K100/K63 -> 0.49695799 | ... AB27: =AB100/AB63 -> 0.50416648
B28: Papua | C28: share | D28: =D101/D64 -> 0.056655697 | E28: =E101/E64 -> 0.04895975 | F28: =F101/F64 -> 0.049427395 | G28: =G101/G64 -> 0.053661004 | H28: =H101/H64 -> 0.070087134 | I28: =I101/I64 -> 0.058054736 | J28: =J101/J64 -> 0.085868166 | K28: =K101/K64 -> 0.076646993 | ... AB28: =AB101/AB64 -> 0.42008968
B29: Papua Barat | C29: share | F29: =F102/F65 -> 0.98041493 | G29: =G102/G65 -> 0.84208442 | H29: =H102/H65 -> 0.74016999 | I29: =I102/I65 -> 0.83230986 | J29: =J102/J65 -> 0.93844174 | K29: =K102/K65 -> 0.89035395 | L29: =L102/L65 -> 0.79236112 | M29: =M102/M65 -> 0.5306499 | ... AB29: =AB102/AB65 -> 0.2688619
B30: Riau | C30: share | D30: =D103/D66 -> 0.14390886 | E30: =E103/E66 -> 0.13670843 | F30: =F103/F66 -> 0.13215371 | G30: =G103/G66 -> 0.13731425 | H30: =H103/H66 -> 0.14281107 | I30: =I103/I66 -> 0.15314207 | J30: =J103/J66 -> 0.16066511 | K30: =K103/K66 -> 0.1702624 | ... AB30: =AB103/AB66 -> 0.32048683
B31: Sulawesi Barat | C31: share | I31: =I104/I67 -> 0.4476623 | J31: =J104/J67 -> 0.49524264 | K31: =K104/K67 -> 0.55933451 | L31: =L104/L67 -> 0.61170597 | M31: =M104/M67 -> 0.63233642 | N31: =N104/N67 -> 0.63210353 | O31: =O104/O67 -> 0.63772883 | P31: =P104/P67 -> 0.61431834 | ... AB31: =AB104/AB67 -> 0.35006489
B32: Sulawesi Selatan | C32: share | D32: =D105/D68 -> 0.18023939 | E32: =E105/E68 -> 0.25203213 | F32: =F105/F68 -> 0.18412143 | G32: =G105/G68 -> 0.17318501 | H32: =H105/H68 -> 0.28294491 | I32: =I105/I68 -> 0.34333542 | J32: =J105/J68 -> 0.32037806 | K32: =K105/K68 -> 0.40828799 | ... AB32: =AB105/AB68 -> 0.11527465
B33: Sulawesi Tengah | C33: share | D33: =D106/D69 -> 0.37843301 | E33: =E106/E69 -> 0.36853842 | F33: =F106/F69 -> 0.36035932 | G33: =G106/G69 -> 0.34486699 | H33: =H106/H69 -> 0.33111118 | I33: =I106/I69 -> 0.31823594 | J33: =J106/J69 -> 0.30980837 | K33: =K106/K69 -> 0.48969235 | ... AB33: =AB106/AB69 -> 1.0734582
B34: Sulawesi Tenggara | C34: share | D34: =D107/D70 -> 0.18036802 | E34: =E107/E70 -> 0.18882004 | F34: =F107/F70 -> 0.18730713 | G34: =G107/G70 -> 0.19355181 | H34: =H107/H70 -> 0.24639377 | I34: =I107/I70 -> 0.27089933 | J34: =J107/J70 -> 0.35584094 | K34: =K107/K70 -> 0.34859304 | ... AB34: =AB107/AB70 -> 0.46528073
B35: Sulawesi Utara | C35: share | D35: =D108/D71 -> 0.22204444 | E35: =E108/E71 -> 0.12259482 | F35: =F108/F71 -> 0.12406007 | G35: =G108/G71 -> 0.1625203 | H35: =H108/H71 -> 0.26211821 | I35: =I108/I71 -> 0.29069943 | J35: =J108/J71 -> 0.26755748 | K35: =K108/K71 -> 0.27122233 | ... AB35: =AB108/AB71 -> 0.21873911
B36: Sumatera Barat | C36: share | D36: =D109/D72 -> 0.34119292 | E36: =E109/E72 -> 0.28434227 | F36: =F109/F72 -> 0.26686018 | G36: =G109/G72 -> 0.3213419 | H36: =H109/H72 -> 0.3057362 | I36: =I109/I72 -> 0.39826231 | J36: =J109/J72 -> 0.40938767 | K36: =K109/K72 -> 0.52853235 | ... AB36: =AB109/AB72 -> 0.48536262
B37: Sumatera Selatan | C37: share | D37: =D110/D73 -> 0.33243838 | E37: =E110/E73 -> 0.32887945 | F37: =F110/F73 -> 0.33718245 | G37: =G110/G73 -> 0.30035556 | H37: =H110/H73 -> 0.31676061 | I37: =I110/I73 -> 0.32635569 | J37: =J110/J73 -> 0.32389747 | K37: =K110/K73 -> 0.3402954 | ... AB37: =AB110/AB73 -> 0.29896317
B38: Sumatera Utara | C38: share | D38: =D111/D74 -> 0.23037669 | E38: =E111/E74 -> 0.23213838 | F38: =F111/F74 -> 0.23206863 | G38: =G111/G74 -> 0.21530603 | H38: =H111/H74 -> 0.2497986 | I38: =I111/I74 -> 0.27170521 | J38: =J111/J74 -> 0.28311359 | K38: =K111/K74 -> 0.31906705 | ... AB38: =AB111/AB74 -> 0.32494246
B40: provname | C40: indicator | D40: 2000 | E40: 2001 | F40: 2002 | G40: 2003 | H40: 2004 | I40: 2005 | J40: 2006 | K40: 2007 | L40: 2008 | M40: 2009 | N40: 2010 | O40: 2011 | P40: 2012 | Q40: 2013 | R40: 2014 | S40: 2015 | T40: 2016 | U40: 2017 | V40: 2018 | W40: 2019 | X40: 2020 | Y40: 2021 | Z40: 2022 | AA40: 2023 | AB40: 2024
B41: Aceh | C41: rdgp_ceic | D41: 110073.1 | E41: 108170.82 | F41: 129876.08 | G41: 137049.26 | H41: 123849.98 | I41: 111314.86 | J41: 113050.95 | K41: 110379.79 | L41: 104597.17 | M41: 98833.537 | N41: 101545.24 | O41: 104874.21 | P41: 108914.9 | Q41: 111755.83 | R41: 113490.36 | S41: 112665.53 | T41: 116374.3 | U41: 121240.98 | V41: 126824.37 | W41: 132069.62 | X41: 131580.97 | Y41: 135274.04 | Z41: 140971.72 | AA41: 146932.5 | AB41: 153780.49
B42: Bali | C42: rdgp_ceic | D42: 56050.74 | E42: 58036.078 | F42: 59801.795 | G42: 61934.458 | H42: 64798.46 | I42: 68398.803 | J42: 72008.991 | K42: 79361.599 | L42: 84102.023 | M42: 88583.362 | N42: 93749.35 | O42: 99991.632 | P42: 106951.46 | Q42: 114103.58 | R42: 121787.57 | S42: 129126.56 | T42: 137296.45 | U42: 144933.31 | V42: 154072.66 | W42: 162693.36 | X42: 147498.94 | Y42: 143871.68 | Z42: 150830.77 | AA42: 159464.3 | AB42: 168198.68
B43: Banten | C43: rdgp_ceic | D43: 138907.81 | E43: 145601.68 | F43: 151591.67 | G43: 159280.6 | H43: 168241.18 | I43: 178132.46 | J43: 188048.78 | K43: 230991.51 | L43: 244330.14 | M43: 255835.47 | N43: 271465.28 | O43: 290545.84 | P43: 310385.59 | Q43: 331099.11 | R43: 349351.23 | S43: 368377.2 | T43: 387835.09 | U43: 410137 | V43: 433782.71 | W43: 456620.03 | X43: 441148.58 | Y43: 460952.79 | Z43: 484129.42 | AA43: 507425.73 | AB43: 531735.25
B44: Bengkulu | C44: rdgp_ceic | D44: 16550.039 | E44: 17236.785 | F44: 18052.424 | G44: 19021.376 | H44: 20045.454 | I44: 21211.919 | J44: 22474.093 | K44: 23925.008 | L44: 25300.078 | M44: 26721.308 | N44: 28352.572 | O44: 30295.054 | P44: 32363.038 | Q44: 34326.372 | R44: 36207.146 | S44: 38066.006 | T44: 40076.544 | U44: 42073.516 | V44: 44164.11 | W44: 46345.454 | X44: 46338.431 | Y44: 47853.777 | Z44: 49916.061 | AA44: 52051.6 | AB44: 54454.65
B45: DI Yogyakarta | C45: rdgp_ceic | D45: 41432.689 | E45: 43198.331 | F45: 45141.443 | G45: 47210.294 | H45: 49626.114 | I45: 52064.2 | J45: 53894.999 | K45: 56219.054 | L45: 59049.658 | M45: 61667.594 | N45: 64678.968 | O45: 68049.874 | P45: 71702.449 | Q45: 75627.45 | R45: 79536.082 | S45: 83474.452 | T45: 87685.81 | U45: 92300.244 | V45: 98024.014 | W45: 104485.46 | X45: 101698.52 | Y45: 107372.56 | Z45: 112901.32 | AA45: 118625.55 | AB45: 124590.45
B46: DKI Jakarta | C46: rdgp_ceic | D46: 619429.61 | E46: 648596.02 | F46: 680325.23 | G46: 716451.86 | H46: 756947.18 | I46: 802457.04 | J46: 850169.45 | K46: 904916.3 | L46: 961314.4 | M46: 1009543 | N46: 1075183.5 | O46: 1147558.2 | P46: 1222527.9 | Q46: 1296694.6 | R46: 1373389.1 | S46: 1454563.8 | T46: 1539916.9 | U46: 1635359.1 | V46: 1735208.3 | W46: 1836240.5 | X46: 1792291.1 | Y46: 1856000.7 | Z46: 1953489 | AA46: 2050474.5 | AB46: 2151198.8
B47: Gorontalo | C47: rdgp_ceic | D47: 7814.9388 | E47: 8248.2965 | F47: 8780.6325 | G47: 9384.5995 | H47: 10034.796 | I47: 10755.989 | J47: 11541.54 | K47: 12408.302 | L47: 13370.827 | M47: 14379.016 | N47: 15475.737 | O47: 16669.09 | P47: 17987.075 | Q47: 19367.573 | R47: 20775.803 | S47: 22068.803 | T47: 23507.209 | U47: 25090.131 | V47: 26719.272 | W47: 28429.97 | X47: 28425.375 | Y47: 29107.911 | Z47: 30282.215 | AA47: 31643.78 | AB47: 32951.94
B48: Jambi | C48: rdgp_ceic | D48: 49631.702 | E48: 52932.186 | F48: 56032.89 | G48: 58832.901 | H48: 61999.862 | I48: 65454.578 | J48: 69311.572 | K48: 74039.36 | L48: 79343.211 | M48: 84411.218 | N48: 90618.411 | O48: 97740.874 | P48: 104615.08 | Q48: 111766.13 | R48: 119991.44 | S48: 125037.4 | T48: 130501.13 | U48: 136501.71 | V48: 142902 | W48: 149111.09 | X48: 148354.25 | Y48: 153850.63 | Z48: 161731.95 | AA48: 169259.05 | AB48: 176868.44
B49: Jawa Barat | C49: rdgp_ceic | D49: 550817.39 | E49: 572247.51 | F49: 590149.68 | G49: 645510.22 | H49: 647192.68 | I49: 683436 | J49: 724561.85 | K49: 771499.09 | L49: 819406.18 | M49: 853733.36 | N49: 906685.76 | O49: 965622.06 | P49: 1028409.7 | Q49: 1093543.5 | R49: 1149216.1 | S49: 1207232.3 | T49: 1275619.2 | U49: 1343662.1 | V49: 1419624.1 | W49: 1490959.7 | X49: 1453380.7 | Y49: 1507746.4 | Z49: 1589984.9 | AA49: 1669406.4 | AB49: 1752124.2
B50: Jawa Tengah | C50: rdgp_ceic | D50: 382285.34 | E50: 396000.45 | F50: 410072.32 | G50: 430495.93 | H50: 452570.94 | I50: 476772.1 | J50: 502206.75 | K50: 530294.91 | L50: 560038.27 | M50: 588830.9 | N50: 623224.62 | O50: 656268.13 | P50: 691343.12 | Q50: 726655.12 | R50: 764959.15 | S50: 806765.09 | T50: 849099.35 | U50: 893750.3 | V50: 941091.14 | W50: 991516.54 | X50: 965227.27 | Y50: 997321.13 | Z50: 1050278.1 | AA50: 1102437.5 | AB50: 1156998.9
B51: Jawa Timur | C51: rdgp_ceic | D51: 587042.53 | E51: 609092.46 | F51: 632257.57 | G51: 662450.68 | H51: 701072.91 | I51: 742014.6 | J51: 785064.59 | K51: 834716.49 | L51: 884307.79 | M51: 928655.01 | N51: 990648.84 | O51: 1054401.8 | P51: 1124464.6 | Q51: 1192789.8 | R51: 1262684.5 | S51: 1331376.1 | T51: 1405563.5 | U51: 1482299.6 | V51: 1563441.8 | W51: 1649895.6 | X51: 1611392.5 | Y51: 1668754.4 | Z51: 1757874.9 | AA51: 1844808.7 | AB51: 1935810.2
... B55: Kalimantan Timur | C55: rdgp_ceic | D55: 284816.54 | E55: 298292.88 | F55: 303482.61 | G55: 309124.36 | H55: 314537.24 | I55: 324512.47 | J55: 333752.8 | K55: 339879.57 | L55: 356532.14 | M55: 364678.17 | N55: 383293 | O55: 407435.38 | P55: 428877.71 | Q55: 438532.91 | R55: 446029.05 | S55: 440676.36 | T55: 439003.83 | U55: 452741.91 | V55: 464694.43 | W55: 486523.18 | X55: 472393.33 | Y55: 484439.61 | Z55: 506158.91 | AA55: 537630.01 | AB55: 570824
B56: Kalimantan Utara | C56: rdgp_ceic | N56: 34918.578 | O56: 37829.039 | P56: 40768.541 | Q56: 44091.699 | R56: 47696.355 | S56: 49315.745 | T56: 51064.737 | U56: 54537.307 | V56: 57459.309 | W56: 61417.792 | X56: 60746.209 | Y56: 63168.434 | Z56: 66528.388 | AA56: 69831.48 | AB56: 73134.41
B57: Kep. Bangka Belitung | C57: rdgp_ceic | D57: 18820.781 | E57: 21111.409 | F57: 23782.013 | G57: 26618.559 | H57: 27492.345 | I57: 28447.407 | J57: 29579.774 | K57: 30921.329 | L57: 32343.768 | M57: 33553.175 | N57: 35561.904 | O57: 38013.99 | P57: 40104.906 | Q57: 42190.857 | R57: 44159.44 | S57: 45962.304 | T57: 47848.372 | U57: 49985.154 | V57: 52208.035 | W57: 53941.902 | X57: 52705.936 | Y57: 55369.646 | Z57: 57804.209 | AA57: 60336.31 | AB57: 60801.87
B58: Kep. Riau | C58: rdgp_ceic | G58: 72502.481 | H58: 77195.765 | I58: 82265.887 | J58: 87842.524 | K58: 93996.764 | L58: 100227.12 | M58: 103758.29 | N58: 111223.67 | O58: 118961.42 | P58: 128034.97 | Q58: 137263.85 | R58: 146325.23 | S58: 155131.35 | T58: 162853.04 | U58: 166081.68 | V58: 173498.75 | W58: 181877.67 | X58: 174959.21 | Y58: 180952.44 | Z58: 190111.09 | AA58: 199912.82 | AB58: 209939.07
B59: Lampung | C59: rdgp_ceic | D59: 91243.844 | E59: 94437.498 | F59: 99746.43 | G59: 105491.12 | H59: 110841.5 | I59: 115292.68 | J59: 121034.76 | K59: 128225.66 | L59: 135082.15 | M59: 142193.09 | N59: 150560.84 | O59: 160437.5 | P59: 170769.21 | Q59: 180620.01 | R59: 189797.49 | S59: 199536.92 | T59: 209793.73 | U59: 220626.1 | V59: 232165.99 | W59: 244378.31 | X59: 240319.59 | Y59: 246966.49 | Z59: 257534.19 | AA59: 269240.54 | AB59: 281557.23
B60: Maluku | C60: rdgp_ceic | D60: 12004.061 | E60: 11999.861 | F60: 12344.249 | G60: 12876.236 | H60: 13446.39 | I60: 14128.023 | J60: 14912.049 | K60: 15750.222 | L60: 16416.889 | M60: 17309.277 | N60: 18428.585 | O60: 19597.39 | P60: 21000.079 | Q60: 22100.937 | R60: 23567.734 | S60: 24859.197 | T60: 26284.228 | U60: 27814.053 | V60: 29457.133 | W60: 31049.449 | X60: 30765.889 | Y60: 31881.23 | Z60: 33575.072 | AA60: 35322.91 | AB60: 37210.06
B61: Maluku Utara | C61: rdgp_ceic | D61: 9277.8138 | E61: 9432.8777 | F61: 9663.2549 | G61: 10032.743 | H61: 10504.308 | I61: 11040.802 | J61: 11646.371 | K61: 15944.264 | L61: 14983.912 | M61: 13880.18 | N61: 14983.912 | O61: 16002.452 | P61: 17120.07 | Q61: 18208.743 | R61: 19208.761 | S61: 20380.304 | T61: 21556.68 | U61: 23210.865 | V61: 25034.082 | W61: 26597.553 | X61: 28031.444 | Y61: 32738.67 | Z61: 40248.383 | AA61: 48929.43 | AB61: 55740.95
B62: Nusa Tenggara Barat | C62: rdgp_ceic | D62: 42557.028 | E62: 45712.892 | F62: 47316.99 | G62: 49164.48 | H62: 52150.784 | I62: 53043.779 | J62: 54505.263 | K62: 57185.018 | L62: 58800.32 | M62: 65936.745 | N62: 70122.726 | O62: 67379.141 | P62: 66340.812 | Q62: 69766.714 | R62: 73372.964 | S62: 89337.986 | T62: 94524.29 | U62: 94608.209 | V62: 90349.129 | W62: 93872.439 | X62: 93288.874 | Y62: 95437.864 | Z62: 102073.66 | AA62: 103906.21 | AB62: 109415.25
B63: Nusa Tenggara Timur | C63: rdgp_ceic | D63: 27435.094 | E63: 28731.427 | F63: 30132.49 | G63: 31640.213 | H63: 33328.718 | I63: 34482.683 | J63: 36234.161 | K63: 38099.964 | L63: 39942.925 | M63: 41658.196 | N63: 43846.609 | O63: 46334.128 | P63: 48863.188 | Q63: 51505.189 | R63: 54107.974 | S63: 56770.793 | T63: 59678.012 | U63: 62725.41 | V63: 65929.194 | W63: 69389.016 | X63: 68809.614 | Y63: 70540.557 | Z63: 72711.277 | AA63: 75246.66 | AB63: 78161.59
B64: Papua | C64: rdgp_ceic | D64: 110227.63 | E64: 119310.28 | F64: 104272.72 | G64: 103978.32 | H64: 80548.161 | I64: 109863.86 | J64: 91030.535 | K64: 94979.532 | L64: 93651.542 | M64: 114460.66 | N64: 110808.18 | O64: 106066.72 | P64: 107890.94 | Q64: 117118.82 | R64: 121391.23 | S64: 130311.6 | T64: 142224.93 | U64: 148818.29 | V64: 159711.85 | W64: 134565.89 | X64: 137787.29 | Y64: 158675.15 | Z64: 298258.97 | AA64: 181926.24 | AB64: 189919.9
B65: Papua Barat | C65: rdgp_ceic | F65: 18987.336 | G65: 20445.294 | H65: 21955.659 | I65: 23449.588 | J65: 24516.927 | K65: 26219.825 | L65: 28275.291 | M65: 32196.343 | N65: 41361.672 | O65: 42867.187 | P65: 44423.335 | Q65: 47694.235 | R65: 50259.908 | S65: 52346.486 | T65: 54711.282 | U65: 56907.959 | V65: 60465.521 | W65: 62074.519 | X65: 61604.125 | Y65: 61289.4 | Z65: 62530.526 | AA65: 64975.01 | AB65: 74359.96
B66: Riau | C66: rdgp_ceic | D66: 376739.47 | E66: 375243.33 | F66: 385146.72 | G66: 290544.12 | H66: 299047.43 | I66: 315232.43 | J66: 331466.78 | K66: 342767.59 | L66: 362138.23 | M66: 372876.31 | N66: 388578.23 | O66: 410215.84 | P66: 425626 | Q66: 436187.51 | R66: 447986.78 | S66: 448991.96 | T66: 458769.34 | U66: 470983.51 | V66: 482064.63 | W66: 495607.05 | X66: 489995.75 | Y66: 506471.91 | Z66: 529532.98 | AA66: 551828.48 | AB66: 571233.59
B67: Sulawesi Barat | C67: rdgp_ceic | I67: 11254.052 | J67: 12030.822 | K67: 12924.367 | L67: 14484.52 | M67: 15357.391 | N67: 17183.832 | O67: 19027.504 | P67: 20786.886 | Q67: 22227.393 | R67: 24195.655 | S67: 25964.432 | T67: 27524.767 | U67: 29282.487 | V67: 31114.143 | W67: 32843.808 | X67: 32074.019 | Y67: 32898.298 | Z67: 33643.019 | AA67: 35402.49 | AB67: 37087.41
B68: Sulawesi Selatan | C68: rdgp_ceic | D68: 103190 | E68: 108423.41 | F68: 112857.31 | G68: 118778.3 | H68: 125087.19 | I68: 122170.26 | J68: 130374.55 | K68: 138642.1 | L68: 149434.28 | M68: 158746.72 | N68: 171740.74 | O68: 185708.47 | P68: 202184.59 | Q68: 217589.13 | R68: 233988.05 | S68: 250802.99 | T68: 269401.31 | U68: 288814.17 | V68: 309156.19 | W68: 330506.38 | X68: 328154.57 | Y68: 343395.41 | Z68: 360912.82 | AA68: 377207.79 | AB68: 396141.74
B69: Sulawesi Tengah | C69: rdgp_ceic | D69: 25397.748 | E69: 26691.836 | F69: 28190.752 | G69: 29941.995 | H69: 32081.809 | I69: 34509.563 | J69: 37209.061 | K69: 40995.863 | L69: 44185.651 | M69: 47592.395 | N69: 51752.071 | O69: 56833.829 | P69: 62249.529 | Q69: 68219.319 | R69: 71677.531 | S69: 82787.202 | T69: 91014.565 | U69: 97474.859 | V69: 117555.83 | W69: 127935.06 | X69: 134152.69 | Y69: 149815.86 | Z69: 172624.82 | AA69: 193181.37 | AB69: 212281.54
B70: Sulawesi Tenggara | C70: rdgp_ceic | D70: 23983.362 | E70: 25185.024 | F70: 26863.237 | G70: 28896.652 | H70: 31066.78 | I70: 33337.241 | J70: 35897.588 | K70: 38756.618 | L70: 41576.095 | M70: 44724.192 | N70: 48401.152 | O70: 53546.69 | P70: 59785.399 | Q70: 64268.714 | R70: 68291.785 | S70: 72993.328 | T70: 77745.512 | U70: 83001.687 | V70: 88310.048 | W70: 94053.524 | X70: 93445.72 | Y70: 97275.325 | Z70: 102656.43 | AA70: 108152.98 | AB70: 113989.49
B71: Sulawesi Utara | C71: rdgp_ceic | D71: 29734.554 | E71: 30759.461 | F71: 31779.675 | G71: 32796.635 | H71: 34194.613 | I71: 35869.37 | J71: 37919.583 | K71: 40371.852 | L71: 44756.178 | M71: 48267.395 | N71: 51721.334 | O71: 54910.897 | P71: 58677.587 | Q71: 62422.498 | R71: 66360.757 | S71: 70425.33 | T71: 74764.66 | U71: 79484.025 | V71: 84249.72 | W71: 89009.265 | X71: 88126.374 | Y71: 91790.692 | Z71: 96768.152 | AA71: 102070.48 | AB71: 107575.01
B72: Sumatera Barat | C72: rdgp_ceic | D72: 61854.941 | E72: 64118.832 | F72: 67126.005 | G72: 70656.833 | H72: 74524.804 | I72: 78798.093 | J72: 83636.492 | K72: 88941.199 | L72: 95058.331 | M72: 99129.656 | N72: 105017.74 | O72: 111679.49 | P72: 118724.42 | Q72: 125940.63 | R72: 133340.84 | S72: 140719.47 | T72: 148134.24 | U72: 155984.36 | V72: 163996.19 | W72: 172205.57 | X72: 169426.61 | Y72: 174999.89 | Z72: 182628.34 | AA72: 191069.34 | AB72: 199419.97
B73: Sumatera Selatan | C73: rdgp_ceic | D73: 125529.24 | E73: 128627.02 | F73: 132594.36 | G73: 137467.91 | H73: 143838.88 | I73: 150793.6 | J73: 158636 | K73: 167894.01 | L73: 176410.95 | M73: 183664.48 | N73: 194012.97 | O73: 206360.7 | P73: 220459.2 | Q73: 232175.05 | R73: 243297.77 | S73: 254044.88 | T73: 266857.4 | U73: 281571.01 | V73: 298484.07 | W73: 315464.75 | X73: 315129.22 | Y73: 326405.18 | Z73: 343503.62 | AA73: 360967.45 | AB73: 379119.64
B74: Sumatera Utara | C74: rdgp_ceic | D74: 192858.13 | E74: 200539.22 | F74: 209688.72 | G74: 219774.38 | H74: 232389.15 | I74: 245130.81 | J74: 260328.77 | K74: 278302.34 | L74: 296095.23 | M74: 311118.21 | N74: 331085.24 | O74: 353147.59 | P74: 375924.14 | Q74: 398727.14 | R74: 419573.31 | S74: 440955.85 | T74: 463775.46 | U74: 487531.23 | V74: 512762.63 | W74: 539513.85 | X74: 533746.36 | Y74: 547651.82 | Z74: 573528.77 | AA74: 602235.94 | AB74: 632534.73
B76: Step 3: New dataset
B78: Aceh | C78: impr_ceic | D78: =D116*$E155 -> 47068.681 | E78: =E116*$E155 -> 52728.691 | F78: =F116*$E155 -> 10003.4 | G78: =G116*$E155 -> 19050.714 | H78: =H116*$E155 -> 12248.278 | I78: =I116*$E155 -> 96285.816 | J78: =J116*$E155 -> 7660.7526 | K78: =K116*$E155 -> 46901.499 | ... M78: =M116*$E155 -> 56505.589 | N78: 54431.948 | O78: 61765.897 | P78: 69320.8 | Q78: 56583.797 | R78: 57795.662 | S78: 60839.483 | T78: 58843.343 | U78: 60748.801 | V78: 61855.802 | W78: 63730.357 | X78: 63339.227 | Y78: 64572.076 | Z78: 74111.39 | AA78: 82596.23 | AB78: 89266.36
B79: Bali | C79: impr_ceic | D79: =D117*$E156 -> 2809.8629 | E79: =E117*$E156 -> 2815.6951 | F79: =F117*$E156 -> 2914.3414 | G79: =G117*$E156 -> 3058.1912 | H79: =H117*$E156 -> 5457.7954 | I79: =I117*$E156 -> 6325.6776 | J79: =J117*$E156 -> 5669.435 | K79: =K117*$E156 -> 7383.0606 | ... M79: =M117*$E156 -> 11970.652 | N79: 13334.406 | O79: 11705.052 | P79: 6025.5788 | Q79: 8053.885 | R79: 10276.551 | S79: 9263.655 | T79: 11369.063 | U79: 13317.177 | V79: 16568.491 | W79: 14315.441 | X79: 3123.4214 | Y79: 549.11828 | Z79: 4036.9927 | AA79: 8027.55 | AB79: 9109.8
B80: Banten | C80: impr_ceic | D80: =D118*$E157 -> 100665.85 | E80: =E118*$E157 -> 98707.85 | F80: =F118*$E157 -> 109587.3 | G80: =G118*$E157 -> 121482.57 | H80: =H118*$E157 -> 136147.44 | I80: =I118*$E157 -> 149117.06 | J80: =J118*$E157 -> 166071.37 | K80: =K118*$E157 -> 207069.17 | ... M80: =M118*$E157 -> 194922.85 | N80: 225555.17 | O80: 239024.93 | P80: 263272.9 | Q80: 249609.38 | R80: 257091 | S80: 265819.42 | T80: 271158.56 | U80: 303354.78 | V80: 310806.38 | W80: 306020.48 | X80: 296049.52 | Y80: 321165 | Z80: 342844.84 | AA80: 340277.99 | AB80: 369862.47
B81: Bengkulu | C81: impr_ceic | D81: =D119*$E158 -> 10043.581 | E81: =E119*$E158 -> 9977.3848 | F81: =F119*$E158 -> 10230.905 | G81: =G119*$E158 -> 10488.298 | H81: =H119*$E158 -> 11688.342 | I81: =I119*$E158 -> 13281.511 | J81: =J119*$E158 -> 13983.841 | K81: =K119*$E158 -> 15409.393 | ... M81: =M119*$E158 -> 16858.245 | N81: 18092.75 | O81: 20334.386 | P81: 22407.652 | Q81: 22916.774 | R81: 24205.031 | S81: 25676.344 | T81: 26796.021 | U81: 28895.269 | V81: 29562.645 | W81: 30477.643 | X81: 29823.348 | Y81: 30857.961 | Z81: 32101.013 | AA81: 33033.715 | AB81: 34078.352
B82: DI Yogyakarta | C82: impr_ceic | D82: =D120*$E159 -> 887.07303 | E82: =E120*$E159 -> 963.84718 | F82: =F120*$E159 -> 1022.2713 | G82: =G120*$E159 -> 1106.8434 | H82: =H120*$E159 -> 1160.4015 | I82: =I120*$E159 -> 1213.2191 | J82: =J120*$E159 -> 1262.9583 | K82: =K120*$E159 -> 1326.9174 | ... M82: =M120*$E159 -> 1451.1644 | N82: 1520.5198 | O82: 1506.2006 | P82: 1901.8464 | Q82: 2241.6256 | R82: 3228.5405 | S82: 3728.7494 | T82: 4492.5106 | U82: 4905.2219 | V82: 5102.3907 | W82: 4503.1881 | X82: 3833.5659 | Y82: 4113.2565 | Z82: 4121.081 | AA82: 4283.5964 | AB82: 4502.4046
B83: DKI Jakarta | C83: impr_ceic | D83: =D121*$E160 -> 318223.76 | E83: =E121*$E160 -> 250671.02 | F83: =F121*$E160 -> 246132.12 | G83: =G121*$E160 -> 299773.32 | H83: =H121*$E160 -> 371693.19 | I83: =I121*$E160 -> 438711.16 | J83: =J121*$E160 -> 462595.04 | K83: =K121*$E160 -> 519939.98 | ... M83: =M121*$E160 -> 653307.09 | N83: 705332.42 | O83: 821351.34 | P83: 844132.83 | Q83: 825842.82 | R83: 831005.05 | S83: 812085.05 | T83: 803869.77 | U83: 1005586.3 | V83: 1286430.6 | W83: 1210887 | X83: 1079154.2 | Y83: 1213500.9 | Z83: 1314952.7 | AA83: 1384981.7 | AB83: 1524662.3
B84: Gorontalo | C84: impr_ceic | D84: =D122*$E161 -> 147.20436 | E84: =E122*$E161 -> 190.95193 | F84: =F122*$E161 -> 197.25507 | G84: =G122*$E161 -> 1650.3067 | H84: =H122*$E161 -> 2024.6582 | I84: =I122*$E161 -> 1231.9082 | J84: =J122*$E161 -> 3159.6112 | K84: =K122*$E161 -> 4016.9635 | ... M84: =M122*$E161 -> 6112.3628 | N84: 6433.17 | O84: 7080.25 | P84: 8339.28 | Q84: 8283.9 | R84: 9047.03 | S84: 9341.1 | T84: 9101.96 | U84: 9309.59 | V84: 10071.25 | W84: 10180.63 | X84: 9479.59 | Y84: 10215.75 | Z84: 10425.67 | AA84: 10702.43 | AB84: 11236.76
B85: Jambi | C85: impr_ceic | D85: =D123*$E162 -> 17783.503 | E85: =E123*$E162 -> 20141.554 | F85: =F123*$E162 -> 20219.399 | G85: =G123*$E162 -> 22447.578 | H85: =H123*$E162 -> 24569.779 | I85: =I123*$E162 -> 29043.282 | J85: =J123*$E162 -> 33032.109 | K85: =K123*$E162 -> 39214.281 | ... M85: =M123*$E162 -> 45827.439 | N85: 59114.622 | O85: 52687.607 | P85: 53859.406 | Q85: 52346.212 | R85: 53876.383 | S85: 58201.042 | T85: 58984.41 | U85: 65943.4 | V85: 71180.25 | W85: 73939.2 | X85: 63075.79 | Y85: 68455.4 | Z85: 68726.23 | AA85: 66118.21 | AB85: 68696.97
B86: Jawa Barat | C86: impr_ceic | D86: =D124*$E163 -> 194389.13 | E86: =E124*$E163 -> 253095.38 | F86: =F124*$E163 -> 369437.51 | G86: =G124*$E163 -> 402028.56 | H86: =H124*$E163 -> 438731.63 | I86: =I124*$E163 -> 447570.05 | J86: =J124*$E163 -> 399626.14 | K86: =K124*$E163 -> 370304.68 | ... M86: =M124*$E163 -> 318334.56 | N86: 346048.37 | O86: 398893.31 | P86: 464966.47 | Q86: 368279.95 | R86: 381830.5 | S86: 390857.05 | T86: 391197.34 | U86: 439013.45 | V86: 485078.85 | W86: 513431.14 | X86: 432249.84 | Y86: 511346.46 | Z86: 556591.43 | AA86: 654746.47 | AB86: 753395.91
B87: Jawa Tengah | C87: impr_ceic | D87: =D125*$E164 -> 82761.967 | E87: =E125*$E164 -> 73973.987 | F87: =F125*$E164 -> 70866.608 | G87: =G125*$E164 -> 78653.774 | H87: =H125*$E164 -> 82513.45 | I87: =I125*$E164 -> 90541.516 | J87: =J125*$E164 -> 87526.02 | K87: =K125*$E164 -> 88692.956 | ... M87: =M125*$E164 -> 93219.828 | N87: 97675.34 | O87: 105571.11 | P87: 112615.21 | Q87: 127813.41 | R87: 118498.48 | S87: 99894.366 | T87: 95528.922 | U87: 104677.13 | V87: 142739.9 | W87: 133171.99 | X87: 105879.99 | Y87: 143700.5 | Z87: 166454.64 | AA87: 161759.23 | AB87: 181874.93
B88: Jawa Timur | C88: impr_ceic | D88: =D126*$E165 -> 236729.96 | E88: =E126*$E165 -> 231757.24 | F88: =F126*$E165 -> 219435.95 | G88: =G126*$E165 -> 223576.93 | H88: =H126*$E165 -> 242554.67 | I88: =I126*$E165 -> 276647.89 | J88: =J126*$E165 -> 293892.97 | K88: =K126*$E165 -> 309553.42 | ... M88: =M126*$E165 -> 319352.26 | N88: 352137.22 | O88: 405636.82 | P88: 456290.37 | Q88: 474424.23 | R88: 557469.47 | S88: 550072.44 | T88: 595223.42 | U88: 658436.77 | V88: 717519.07 | W88: 728779.55 | X88: 697922.17 | Y88: 763819.49 | Z88: 843110.21 | AA88: 852969.36 | AB88: 940846.7
B89: Kalimantan Barat | C89: impr_ceic | D89: =D127*$E166 -> 11248.125 | E89: =E127*$E166 -> 10429.259 | F89: =F127*$E166 -> 9394.1048 | G89: =G127*$E166 -> 10287.282 | H89: =H127*$E166 -> 10193.846 | I89: =I127*$E166 -> 10461.636 | J89: =J127*$E166 -> 12261.815 | K89: =K127*$E166 -> 10765.969 | ... M89: =M127*$E166 -> 11916.237 | N89: 13450.179 | O89: 24014.772 | P89: 19166.052 | Q89: 20621.768 | R89: 12293.71 | S89: 12546.782 | T89: 9917.5027 | U89: 9243.3084 | V89: 10073.735 | W89: 10796.665 | X89: 8514.4359 | Y89: 7643.0195 | Z89: 7714.75 | AA89: 12545.1 | AB89: 23320.25
... B111: Sumatera Utara | C111: impr_ceic | D111: =D149*$E188 -> 44430.017 | E111: =E149*$E188 -> 46552.849 | F111: =F149*$E188 -> 48662.174 | G111: =G149*$E188 -> 47318.75 | H111: =H149*$E188 -> 58050.484 | I111: =I149*$E188 -> 66603.318 | J111: =J149*$E188 -> 73702.613 | K111: =K149*$E188 -> 88797.106 | ... M111: =M149*$E188 -> 107086 | N111: 122546.5 | O111: 130765.52 | P111: 143814.32 | Q111: 145391.15 | R111: 156672.44 | S111: 150276.35 | T111: 146923.82 | U111: 156909.03 | V111: 173072.38 | W111: 166432.47 | X111: 141711.05 | Y111: 167677.24 | Z111: 186490.73 | AA111: 182912.03 | AB111: 205537.39
B113: Step 2: Import SNA93 data
B115: provname | C115: indicator | D115: 2000 | E115: 2001 | F115: 2002 | G115: 2003 | H115: 2004 | I115: 2005 | J115: 2006 | K115: 2007 | L115: 2008 | M115: 2009
A116: =B116=B155 -> TRUE | B116: Aceh | C116: impr_ceic | D116: 2929.613 | E116: 3281.899 | F116: 622.624 | G116: 1185.74 | H116: 762.348 | I116: 5992.9484 | J116: 476.81473 | K116: 2919.2074 | L116: 3355.733 | M116: 3516.9779
A117: =B117=B156 -> TRUE | B117: Bali | C117: impr_ceic | D117: 4059.477 | E117: 4067.903 | F117: 4210.4197 | G117: 4418.243 | H117: 7885.0093 | I117: 9138.8598 | J117: 8190.7702 | K117: 10666.487 | L117: 14553.151 | M117: 17294.291
A118: =B118=B157 -> TRUE | B118: Banten | C118: impr_ceic | D118: 25261.523 | E118: 24770.175 | F118: 27500.312 | G118: 30485.361 | H118: 34165.427 | I118: 37420.079 | J118: 41674.669 | K118: 51962.832 | L118: 57476.725 | M118: 48914.783
A119: =B119=B158 -> TRUE | B119: Bengkulu | C119: impr_ceic | D119: 733.895 | E119: 729.058 | F119: 747.583 | G119: 766.391 | H119: 854.07942 | I119: 970.494 | J119: 1021.814 | K119: 1125.9805 | L119: 1250.0555 | M119: 1231.8497
A120: =B120=B159 -> TRUE | B120: DI Yogyakarta | C120: impr_ceic | D120: 5251.866 | E120: 5706.403 | F120: 6052.2994 | G120: 6553.0042 | H120: 6870.0918 | I120: 7182.7956 | J120: 7477.2738 | K120: 7855.9397 | L120: 8310.618 | M120: 8591.537
A121: =B121=B160 -> TRUE | B121: DKI Jakarta | C121: impr_ceic | D121: 109534.17 | E121: 86282.188 | F121: 84719.876 | G121: 103183.44 | H121: 127938.61 | I121: 151006.52 | J121: 159227.47 | K121: 178965.88 | L121: 228286.34 | M121: 224871.49
A122: =B122=B161 -> TRUE | B122: Gorontalo | C122: impr_ceic | D122: 31.061 | E122: 40.292 | F122: 41.622 | G122: 348.22459 | H122: 427.215 | I122: 259.94 | J122: 666.69686 | K122: 847.60332 | L122: 1087.7673 | M122: 1289.7451
A123: =B123=B162 -> TRUE | B123: Jambi | C123: impr_ceic | D123: 4115.027 | E123: 4660.67 | F123: 4678.683 | G123: 5194.2742 | H123: 5685.3424 | I123: 6720.492 | J123: 7643.4897 | K123: 9074.0181 | L123: 9827.2887 | M123: 10604.275
A124: =B124=B163 -> TRUE | B124: Jawa Barat | C124: impr_ceic | D124: 56746.514 | E124: 73884.175 | F124: 107847.03 | G124: 117361.08 | H124: 128075.53 | I124: 130655.66 | J124: 116659.76 | K124: 108100.18 | L124: 96365.583 | M124: 92928.943
A125: =B125=B164 -> TRUE | B125: Jawa Tengah | C125: impr_ceic | D125: 72602.947 | E125: 64893.691 | F125: 62167.742 | G125: 68999.034 | H125: 72384.936 | I125: 79427.558 | J125: 76782.213 | K125: 77805.908 | L125: 89267.443 | M125: 81777.107
A126: =B126=B165 -> TRUE | B126: Jawa Timur | C126: impr_ceic | D126: 106891.57 | E126: 104646.22 | F126: 99082.745 | G126: 100952.54 | H126: 109521.62 | I126: 124915.87 | J126: 132702.6 | K126: 139773.83 | L126: 144688.47 | M126: 144198.33
A127: =B127=B166 -> TRUE | B127: Kalimantan Barat | C127: impr_ceic | D127: 7018.697 | E127: 6507.734 | F127: 5861.8103 | G127: 6419.1426 | H127: 6360.8396 | I127: 6527.9372 | J127: 7651.2274 | K127: 6717.8372 | L127: 7865.6663 | M127: 7435.5908
... A130: =B130=B169 -> TRUE | B130: Kalimantan Timur | C130: impr_ceic | D130: 32774.16 | E130: 35865.939 | F130: 35447.093 | G130: 38876.835 | H130: 43848.781 | I130: 51435.529 | J130: 56751.943 | K130: 59029.235 | L130: 63046.114 | M130: 55503.68
A131: =B131=B170 -> TRUE | B131: Kalimantan Utara | C131: impr_ceic
A132: =B132=B171 -> TRUE | B132: Kep. Bangka Belitung | C132: impr_ceic | D132: 1438.223 | E132: 1848.044 | F132: 1784.812 | G132: 1970.0484 | H132: 4274.5989 | I132: 4934.1776 | J132: 5120.7024 | K132: 5078.348 | L132: 5056.7933 | M132: 5154.9245
A133: =B133=B172 -> TRUE | B133: Kep. Riau | C133: impr_ceic | G133: 8615.3835 | H133: 12725.318 | I133: 15829.268 | J133: 16157.012 | K133: 18832.775 | L133: 22206.415 | M133: 23912.201
A134: =B134=B173 -> TRUE | B134: Lampung | C134: impr_ceic | D134: 8510.354 | E134: 8212.116 | F134: 9327.7149 | G134: 9885.4644 | H134: 7790.4093 | I134: 8563.7735 | J134: 9155.141 | K134: 9470.9886 | L134: 14102.099 | M134: 14700.482
A135: =B135=B174 -> TRUE | B135: Maluku | C135: impr_ceic | D135: 374.324 | E135: 508.791 | F135: 528.67 | G135: 532.933 | H135: 527.44223 | I135: 535.22925 | J135: 588.8678 | K135: 630.57954 | L135: 677.66929 | M135: 699.17079
...

Sheet RAW_CEIC
A1: indicator | B1: provname_en | C1: provname_pap | D1: provname | E1: 2000 | F1: 2001 | G1: 2002 | H1: 2003 | I1: 2004 | J1: 2005 | K1: 2006 | L1: 2007 | M1: 2008 | N1: 2009 | O1: 2010 | P1: 2011 | Q1: 2012 | R1: 2013 | S1: 2014 | T1: 2015 | U1: 2016 | V1: 2017 | W1: 2018 | X1: 2019 | Y1: 2020 | Z1: 2021 | AA1: 2022 | AB1: 2023 | AC1: 2024 | AD1: 2025
A2: agrr_ceic | B2: Aceh | C2: Aceh | D2: Aceh | E2: 21575.61 | F2: 20882.8 | G2: 21327.97 | H2: 22025.17 | I2: 23356.22 | J2: 22447.34 | K2: 22788.31 | L2: 23612.76 | M2: 23803.54 | N2: 24412.68 | O2: 25579.57 | P2: 26515.48 | Q2: 27685.11 | R2: 28980.43 | S2: 29690.56 | T2: 31186.38 | U2: 32355.09 | V2: 34052.85 | W2: 35426.16 | X2: 36626.71 | Y2: 37899.52 | Z2: 37768.08 | AA2: 39005.09 | AB2: 41626.32 | AC2: 42121.38 | AD2: 43637.59
A3: agrr_ceic | B3: Bali | C3: Bali | D3: Bali | E3: 10487.44 | F3: 11082.48 | G3: 11488.73 | H3: 11905.69 | I3: 12341.19 | J3: 12858.93 | K3: 13386.6 | L3: 14618.96 | M3: 14963.8 | N3: 15813.19 | O3: 16092.72 | P3: 16258.74 | Q3: 16969.88 | R3: 17343.29 | S3: 18151.21 | T3: 18637.35 | U3: 19295.7 | V3: 19821.71 | W3: 20760.22 | X3: 21479.55 | Y3: 21269.19 | Z3: 21338.45 | AA3: 21157.3 | AB3: 21058.7 | AC3: 21586.55 | AD3: 21954.29
A4: agrr_ceic | B4: Bangka Belitung | C4: Kep. Bangka Belitung | D4: Kep. Bangka Belitung | E4: 3798.22 | F4: 4111.44 | G4: 4317.44 | H4: 4410.78 | I4: 4606.99 | J4: 4824.45 | K4: 5090.6 | L4: 5244.62 | M4: 5457.99 | N4: 5658.28 | O4: 6097.69 | P4: 6642.8 | Q4: 7072.89 | R4: 7557.66 | S4: 8254.34 | T4: 8743.51 | U4: 9123.19 | V4: 9095.69 | W4: 9589.72 | X4: 9862.83 | Y4: 10666.36 | Z4: 10768.72 | AA4: 10875.68 | AB4: 11281.88 | AC4: 11634.94 | AD4: 12003.87
A5: agrr_ceic | B5: Banten | C5: Banten | D5: Banten | E5: 10985.99 | F5: 11506.54 | G5: 11692.12 | H5: 12037.69 | I5: 12287.14 | J5: 12614.58 | K5: 12535.72 | L5: 14118.95 | M5: 14569.42 | N5: 15354.49 | O5: 16737.61 | P5: 17242.08 | Q5: 17793.38 | R5: 18990.92 | S5: 19456.95 | T5: 20743.47 | U5: 22108.75 | V5: 23055.55 | W5: 23880.77 | X5: 24408.33 | Y5: 25275.08 | Z5: 25416.58 | AA5: 26490.53 | AB5: 26531.3 | AC5: 26703.35 | AD5: 29266.23
A6: agrr_ceic | B6: Bengkulu | C6: Bengkulu | D6: Bengkulu | E6: 5728.65 | F6: 5937.16 | G6: 6202.04 | H6: 6565.87 | I6: 6928.19 | J6: 7331.42 | K6: 7751.37 | L6: 8189.66 | M6: 8643.42 | N6: 9119.25 | O6: 9343.96 | P6: 9734.67 | Q6: 10272.89 | R6: 10687.21 | S6: 10950.44 | T6: 11197.98 | U6: 11551.54 | V6: 11929.47 | W6: 12309.49 | X6: 12747.26 | Y6: 12795.99 | Z6: 13109.72 | AA6: 13699.33 | AB6: 13981.69 | AC6: 14341.27 | AD6: 14930.39
A7: agrr_ceic | B7: Central Java | C7: Jawa Tengah | D7: Jawa Tengah | E7: 74414.1 | F7: 75249.33 | G7: 78974.16 | H7: 77357.68 | I7: 81484.1 | J7: 85239.54 | K7: 88308.93 | L7: 90760.04 | M7: 93659.82 | N7: 97136.21 | O7: 99572.44 | P7: 103389.33 | Q7: 106536.7 | R7: 108832.11 | S7: 107793.38 | T7: 113826.3 | U7: 116331.12 | V7: 118450.17 | W7: 121554.48 | X7: 123150.02 | Y7: 126111.76 | Z7: 127065.84 | AA7: 130762.52 | AB7: 131330.54 | AC7: 133162.54 | AD7: 139530.4
A8: agrr_ceic | B8: Central Kalimantan | C8: Kalimantan Tengah | D8: Kalimantan Tengah | E8: 11342.89 | F8: 11846.56 | G8: 11594.9 | H8: 12535.97 | I8: 12561.59 | J8: 12695.63 | K8: 13122.8 | L8: 13175.81 | M8: 13118.8 | N8: 13541.43 | O8: 13935.36 | P8: 14165.41 | Q8: 14536.58 | R8: 15028.38 | S8: 16080.17 | T8: 17031.88 | U8: 17686.42 | V8: 18514.01 | W8: 19824.58 | X8: 21250.83 | Y8: 21304.92 | Z8: 22073.16 | AA8: 22834.25 | AB8: 23830.77 | AC8: 24138.62 | AD8: 25090.12
A9: agrr_ceic | B9: Central Papua | C9: Papua Tengah | D9: Papua | AA9: 3769.69 | AB9: 3829.34 | AC9: 3865.81 | AD9: 3966.19
A10: agrr_ceic | B10: Central Sulawesi | C10: Sulawesi Tengah | D10: Sulawesi Tengah | E10: 10450.93 | F10: 11123.93 | G10: 11885.49 | H10: 12772.13 | I10: 13766.84 | J10: 14650.9 | K10: 15448.99 | L10: 16550.24 | M10: 17312.7 | N10: 18419.21 | O10: 19523.49 | P10: 20711.36 | Q10: 21923.49 | R10: 23163.93 | S10: 24728.72 | T10: 26297.82 | U10: 26929.49 | V10: 28131.33 | W10: 29340.85 | X10: 29995.99 | Y10: 29593.65 | Z10: 30793.12 | AA10: 31639.57 | AB10: 32224.74 | AC10: 32848.02 | AD10: 34309.75
A11: agrr_ceic | B11: DI Yogyakarta | C11: DI Yogyakarta | D11: DI Yogyakarta | E11: 5533.2 | F11: 5759.8 | G11: 5860.64 | H11: 5886.44 | I11: 6095.14 | J11: 6360.34 | K11: 6602.23 | L11: 6655.05 | M11: 7035.5 | N11: 7272.59 | O11: 7252.6 | P11: 7134.68 | Q11: 7500.73 | R11: 7670.03 | S11: 7508.98 | T11: 7667.6 | U11: 7779.8 | V11: 7930.31 | W11: 8101.23 | X11: 8184.19 | Y11: 8534.64 | Z11: 8638.19 | AA11: 9077.78 | AB11: 9194.03 | AC11: 9206.5 | AD11: 9791.84
A12: agrr_ceic | B12: DKI Jakarta | C12: DKI Jakarta | D12: DKI Jakarta | E12: 1640.57 | F12: 1594.77 | G12: 1448.79 | H12: 1221.17 | I12: 1205.61 | J12: 1218.29 | K12: 1232.01 | L12: 1251.06 | M12: 1260.72 | N12: 1265.06 | O12: 1275.63 | P12: 1277.28 | Q12: 1319.31 | R12: 1353.56 | S12: 1359.95 | T12: 1375.42 | U12: 1387.53 | V12: 1391.53 | W12: 1394.05 | X12: 1398.22 | Y12: 1405.1 | Z12: 1463.34 | AA12: 1501.26 | AB12: 1443.04 | AC12: 1516.95 | AD12: 1561.67
A13: agrr_ceic | B13: East Java | C13: Jawa Timur | D13: Jawa Timur | E13: 104112.98 | F13: 105425.77 | G13: 107560.12 | H13: 109612.12 | I13: 112702.18 | J13: 116264.13 | K13: 118147.24 | L13: 121859.06 | M13: 125664.22 | N13: 130589.82 | O13: 133504.56 | P13: 138870.09 | Q13: 146002.57 | R13: 150463.72 | S13: 155783.96 | T13: 160889.4 | U13: 164762.91 | V13: 167360.57 | W13: 163799.94 | X13: 165951.23 | Y13: 167631.24 | Z13: 170556.77 | AA13: 173747.56 | AB13: 177668.37 | AC13: 177809.47 | AD13: 186662.71
A14: agrr_ceic | B14: East Kalimantan | C14: Kalimantan Timur | D14: Kalimantan Timur | E14: 16282.68 | F14: 16580.67 | G14: 17030 | H14: 17214.66 | I14: 17708.7 | J14: 18161.03 | K14: 18806.2 | L14: 19141.98 | M14: 19698.74 | N14: 19993.01 | O14: 21167.77 | P14: 22292.61 | Q14: 23991.79 | R14: 25535.67 | S14: 27267.2 | T14: 28506.91 | U14: 28639.4 | V14: 30261.4 | W14: 32140.16 | X14: 33355.19 | Y14: 33026.69 | Z14: 33003.9 | AA14: 33712.58 | AB14: 34551.18 | AC14: 35368.75 | AD14: 38094.43
A15: agrr_ceic | B15: East Nusa Tenggara | C15: Nusa Tenggara Timur | D15: Nusa Tenggara Timur | E15: 10469.09 | F15: 10799.67 | G15: 11205.53 | H15: 11435.39 | I15: 11835.1 | J15: 11949.36 | K15: 12540.98 | L15: 12884.94 | M15: 13379.21 | N15: 13684.3 | O15: 13963.14 | P15: 14244.98 | Q15: 14669.95 | R15: 15069.63 | S15: 15613.95 | T15: 16123.17 | U15: 16512.69 | V15: 17328.87 | W15: 17837.81 | X15: 18496.01 | Y15: 18680.64 | Z15: 19601.9 | AA15: 20341.73 | AB15: 20842.3 | AC15: 21224.74 | AD15: 21967.56
A16: agrr_ceic | B16: Gorontalo | C16: Gorontalo | D16: Gorontalo | E16: 3287.79 | F16: 3519.47 | G16: 3826.86 | H16: 3998.73 | I16: 4125.14 | J16: 4432.57 | K16: 4784.47 | L16: 5134.78 | M16: 5548.66 | N16: 5742.5 | O16: 5977.73 | P16: 6321.23 | Q16: 6763.85 | R16: 7232.59 | S16: 7698.32 | T16: 8024.61 | U16: 8540.36 | V16: 9314.37 | W16: 10019.05 | X16: 10652.83 | Y16: 10478.78 | Z16: 10663.64 | AA16: 10907.95 | AB16: 11365.5 | AC16: 11719.48 | AD16: 12205.24
A17: agrr_ceic | B17: Jambi | C17: Jambi | D17: Jambi | E17: 13821.41 | F17: 14334.5 | G17: 15029.5 | H17: 15563.87 | I17: 16354.9 | J17: 17108.3 | K17: 19047.67 | L17: 19917.72 | M17: 21056.68 | N17: 22458.21 | O17: 23627.24 | P17: 24744.88 | Q17: 26429.05 | R17: 28070.96 | S17: 31145.43 | T17: 32846.19 | U17: 34933.69 | V17: 36809.09 | W17: 38041.61 | X17: 39160.08 | Y17: 39751.94 | Z17: 41209.13 | AA17: 43268.38 | AB17: 45698.37 | AC17: 47643.01 | AD17: 50259.68
A18: agrr_ceic | B18: Lampung | C18: Lampung | D18: Lampung | E18: 36401.86 | F18: 37589.5 | G18: 38093.11 | H18: 39660.9 | I18: 41879.08 | J18: 43834.02 | K18: 46198.15 | L18: 48747.48 | M18: 50168.11 | N18: 51486.83 | O18: 52038.77 | P18: 54841.03 | Q18: 56997.47 | R18: 59636.49 | S18: 61595.15 | T18: 63745.49 | U18: 65730.54 | V18: 66297.14 | W18: 66941.02 | X18: 67848.65 | Y18: 68312.25 | Z18: 67969.86 | AA18: 69317.66 | AB18: 69697.99 | AC18: 68339.77 | AD18: 72381.45
A19: agrr_ceic | B19: Maluku | C19: Maluku | D19: Maluku | E19: 3670.3 | F19: 3627.36 | G19: 3663.05 | H19: 3734.53 | I19: 3839.09 | J19: 3978.62 | K19: 4096.73 | L19: 4265.79 | M19: 4388.96 | N19: 4567.08 | O19: 4825.72 | P19: 4972.6 | Q19: 5282.61 | R19: 5500.92 | S19: 5835.44 | T19: 5908.36 | U19: 6188.01 | V19: 6558.6 | W19: 6858.55 | X19: 7230.24 | Y19: 7353.71 | Z19: 7409.16 | AA19: 7833.24 | AB19: 8276.73 | AC19: 8557.59 | AD19: 9106.61
A20: agrr_ceic | B20: North Kalimantan | C20: Kalimantan Utara | D20: Kalimantan Utara | O20: 6235.36 | P20: 6676.56 | Q20: 7130 | R20: 7496.93 | S20: 8021.34 | T20: 8574.02 | U20: 9022 | V20: 9423 | W20: 9941.19 | X20: 10475.64 | Y20: 10925.64 | Z20: 11300.51 | AA20: 11723.08 | AB20: 12229.92 | AC20: 12444.24 | AD20: 12767.3
A21: agrr_ceic | B21: North Maluku | C21: Maluku Utara | D21: Maluku Utara | E21: 2514.56 | F21: 2562.49 | G21: 2645.37 | H21: 2768.44 | I21: 2848.76 | J21: 2974.86 | K21: 3116.28 | L21: 4102.26 | M21: 3936.69 | N21: 3739.01 | O21: 3936.69 | P21: 4105.56 | Q21: 4371.36 | R21: 4525.96 | S21: 4662.5 | T21: 4742.55 | U21: 4943.91 | V21: 5100.39 | W21: 5305.88 | X21: 5518.06 | Y21: 5594.84 | Z21: 5727.23 | AA21: 5911.57 | AB21: 6162.71 | AC21: 6440.92 | AD21: 6646.89
A22: agrr_ceic | B22: North Sulawesi | C22: Sulawesi Utara | D22: Sulawesi Utara | E22: 7667.12 | F22: 7964.89 | G22: 8320.34 | H22: 8392.96 | I22: 8947.76 | J22: 9497.69 | K22: 9740.67 | L22: 10479.52 | M22: 11089.02 | N22: 11318.59 | O22: 12281.01 | P22: 12154.19 | Q22: 12918.08 | R22: 13765.3 | S22: 14243.12 | T22: 14605.52 | U22: 15141.89 | V22: 15814.32 | W22: 16367.26 | X22: 17320.48 | Y22: 17705.45 | Z22: 18040.14 | AA22: 19187.16 | AB22: 20036.33 | AC22: 21113.98 | AD22: 22337.2
A23: agrr_ceic | B23: North Sumatera | C23: Sumatera Utara | D23: Sumatera Utara | E23: 57864.17 | F23: 60061.78 | G23: 61584.13 | H23: 63131.37 | I23: 65499.04 | J23: 67713.98 | K23: 69340.93 | L23: 72794.06 | M23: 77201.71 | N23: 80943.58 | O23: 85561.14 | P23: 90592.55 | Q23: 95405.42 | R23: 99894.57 | S23: 104262.83 | T23: 110066 | U23: 115179.69 | V23: 121300.04 | W23: 127202.65 | X23: 133726.02 | Y23: 136327.03 | Z23: 141601.18 | AA23: 148721.97 | AB23: 153246.71 | AC23: 158940.62 | AD23: 166702.96
A24: agrr_ceic | B24: Papua | C24: Papua | D24: Papua | E24: 11391.95 | F24: 12512.43 | G24: 8854.27 | H24: 9280.62 | I24: 9223.47 | J24: 9668.39 | K24: 10171.16 | L24: 10309.74 | M24: 10793.27 | N24: 11248.9 | O24: 11681.13 | P24: 12133.26 | Q24: 12883.7 | R24: 13661.8 | S24: 14432.99 | T24: 15192.6 | U24: 15461.69 | V24: 16070.49 | W24: 16602.56 | X24: 16608.11 | Y24: 16490.61 | Z24: 16755.83 | AA24: 17135.86 | AB24: 7017.85 | AC24: 7073.68 | AD24: 7401.07
A25: agrr_ceic | B25: Papua Mountains | C25: Papua Pegunungan | D25: Papua | AA25: 2276.97 | AB25: 2333.87 | AC25: 2409.55 | AD25: 2483.29
A26: agrr_ceic | B26: Riau | C26: Riau | D26: Riau | E26: 59133.63 | F26: 62824.44 | G26: 66608.53 | H26: 63611.7 | I26: 68065.58 | J26: 72673.07 | K26: 77010.89 | L26: 80739.72 | M26: 84607.9 | N26: 87757.75 | O26: 91152.77 | P26: 94307.4 | Q26: 97910.95 | R26: 102216.74 | S26: 108498.09 | T26: 108969.04 | U26: 113287.59 | V26: 119281.64 | W26: 124547.86 | X26: 129690.41 | Y26: 135124.21 | Z26: 140717.74 | AA26: 144691.04 | AB26: 149361.11 | AC26: 152698.4 | AD26: 160178.56
A27: agrr_ceic | B27: Riau Islands | C27: Kep. Riau | D27: Kep. Riau | H27: 3288.86 | I27: 3476.17 | J27: 3663.79 | K27: 3862.14 | L27: 4105.26 | M27: 4261.11 | N27: 4324.91 | O27: 4506.56 | P27: 4683.47 | Q27: 4794.17 | R27: 5000.01 | S27: 5378.15 | T27: 5689.22 | U27: 6018.41 | V27: 5945.61 | W27: 5757.78 | X27: 5717.73 | Y27: 5466.78 | Z27: 5322.05 | AA27: 5601.86 | AB27: 5687.64 | AC27: 5720.17 | AD27: 5919.88
A28: agrr_ceic | B28: South East Sulawesi | C28: Sulawesi Tenggara | D28: Sulawesi Tenggara | E28: 8231.62 | F28: 8673.44 | G28: 9302.72 | H28: 9875.04 | I28: 10649.04 | J28: 11385.14 | K28: 11905.93 | L28: 12572.51 | M28: 13205.9 | N28: 13566.97 | O28: 13741.14 | P28: 14007.46 | Q28: 14625.41 | R28: 15508.22 | S28: 16952.31 | T28: 16970.46 | U28: 18270.18 | V28: 19323.26 | W28: 20554.63 | X28: 21581.03 | Y28: 21728.37 | Z28: 22247.11 | AA28: 23754.98 | AB28: 24779.74 | AC28: 25734.91 | AD28: 26698.67
A29: agrr_ceic | B29: South Kalimantan | C29: Kalimantan Selatan | D29: Kalimantan Selatan | E29: 8386.9 | F29: 9058.77 | G29: 9309.45 | H29: 9585.57 | I29: 10161.95 | J29: 10680.79 | K29: 11182.38 | L29: 11822.1 | M29: 12618.34 | N29: 13419.22 | O29: 13701.55 | P29: 14052.46 | Q29: 14490.15 | R29: 14967.33 | S29: 15636.19 | T29: 16013.3 | U29: 16600.74 | V29: 17280.42 | W29: 17925.11 | X29: 18568.23 | Y29: 18399.41 | Z29: 18614.34 | AA29: 18911.08 | AB29: 19537.28 | AC29: 20350.73 | AD29: 21717.59
A30: agrr_ceic | B30: South Papua | C30: Papua Selatan | D30: Papua | AA30: 4201.92 | AB30: 4345.1 | AC30: 4444.51 | AD30: 4652.05
A31: agrr_ceic | B31: South Sulawesi | C31: Sulawesi Selatan | D31: Sulawesi Selatan | E31: 33353.51 | F31: 33671.01 | G31: 35218.73 | H31: 35478.6 | I31: 35240.91 | J31: 32427.95 | K31: 33757.98 | L31: 34842.74 | M31: 36963.89 | N31: 38695.1 | O31: 39598.91 | P31: 42325.57 | Q31: 44263.48 | R31: 46446.73 | S31: 51101.68 | T31: 54099.1 | U31: 58351.27 | V31: 61597.2 | W31: 64815.46 | X31: 66615.94 | Y31: 66139.9 | Z31: 70357.8 | AA31: 72162.73 | AB31: 72226.31 | AC31: 75166.74 | AD31: 80474.87
A32: agrr_ceic | B32: South Sumatera | C32: Sumatera Selatan | D32: Sumatera Selatan | E32: 23259.1 | F32: 24246.67 | G32: 25345.81 | H32: 26609.16 | I32: 28243.27 | J32: 29902.61 | K32: 31828.85 | L32: 33891.45 | M32: 35276.2 | N32: 36371.82 | O32: 38067.01 | P32: 40120.77 | Q32: 42557.3 | R32: 44794.97 | S32: 46612.03 | T32: 48287.68 | U32: 48942.64 | V32: 49518.88 | W32: 50674.28 | X32: 52366.83 | Y32: 53281.53 | Z32: 54834.53 | AA32: 56926.73 | AB32: 58154.46 | AC32: 59555.29 | AD32: 63001.27
A33: agrr_ceic | B33: South West Papua | C33: Papua Barat Daya | D33: Papua Barat | AB33: 2834.43 | AC33: 2849.11 | AD33: 3000.25
A34: agrr_ceic | B34: West Java | C34: Jawa Barat | D34: Jawa Barat | E34: 60856.34 | F34: 67181.71 | G34: 66846.15 | H34: 68505.57 | I34: 72851.48 | J34: 73875.4 | K34: 73621.7 | L34: 75451.5 | M34: 78522.4 | N34: 88209.99 | O34: 89088.26 | P34: 88386.51 | Q34: 88409.46 | R34: 92390.13 | S34: 92653.58 | T34: 92802.8 | U34: 98096.58 | V34: 99669.37 | W34: 101752.2 | X34: 104596.75 | Y34: 107000.79 | Z34: 108406.55 | AA34: 113186.39 | AB34: 113308.41 | AC34: 115104.77 | AD34: 126696.51
A35: agrr_ceic | B35: West Kalimantan | C35: Kalimantan Barat | D35: Kalimantan Barat | E35: 14734.24 | F35: 14333.19 | G35: 15365.42 | H35: 15834.1 | I35: 16210.1 | J35: 16964.12 | K35: 17869.57 | L35: 18740.84 | M35: 19820.43 | N35: 20610.8 | O35: 21485.41 | P35: 22292.71 | Q35: 23201.41 | R35: 24401.6 | S35: 24967.38 | T35: 25571.67 | U35: 26618.92 | V35: 28357.68 | W35: 30209.4 | X35: 31956.43 | Y35: 32371.35 | Z35: 33811.57 | AA35: 34547.57 | AB35: 35108.57 | AC35: 36150.73 | AD35: 36926.67
A36: agrr_ceic | B36: West Nusa Tenggara | C36: Nusa Tenggara Barat | D36: Nusa Tenggara Barat | E36: 11680.7 | F36: 11610.91 | G36: 11756.51 | H36: 12301.62 | I36: 12624.99 | J36: 12746.37 | K36: 13113.49 | L36: 13493.58 | M36: 14239.44 | N36: 14743.1 | O36: 14939.02 | P36: 15691.91 | Q36: 16407.44 | R36: 16946.74 | S36: 17702.37 | T36: 18964.88 | U36: 19564.75 | V36: 20843.23 | W36: 21262.43 | X36: 21555.36 | Y36: 21466.1 | Z36: 21712.18 | AA36: 22187.32 | AB36: 22642.74 | AC36: 22992.48 | AD36: 24150
A37: agrr_ceic | B37: West Papua | C37: Papua Barat | D37: Papua Barat | G37: 3429.79 | H37: 3603.52 | I37: 3744.32 | J37: 3821.22 | K37: 3946.88 | L37: 4152.88 | M37: 4439.14 | N37: 4609.14 | O37: 4889.56 | P37: 4583.19 | Q37: 4785.62 | R37: 5090.42 | S37: 5343.52 | T37: 5482.57 | U37: 5598.84 | V37: 5926.64 | W37: 6058.67 | X37: 6273.1 | Y37: 6122.47 | Z37: 6182.41 | AA37: 6199.07 | AB37: 3304.15 | AC37: 3310.73 | AD37: 3350.82
A38: agrr_ceic | B38: West Sulawesi | C38: Sulawesi Barat | D38: Sulawesi Barat | J38: 5684.53 | K38: 5934.41 | L38: 6146.94 | M38: 6338.3 | N38: 6535.66 | O38: 7486.61 | P38: 8115.11 | Q38: 8709.5 | R38: 9207.15 | S38: 9753.26 | T38: 10313.54 | U38: 10734.08 | V38: 11433.15 | W38: 12131.88 | X38: 12692.97 | Y38: 12761.98 | Z38: 12910.29 | AA38: 13342.96 | AB38: 13878.49 | AC38: 14541.57 | AD38: 15421.69
A39: agrr_ceic | B39: West Sumatera | C39: Sumatera Barat | D39: Sumatera Barat | E39: 16086.3 | F39: 16870.1 | G39: 18196.02 | H39: 19586.71 | I39: 20720.73 | J39: 21784.17 | K39: 22874.96 | L39: 24011.55 | M39: 25325.98 | N39: 26205.69 | O39: 27277.72 | P39: 28535.02 | Q39: 29284.9 | R39: 30372.99 | S39: 32151.49 | T39: 33546.76 | U39: 34222.56 | V39: 35394.69 | W39: 36639.6 | X39: 37549.46 | Y39: 37993.39 | Z39: 38820.71 | AA39: 40188.63 | AB39: 41612.83 | AC39: 42467.73 | AD39: 44227.28
A40: expr_ceic | B40: Aceh | C40: Aceh | D40: Aceh | E40: 126799.83 | F40: 120175.9 | G40: 136014.13 | H40: 139803.4 | I40: 113537.39 | J40: 79008.045 | K40: 68539.979 | L40: 70084.721 | M40: 66412.571 | N40: 52053.677 | O40: 48794.255 | P40: 48189.041 | Q40: 49148.162 | R40: 48786.604 | S40: 47198.272 | T40: 45570.602 | U40: 46196.343 | V40: 50893.467 | W40: 52747.141 | X40: 52517.086 | Y40: 52072.394 | Z40: 54937.198 | AA40: 68395.63 | AB40: 76810.85 | AC40: 81753.39 | AD40: 88632.84
A41: expr_ceic | B41: Bali | C41: Bali | D41: Bali | E41: 11814.153 | F41: 12448.631 | G41: 12936.624 | H41: 13710.565 | I41: 15318.109 | J41: 15772.045 | K41: 17707.32 | L41: 20082.917 | M41: 23492.397 | N41: 26183.858 | O41: 30918.016 | P41: 31862.949 | Q41: 33174.014 | R41: 37069.63 | S41: 43139.801 | T41: 45736.99 | U41: 52314.23 | V41: 56024.959 | W41: 59447.661 | X41: 59187.152 | Y41: 14121.597 | Z41: 4340.0661 | AA41: 28410.212 | AB41: 57666.17 | AC41: 66949.35 | AD41: 72452.11
A42: expr_ceic | B42: Bangka Belitung | C42: Kep. Bangka Belitung | D42: Kep. Bangka Belitung | E42: 10255.207 | F42: 12369.517 | G42: 10231.109 | H42: 10262.634 | I42: 20617.083 | J42: 21642.067 | K42: 21470.094 | L42: 21682.443 | M42: 21635.24 | N42: 21410.866 | O42: 21755.362 | P42: 30265.464 | Q42: 27941.951 | R42: 30238.287 | S42: 35019.116 | T42: 28501.762 | U42: 25174.565 | V42: 30894.843 | W42: 30845.017 | X42: 25775.369 | Y42: 23895.469 | Z42: 34704.363 | AA42: 34244.873 | AB42: 28171.039 | AC42: 23604.979
A43: expr_ceic | B43: Banten | C43: Banten | D43: Banten | E43: 72858.227 | F43: 71490.491 | G43: 74361.576 | H43: 79587.487 | I43: 87397.471 | J43: 94241.662 | K43: 104918.24 | L43: 208859.15 | M43: 219942.32 | N43: 201828.89 | O43: 225820.84 | P43: 244595.48 | Q43: 269522.32 | R43: 266070.52 | S43: 281606 | T43: 293912.58 | U43: 300740.57 | V43: 332512.6 | W43: 340890.02 | X43: 336892.96 | Y43: 318894.27 | Z43: 351228.89 | AA43: 379728.39 | AB43: 384298.13 | AC43: 419119.83 | AD43: 432045.42
A44: expr_ceic | B44: Bengkulu | C44: Bengkulu | D44: Bengkulu | E44: 5885.5718 | F44: 5981.9601 | G44: 6210.9182 | H44: 6509.234 | I44: 7186.6414 | J44: 7544.7096 | K44: 7913.6746 | L44: 8332.0208 | M44: 9006.269 | N44: 8968.986 | O44: 10010.582 | P44: 11639.894 | Q44: 13078.846 | R44: 12820.114 | S44: 12751.372 | T44: 13793.957 | U44: 14552.437 | V44: 15960.521 | W44: 16197.879 | X44: 16544.333 | Y44: 16114.69 | Z44: 17164.758 | AA44: 17640.592 | AB44: 18201.558 | AC44: 18005.315
A45: expr_ceic | B45: Central Java | C45: Jawa Tengah | D45: Jawa Tengah | E45: 35420.345 | F45: 35510.639 | G45: 33178.113 | H45: 38280.347 | I45: 40515.391 | J45: 39749.425 | K45: 38578.953 | L45: 40716.537 | M45: 41238.36 | N45: 39396.975 | O45: 43652.54 | P45: 49680.05 | Q45: 53707.48 | R45: 61923.62 | S45: 68523.198 | T45: 68716.856 | U45: 66644.885 | V45: 75670.848 | W45: 84592.902 | X45: 88909.097 | Y45: 85535.252 | Z45: 104222.2 | AA45: 115030.49 | AB45: 104053.81 | AC45: 117267.52 | AD45: 133212.43
A46: expr_ceic | B46: Central Kalimantan | C46: Kalimantan Tengah | D46: Kalimantan Tengah | E46: 10039.659 | F46: 9637.8133 | G46: 9796.6666 | H46: 10695.267 | I46: 11180.687 | J46: 11794.117 | K46: 13107.875 | L46: 13295.736 | M46: 15755.681 | N46: 19012.108 | O46: 23886.645 | P46: 25677.581 | Q46: 27975.125 | R46: 31494.949 | S46: 32006.5 | T46: 34498.6 | U46: 38054.827 | V46: 42464.7 | W46: 46881.9 | X46: 48925 | Y46: 45881.2 | Z46: 48326.2 | AA46: 57134.6 | AB46: 56841 | AC46: 56590 | AD46: 62629.3
A47: expr_ceic | B47: Central Papua | C47: Papua Tengah | D47: Papua | AA47: 59394.65 | AB47: 57982.28 | AC47: 64800.28
A48: expr_ceic | B48: Central Sulawesi | C48: Sulawesi Tengah | D48: Sulawesi Tengah | E48: 7500.7863 | F48: 7892.6755 | G48: 8274.6381 | H48: 8578.9083 | I48: 8890.5097 | J48: 9332.371 | K48: 9878.0313 | L48: 10825.611 | M48: 11881.273 | N48: 12491.711 | O48: 13951.023 | P48: 17033.437 | Q48: 22073.64 | R48: 19843.542 | S48: 19644.772 | T48: 25067.743 | U48: 40319.446 | V48: 44537.492 | W48: 97813.048 | X48: 112407.85 | Y48: 143629.45 | Z48: 158796.11 | AA48: 194754.67 | AB48: 231589.54 | AC48: 275299.86
A49: expr_ceic | B49: DI Yogyakarta | C49: DI Yogyakarta | D49: DI Yogyakarta | E49: 1628.5232 | F49: 1767.4508 | G49: 1903.5744 | H49: 2033.584 | I49: 2133.5795 | J49: 2268.757 | K49: 2226.2326 | L49: 2336.6401 | M49: 2477.2759 | N49: 2555.1555 | O49: 2719.3946 | P49: 2543.2615 | Q49: 2933.9539 | R49: 3541.6402 | S49: 4278.2479 | T49: 4416.2521 | U49: 4400.889 | V49: 4808.5274 | W49: 5424.8027 | X49: 5413.1309 | Y49: 4714.7278 | Z49: 5736.9344 | AA49: 6213.754 | AB49: 5265.2602 | AC49: 5983.5242 | AD49: 6461
A50: expr_ceic | B50: DKI Jakarta | C50: DKI Jakarta | D50: DKI Jakarta | E50: 244095.98 | F50: 234876.96 | G50: 254639.93 | H50: 295410.75 | I50: 343153.47 | J50: 381932.26 | K50: 398128.25 | L50: 420937.69 | M50: 440312.4 | N50: 441353.39 | O50: 473891.32 | P50: 584876.79 | Q50: 576970.6 | R50: 541272.49 | S50: 551708.76 | T50: 553924.18 | U50: 576458.93 | V50: 756531.28 | W50: 1001227.3 | X50: 983214.58 | Y50: 887825.88 | Z50: 988640.33 | AA50: 1113108.9 | AB50: 1199015 | AC50: 1314627.6
A51: expr_ceic | B51: East Java | C51: Jawa Timur | D51: Jawa Timur | E51: 235331.66 | F51: 237926.09 | G51: 221612.66 | H51: 231802.27 | I51: 244331.6 | J51: 270529.03 | K51: 294431.81 | L51: 311001.45 | M51: 329225.76 | N51: 319391.06 | O51: 348456.1 | P51: 431205.4 | Q51: 496215.45 | R51: 515981.67 | S51: 575459.31 | T51: 592478.23 | U51: 671096.85 | V51: 749400.18 | W51: 817740.56 | X51: 845287.79 | Y51: 817057.63 | Z51: 902139.84 | AA51: 985733.75 | AB51: 1002438.7 | AC51: 1093502.8 | AD51: 1166044.8
A52: expr_ceic | B52: East Kalimantan | C52: Kalimantan Timur | D52: Kalimantan Timur | E52: 291350.95 | F52: 304457.51 | G52: 301062.71 | H52: 307203.72 | I52: 328304.36 | J52: 351845.87 | K52: 371611.13 | L52: 380265.2 | M52: 399930.62 | N52: 378007.94 | O52: 408291.06 | P52: 430355.79 | Q52: 454195.06 | R52: 467041.12 | S52: 475151.61 | T52: 473419.87 | U52: 481739.01 | V52: 502223.35 | W52: 513208.17 | X52: 539516.96 | Y52: 519613.4 | Z52: 537033.35 | AA52: 556463.45 | AB52: 589664.61 | AC52: 631016.87 | AD52: 669089.9
A53: expr_ceic | B53: East Nusa Tenggara | C53: Nusa Tenggara Timur | D53: Nusa Tenggara Timur | E53: 1371.6527 | F53: 1898.9188 | G53: 2106.8238 | H53: 2232.2149 | I53: 2270.8257 | J53: 2473.1715 | K53: 2739.5862 | L53: 2994.0368 | M53: 3074.341 | N53: 3114.7682 | O53: 3152.7413 | P53: 5481.6007 | Q53: 7750.0073 | R53: 4708.8683 | S53: 5347.4405 | T53: 10490.511 | U53: 5746.0346 | V53: 5540.1921 | W53: 6474.4411 | X53: 6217.0265 | Y53: 4057.9702 | Z53: 3426.4636 | AA53: 3757.3608 | AB53: 4509.5679 | AC53: 4330.1326
A54: expr_ceic | B54: Gorontalo | C54: Gorontalo | D54: Gorontalo | E54: 595.6125 | F54: 871.07981 | G54: 1078.3719 | H54: 1344.2817 | I54: 1617.7154 | J54: 1948.9089 | K54: 2340.9748 | L54: 2882.7792 | M54: 3132.9693 | N54: 3069.588 | O54: 3226.69 | P54: 3799.53 | Q54: 4775.88 | R54: 4812.59 | S54: 5175.65 | T54: 5327.66 | U54: 5083.93 | V54: 5383.49 | W54: 6135.94 | X54: 6254.89 | Y54: 6102.36 | Z54: 6776.3 | AA54: 7259.77 | AB54: 7737.11 | AC54: 8409.63
A55: expr_ceic | B55: Jambi | C55: Jambi | D55: Jambi | E55: 27406.778 | F55: 29184.503 | G55: 29208.938 | H55: 28964.155 | I55: 30716.31 | J55: 34709.889 | K55: 39551.498 | L55: 47189.309 | M55: 48943.841 | N55: 54293.165 | O55: 73721.858 | P55: 76468.471 | Q55: 72869.868 | R55: 76358.625 | S55: 80931.574 | T55: 88473.649 | U55: 91157.01 | V55: 100551.44 | W55: 108691.61 | X55: 112297.08 | Y55: 101607.31 | Z55: 106352.4 | AA55: 110836.94 | AB55: 108965.38 | AC55: 112821.18
A56: expr_ceic | B56: Lampung | C56: Lampung | D56: Lampung | E56: 33560.177 | F56: 29077.251 | G56: 31302.198 | H56: 38605.178 | I56: 35413.89 | J56: 41744.98 | K56: 46511.223 | L56: 46447.257 | M56: 68386.425 | N56: 61676.058 | O56: 58516.351 | P56: 66929.745 | Q56: 88912.712 | R56: 88292.004 | S56: 91988.581 | T56: 87104.122 | U56: 84860.15 | V56: 89754.319 | W56: 100202.05 | X56: 105181.84 | Y56: 100669.15 | Z56: 117991.61 | AA56: 125813.01 | AB56: 133226.67 | AC56: 149412.72 | AD56: 61878.04
A57: expr_ceic | B57: Maluku | C57: Maluku | D57: Maluku | E57: 3103.2197 | F57: 2823.7779 | G57: 2842.2348 | H57: 2994.8259 | I57: 3118.1104 | J57: 3233.5156 | K57: 3453.509 | L57: 3773.0307 | M57: 3960.2072 | N57: 4062.4627 | O57: 4533.9193 | P57: 4417.166 | Q57: 5376.0405 | R57: 5835.6939 | S57: 5189.1782 | T57: 5183.5488 | U57: 5403.5587 | V57: 5347.3848 | W57: 4771.4345 | X57: 3985.1772 | Y57: 2791.8852 | Z57: 4043.7156 | AA57: 4787.5938 | AB57: 4128.3144 | AC57: 145.72
A58: expr_ceic | B58: North Kalimantan | C58: Kalimantan Utara | D58: Kalimantan Utara | Q58: 34402.426 | R58: 37225.75 | S58: 41345.536 | T58: 42093.105 | U58: 44096.759 | V58: 48029.822 | W58: 51249.329 | X58: 57140.194 | Y58: 57834.85 | Z58: 66189.414 | AA58: 70918.925 | AB58: 72137.949 | AC58: 73589.006 | AD58: 75781.568
A59: expr_ceic | B59: North Maluku | C59: Maluku Utara | D59: Maluku Utara
A60: expr_ceic | B60: North Sulawesi | C60: Sulawesi Utara | D60: Sulawesi Utara | E60: 5821.1532 | F60: 3730.6072 | G60: 3736.6581 | H60: 4764.2213 | I60: 6742.4752 | J60: 7576.5816 | K60: 7447.4314 | L60: 8202.2227 | M60: 9995.678 | N60: 10402.383 | O60: 11844.726 | P60: 18579.839 | Q60: 24554.471 | R60: 19319.593 | S60: 22959.623 | T60: 18123.275 | U60: 20406.113 | V60: 20527.698 | W60: 23275.491 | X60: 23521.512 | Y60: 22975.227 | Z60: 24936.158 | AA60: 25347.287 | AB60: 26448.298 | AC60: 26904.414
A61: expr_ceic | B61: North Sumatera | C61: Sumatera Utara | D61: Sumatera Utara | E61: 66631.127 | F61: 75113.063 | G61: 76998.672 | H61: 80887.252 | I61: 99141.187 | J61: 105554.94 | K61: 101650.59 | L61: 111052.67 | M61: 122585.85 | N61: 121424.19 | O61: 133920.53 | P61: 155912.64 | Q61: 159278.56 | R61: 178463.32 | S61: 191872.58 | T61: 189848.62 | U61: 194929.51 | V61: 208689.48 | W61: 222718.56 | X61: 218152.13 | Y61: 195680.31 | Z61: 223930.56 | AA61: 249627.87 | AB61: 248219.13 | AC61: 276532.14
A62: expr_ceic | B62: Papua | C62: Papua | D62: Papua | E62: 56393.053 | F62: 57343.511 | G62: 51548.662 | H62: 58350.256 | I62: 45225.489 | J62: 50917.074 | K62: 52849.599 | L62: 47522.113 | M62: 43592.815 | N62: 51590.985 | O62: 46999.047 | P62: 33910.146 | Q62: 24281.055 | R62: 32143.119 | S62: 17091.171 | T62: 23736.758 | U62: 25377.054 | V62: 24016.292 | W62: 33517.563 | X62: 10533.486 | Y62: 15901.656 | Z62: 28341.609 | AA62: 41443.784 | AB62: 42395.071 | AC62: 61382.73
A63: expr_ceic | B63: Papua Mountains | C63: Papua Pegunungan | D63: Papua | AB63: 2236.9 | AC63: 2319.38
A64: expr_ceic | B64: Riau | C64: Riau | D64: Riau | E64: 227774.34 | F64: 335229.79 | G64: 289578.7 | H64: 186245.16 | I64: 189927.1 | J64: 199143.25 | K64: 207868.62 | L64: 220898.35 | M64: 235674.78 | N64: 226771.24 | O64: 229801.07 | P64: 268075.13 | Q64: 293195.74 | R64: 285085.39 | S64: 242929.36 | T64: 200076.98 | U64: 179832.76 | V64: 205304.96 | W64: 209526.11 | X64: 213493.49 | Y64: 225753.45 | Z64: 289376.88 | AA64: 336936.21 | AB64: 347466.91 | AC64: 353960.03
A65: expr_ceic | B65: Riau Islands | C65: Kep. Riau | D65: Kep. Riau | H65: 115779.23 | I65: 120324.17 | J65: 128656.15 | K65: 127610.91 | L65: 153583.17 | M65: 157960.13 | N65: 154815.04 | O65: 166131.49 | P65: 244113.02 | Q65: 207201.07 | R65: 234453.59 | S65: 237440.03 | T65: 249780.28 | U65: 260019.03 | V65: 257905.68 | W65: 263907.83 | X65: 275718.74 | Y65: 269000.8 | Z65: 292037.37 | AA65: 324436.08 | AB65: 316214.44 | AC65: 328150.97 | AD65: 267698.68
A66: expr_ceic | B66: South East Sulawesi | C66: Sulawesi Tenggara | D66: Sulawesi Tenggara | E66: 3020.2063 | F66: 3103.3616 | G66: 3184.1752 | H66: 3614.7663 | I66: 4383.1032 | J66: 4818.745 | K66: 8809.7065 | L66: 9239.9707 | M66: 9035.9383 | N66: 9541.931 | O66: 10965.377 | P66: 15382.386 | Q66: 18720.096 | R66: 19229.506 | S66: 14910.239 | T66: 7880.9197 | U66: 7141.7824 | V66: 8795.4008 | W66: 17736.51 | X66: 25638.775 | Y66: 37223.046 | Z66: 59643.399 | AA66: 70128.497 | AB66: 58497.317 | AC66: 55123.116
A67: expr_ceic | B67: South Kalimantan | C67: Kalimantan Selatan | D67: Kalimantan Selatan | E67: 35203.608 | F67: 33911.202 | G67: 37927.895 | H67: 41102.021 | I67: 42271.57 | J67: 55563.064 | K67: 51455.886 | L67: 57892.453 | M67: 66609.746 | N67: 67112.634 | O67: 74947.786 | P67: 91457.943 | Q67: 91807.107 | R67: 91706.847 | S67: 91123.191 | T67: 84548.668 | U67: 84859.057 | V67: 92462.024 | W67: 97980.972 | X67: 100100.73 | Y67: 88918.22 | Z67: 105442.21 | AA67: 119455.94 | AB67: 128461.84 | AC67: 134831.74 | AD67: 127289.45
A68: expr_ceic | B68: South Papua | C68: Papua Selatan | D68: Papua | AA68: 5216.3 | AB68: 6247.38 | AC68: 6397.97
A69: expr_ceic | B69: South Sulawesi | C69: Sulawesi Selatan | D69: Sulawesi Selatan | E69: 20078.856 | F69: 19696.224 | G69: 19091.462 | H69: 19498.865 | I69: 32039.312 | J69: 37357.709 | K69: 38875.315 | L69: 49716.895 | M69: 44586.759 | N69: 38940.123 | O69: 58537.975 | P69: 52855.571 | Q69: 51218.349 | R69: 52363.205 | S69: 60314.079 | T69: 54053.188 | U69: 35861.16 | V69: 31475.01 | W69: 32261.5 | X69: 31671.47 | Y69: 31936.54 | Z69: 35722.05 | AA69: 49176.72 | AB69: 48785.62 | AC69: 49903.7
A70: expr_ceic | B70: South Sumatera | C70: Sumatera Selatan | D70: Sumatera Selatan | E70: 34231.627 | F70: 34146.461 | G70: 35268.803 | H70: 39248.781 | I70: 44821.638 | J70: 41426.047 | K70: 52423.004 | L70: 50406.647 | M70: 54324.535 | N70: 48176.64 | O70: 56902.827 | P70: 69140.277 | Q70: 74861.1 | R70: 85500.814 | S70: 93579.506 | T70: 91237.103 | U70: 90043.733 | V70: 115180.71 | W70: 128760.37 | X70: 105887.33 | Y70: 91964.279 | Z70: 98675.655 | AA70: 137914.62 | AB70: 133754.2 | AC70: 124021.01
A71: expr_ceic | B71: South West Papua | C71: Papua Barat Daya | D71: Papua Barat | AB71: 1360.32 | AC71: 1294.55 | AD71: 555.32
A72: expr_ceic | B72: West Java | C72: Jawa Barat | D72: Jawa Barat | E72: 183165.5 | F72: 202234.99 | G72: 290497.99 | H72: 303665.71 | I72: 314393.74 | J72: 325579.78 | K72: 309041.84 | L72: 297457.92 | M72: 269030.58 | N72: 281800.18 | O72: 316311.7 | P72: 380679.95 | Q72: 423333.82 | R72: 379154.22 | S72: 400530.84 | T72: 423152.22 | U72: 435541.82 | V72: 493916.58 | W72: 550805.25 | X72: 591685.34 | Y72: 558716.78 | Z72: 681316.21 | AA72: 756452.62 | AB72: 850488.05 | AC72: 953340.82
A73: expr_ceic | B73: West Kalimantan | C73: Kalimantan Barat | D73: Kalimantan Barat | E73: 9210.6129 | F73: 9385.0231 | G73: 8495.8595 | H73: 8798.5835 | I73: 8830.5587 | J73: 9382.3889 | K73: 10832.205 | L73: 10657.667 | M73: 11452.95 | N73: 10708.727 | O73: 11531.072 | P73: 19992.977 | Q73: 16077.199 | R73: 18475.303 | S73: 9882.0681 | T73: 9501.4304 | U73: 10797.309 | V73: 14336.101 | W73: 17152.376 | X73: 19122.576 | Y73: 20605.587 | Z73: 25287.066 | AA73: 34492.54 | AB73: 26132.97 | AC73: 33307.19
A74: expr_ceic | B74: West Nusa Tenggara | C74: Nusa Tenggara Barat | D74: Nusa Tenggara Barat | E74: 27536.294 | F74: 30570.023 | G74: 32475.543 | H74: 29550.736 | I74: 31133.599 | J74: 30103.184 | K74: 27646.232 | L74: 27306.309 | M74: 24705.73 | N74: 29402.985 | O74: 32859.298 | P74: 25912.107 | Q74: 17349.745 | R74: 15088.569 | S74: 11455.385 | T74: 23089 | U74: 26167.999 | V74: 24100.24 | W74: 19620.68 | X74: 23536.144 | Y74: 25504.198 | Z74: 28073.111 | AA74: 40832.865 | AB74: 36425.221 | AC74: 38526.69 | AD74: 34357.12
A75: expr_ceic | B75: West Papua | C75: Papua Barat | D75: Papua Barat | G75: 16685.047 | H75: 16598.481 | I75: 15862.05 | J75: 19525.481 | K75: 21680.56 | L75: 21718.53 | M75: 20201.975 | N75: 17709.775 | O75: 31529.454 | P75: 24562.901 | Q75: 30602.478 | R75: 30182.355 | S75: 35334.415 | T75: 40438.386 | U75: 39446.298 | V75: 42688.117 | W75: 49488.554 | X75: 47314.462 | Y75: 45934.783 | Z75: 41019.721 | AA75: 54213.34 | AB75: 42010.89 | AC75: 48774.06
A76: expr_ceic | B76: West Sulawesi | C76: Sulawesi Barat | D76: Sulawesi Barat | I76: 4765.8997 | J76: 5011.6542 | K76: 5344.2541 | L76: 5948.2817 | M76: 6966.1856 | N76: 7980.3165 | O76: 9422.2478 | P76: 11066.665 | Q76: 12400.48 | R76: 12055.168 | S76: 12379.137 | T76: 13333.211 | U76: 13594.558 | V76: 13663.555 | W76: 14816.326 | X76: 15513.337 | Y76: 14480.492 | Z76: 14668.585 | AA76: 14218.983 | AB76: 14710.17 | AC76: 15175
A77: expr_ceic | B77: West Sumatera | C77: Sumatera Barat | D77: Sumatera Barat | E77: 14680.411 | F77: 15000.74 | G77: 17739.328 | H77: 20748.064 | I77: 26849.193 | J77: 32540.888 | K77: 38468.564 | L77: 49587.429 | M77: 60625.807 | N77: 61706.852 | O77: 72018.538 | P77: 81016.293 | Q77: 132872.01 | R77: 58747.116 | S77: 98028.053 | T77: 91332.179 | U77: 92501.782 | V77: 99153.079 | W77: 104226.87 | X77: 106852.6 | Y77: 88163.434 | Z77: 92692.873 | AA77: 98839.35 | AB77: 106870.42 | AC77: 122494.07
A78: gfcr_ceic | B78: Aceh | C78: Aceh | D78: Aceh | E78: 9862.5385 | F78: 12692.951 | G78: 22373.815 | H78: 14328.231 | I78: 14641.356 | J78: 27776.415 | K78: 26035.113 | L78: 28495.075 | M78: 29222.293 | N78: 28706.885 | O78: 29766.574 | P78: 32980.776 | Q78: 34901.819 | R78: 34736.027 | S78: 36571.543 | T78: 37892.086 | U78: 40598.055 | V78: 39421.958 | W78: 40769.451 | X78: 43513.914 | Y78: 45045.625 | Z78: 45438.248 | AA78: 45103.704 | AB78: 47746.94 | AC78: 49982.89 | AD78: 49237.05
A79: gfcr_ceic | B79: Bali | C79: Bali | D79: Bali | E79: 9875.9022 | F79: 9813.0488 | G79: 10041.721 | H79: 10170.889 | I79: 10895.335 | J79: 11190.482 | K79: 11411.082 | L79: 18751.318 | M79: 23093.932 | N79: 24925.271 | O79: 29142.201 | P79: 33290.009 | Q79: 36322.554 | R79: 38111.983 | S79: 38800.143 | T79: 41397.444 | U79: 45030.742 | V79: 46623.268 | W79: 51076.077 | X79: 52755.13 | Y79: 46598.906 | Z79: 44547.839 | AA79: 45712.963 | AB79: 47091.11 | AC79: 49708.02 | AD79: 52704.12
A80: gfcr_ceic | B80: Bangka Belitung | C80: Kep. Bangka Belitung | D80: Kep. Bangka Belitung | E80: 2700.3037 | F80: 3045.8728 | G80: 3035.568 | H80: 3709.7513 | I80: 5460.1554 | J80: 5801.4512 | K80: 5331.4283 | L80: 6188.6977 | M80: 6899.442 | N80: 7141.4458 | O80: 7515.7223 | P80: 8147.134 | Q80: 8550.0619 | R80: 8970.0596 | S80: 9408.0275 | T80: 9823.5326 | U80: 10450.945 | V80: 11111.34 | W80: 11779.865 | X80: 12453.338 | Y80: 11633.484 | Z80: 12013.636 | AA80: 12412.528 | AB80: 13018.46 | AC80: 12916.29 | AD80: 12871.75
A81: gfcr_ceic | B81: Banten | C81: Banten | D81: Banten | E81: 49834.592 | F81: 53816.102 | G81: 57240.649 | H81: 61387.988 | I81: 67895.276 | J81: 73816.37 | K81: 79006.75 | L81: 64597.024 | M81: 72363.076 | N81: 75786.709 | O81: 81506.594 | P81: 88786.94 | Q81: 96635.331 | R81: 100195.82 | S81: 103115.31 | T81: 109012.81 | U81: 115877.26 | V81: 126304.24 | W81: 135049 | X81: 143667.51 | Y81: 143572.83 | Z81: 149908.85 | AA81: 155430.59 | AB81: 160769.55 | AC81: 164999.07 | AD81: 173496.76
A82: gfcr_ceic | B82: Bengkulu | C82: Bengkulu | D82: Bengkulu | E82: 5064.7566 | F82: 5189.0037 | G82: 5401.8964 | H82: 5617.7067 | I82: 5981.0416 | J82: 6675.2537 | K82: 7086.1244 | L82: 9524.1011 | M82: 10401.271 | N82: 10934.94 | O82: 11578.477 | P82: 12596.437 | Q82: 13674.63 | R82: 14819.652 | S82: 16014.028 | T82: 16572.904 | U82: 17404.345 | V82: 18463.147 | W82: 19497.272 | X82: 20471.499 | Y82: 20134.107 | Z82: 20964.697 | AA82: 21695.686 | AB82: 22383.1 | AC82: 23024.5 | AD82: 23827.83
A83: gfcr_ceic | B83: Central Java | C83: Jawa Tengah | D83: Jawa Tengah | E83: 98899.754 | F83: 87537.342 | G83: 90772.436 | H83: 97419.272 | I83: 110537.14 | J83: 120563.08 | K83: 136111.19 | L83: 143826.42 | M83: 153453.68 | N83: 162080.34 | O83: 175032.48 | P83: 187096.82 | Q83: 202328.21 | R83: 211220.47 | S83: 220772.87 | T83: 232335.2 | U83: 246247.09 | V83: 264716.11 | W83: 285045.11 | X83: 298877.27 | Y83: 278024.57 | Z83: 297028.56 | AA83: 302949.27 | AB83: 315755.79 | AC83: 336453.49 | AD83: 359214.21
A84: gfcr_ceic | B84: Central Kalimantan | C84: Kalimantan Tengah | D84: Kalimantan Tengah | E84: 13224.255 | F84: 13217.453 | G84: 13322.449 | H84: 13959.054 | I84: 14609.268 | J84: 15984.375 | K84: 18083.517 | L84: 19959.592 | M84: 21645.309 | N84: 22118.524 | O84: 24129.344 | P84: 26770.39 | Q84: 28652.114 | R84: 29743.665 | S84: 31910.246 | T84: 34049.499 | U84: 35835.84 | V84: 37275.022 | W84: 39378.103 | X84: 40449.76 | Y84: 39286.655 | Z84: 40539.276 | AA84: 40002.449 | AB84: 42264.5 | AC84: 44449.54 | AD84: 44905.95
A85: gfcr_ceic | B85: Central Papua | C85: Papua Tengah | D85: Papua | AA85: 18616.95 | AB85: 19286.49 | AC85: 19617.7 | AD85: 19357.11
A86: gfcr_ceic | B86: Central Sulawesi | C86: Sulawesi Tengah | D86: Sulawesi Tengah | E86: 8221.5867 | F86: 8682.3114 | G86: 9083.9372 | H86: 9624.3495 | I86: 10272.543 | J86: 11025.128 | K86: 11903.962 | L86: 14523.57 | M86: 15825.836 | N86: 17114.878 | O86: 18388.284 | P86: 21262.487 | Q86: 24156.746 | R86: 26670.476 | S86: 30720.125 | T86: 35082.328 | U86: 39964.673 | V86: 41366.809 | W86: 42083.727 | X86: 50649.309 | Y86: 46703.437 | Z86: 69263.217 | AA86: 85345.313 | AB86: 86318.5 | AC86: 89253.94 | AD86: 90611.61
A87: gfcr_ceic | B87: DI Yogyakarta | C87: DI Yogyakarta | D87: DI Yogyakarta | E87: 10523.5 | F87: 10764.034 | G87: 12060.315 | H87: 13149.825 | I87: 13171.438 | J87: 14055.42 | K87: 15279.734 | L87: 15697.935 | M87: 16368.303 | N87: 16894.106 | O87: 17470.045 | P87: 18245.345 | Q87: 19207.89 | R87: 20190.81 | S87: 21358.622 | T87: 22286.615 | U87: 23616.948 | V87: 24791.862 | W87: 27327.862 | X87: 30021.484 | Y87: 25995.231 | Z87: 28127.239 | AA87: 29774.647 | AB87: 31709.04 | AC87: 34215.01 | AD87: 37034.57
A88: gfcr_ceic | B88: DKI Jakarta | C88: DKI Jakarta | D88: DKI Jakarta | E88: 291773.7 | F88: 287741.52 | G88: 289361.64 | H88: 291885.58 | I88: 332478.73 | J88: 364173.27 | K88: 379684.9 | L88: 405198.47 | M88: 439598.24 | N88: 451735.75 | O88: 491549.15 | P88: 533589.46 | Q88: 585571.05 | R88: 618800.67 | S88: 637777.7 | T88: 654605.16 | U88: 664738.69 | V88: 704826.29 | W88: 737769.03 | X88: 747263.48 | Y88: 695137.42 | Z88: 702452.35 | AA88: 734191.61 | AB88: 762885.9 | AC88: 802516.25 | AD88: 840775.58
A89: gfcr_ceic | B89: East Java | C89: Jawa Timur | D89: Jawa Timur | E89: 166351.68 | F89: 176382.03 | G89: 182086.33 | H89: 185202 | I89: 191693.08 | J89: 207710.89 | K89: 222713.76 | L89: 228741.68 | M89: 242151.06 | N89: 254796.76 | O89: 272954.03 | P89: 289641.72 | Q89: 314921.95 | R89: 330280.83 | S89: 344715.56 | T89: 364831.01 | U89: 386709.4 | V89: 407185.35 | W89: 431922.41 | X89: 453188.7 | Y89: 433893.01 | Z89: 438579.17 | AA89: 462312.49 | AB89: 487230.49 | AC89: 513996.18 | AD89: 542456.78
A90: gfcr_ceic | B90: East Kalimantan | C90: Kalimantan Timur | D90: Kalimantan Timur | E90: 46055.27 | F90: 54898.704 | G90: 59884.901 | H90: 65025.345 | I90: 67301.45 | J90: 71371.799 | K90: 77281.913 | L90: 81435.441 | M90: 88928.972 | N90: 92460.169 | O90: 97159.066 | P90: 105497.5 | Q90: 110334.68 | R90: 111846.99 | S90: 117106.16 | T90: 115380.24 | U90: 108405.55 | V90: 111386.67 | W90: 119779.85 | X90: 125537.61 | Y90: 124207.97 | Z90: 133824.11 | AA90: 141346.17 | AB90: 157598.52 | AC90: 170659.77 | AD90: 174089.88
A91: gfcr_ceic | B91: East Nusa Tenggara | C91: Nusa Tenggara Timur | D91: Nusa Tenggara Timur | E91: 12449.221 | F91: 13205.173 | G91: 13872.855 | H91: 9204.8727 | I91: 9586.4304 | J91: 9914.3702 | K91: 10414.004 | L91: 10715.169 | M91: 11026.361 | N91: 12768.918 | O91: 14015.892 | P91: 14723.677 | Q91: 15844.365 | R91: 17614.838 | S91: 22195.978 | T91: 24832.317 | U91: 28741.681 | V91: 30527.237 | W91: 32035.755 | X91: 33794.457 | Y91: 30989.782 | Z91: 32473.642 | AA91: 32304.85 | AB91: 34294.47 | AC91: 34892.83 | AD91: 34757.11
A92: gfcr_ceic | B92: Gorontalo | C92: Gorontalo | D92: Gorontalo | E92: 1205.7433 | F92: 1579.4396 | G92: 1640.5429 | H92: 2332.3526 | I92: 3244.8034 | J92: 3540.2468 | K92: 3820.2192 | L92: 4179.1231 | M92: 4398.2527 | N92: 4622.9581 | O92: 4863.9703 | P92: 5288.3445 | Q92: 5726.685 | R92: 6188.2754 | S92: 6722.0788 | T92: 7317.3801 | U92: 7721.2895 | V92: 7956.7846 | W92: 8285.5089 | X92: 8559.357 | Y92: 8474.6846 | Z92: 8714.4374 | AA92: 8873.4931 | AB92: 9187.36 | AC92: 9516.55 | AD92: 10056.98
A93: gfcr_ceic | B93: Jambi | C93: Jambi | D93: Jambi | E93: 10436.526 | F93: 12341.134 | G93: 12658.359 | H93: 13706.5 | I93: 15128.463 | J93: 14564.563 | K93: 16754.176 | L93: 18015.186 | M93: 19579.076 | N93: 20212.383 | O93: 21601.723 | P93: 21571.04 | Q93: 25926.188 | R93: 28266.692 | S93: 28117.165 | T93: 27834.649 | U93: 29038.987 | V93: 30127.534 | W93: 30777.992 | X93: 31894.296 | Y93: 32226.99 | Z93: 35215.518 | AA93: 36100.051 | AB93: 39667.38 | AC93: 42357.57 | AD93: 42622.42
A94: gfcr_ceic | B94: Lampung | C94: Lampung | D94: Lampung | E94: 30448.188 | F94: 29075.817 | G94: 32799.966 | H94: 32653.291 | I94: 31681.198 | J94: 34925.95 | K94: 35793.165 | L94: 37697.675 | M94: 39515.497 | N94: 41024.424 | O94: 43927.327 | P94: 49058.861 | Q94: 53646.824 | R94: 55690.805 | S94: 58841.761 | T94: 62035.82 | U94: 67779.396 | V94: 72861.898 | W94: 79145.389 | X94: 82804.963 | Y94: 78790.293 | Z94: 81913.308 | AA94: 83896.771 | AB94: 87373.16 | AC94: 88928.18 | AD94: 93620.1
A95: gfcr_ceic | B95: Maluku | C95: Maluku | D95: Maluku | E95: 1742.3354 | F95: 1769.0585 | G95: 2082.1101 | H95: 2304.8482 | I95: 2455.8915 | J95: 2599.0699 | K95: 2787.2492 | L95: 3144.9704 | M95: 3534.3433 | N95: 3776.0009 | O95: 4385.6166 | P95: 5173.8677 | Q95: 6281.1712 | R95: 6968.0082 | S95: 7344.1757 | T95: 7619.5878 | U95: 8177.0124 | V95: 8679.3595 | W95: 9427.7486 | X95: 9999.0578 | Y95: 9790.4211 | Z95: 10075.803 | AA95: 10178.451 | AB95: 10273.04 | AC95: 10481.14 | AD95: 10578.07
A96: gfcr_ceic | B96: North Kalimantan | C96: Kalimantan Utara | D96: Kalimantan Utara | O96: 11346.012 | P96: 11649.507 | Q96: 12389.875 | R96: 13122.172 | S96: 14043.441 | T96: 15246.053 | U96: 16317.819 | V96: 16969.655 | W96: 17840.023 | X96: 19068.549 | Y96: 18489.758 | Z96: 18609.925 | AA96: 19050.233 | AB96: 20788.96 | AC96: 22210.3 | AD96: 23203.48
A97: gfcr_ceic | B97: North Maluku | C97: Maluku Utara | D97: Maluku Utara | E97: 871.38184 | F97: 1017.2458 | G97: 1080.7587 | H97: 1039.2965 | I97: 1105.6238 | J97: 1531.9695 | K97: 1898.4517 | L97: 2162.9066 | M97: 2663.9531 | N97: 3293.5645 | O97: 3431.1721 | P97: 4212.3983 | Q97: 4659.0838 | R97: 5026.4942 | S97: 5251.2335 | T97: 5786.4017 | U97: 6414.637 | V97: 7373.4866 | W97: 7196.5992 | X97: 13156.471 | Y97: 16821.606 | Z97: 18585.603 | AA97: 29994.854 | AB97: 24118.86 | AC97: 26554.82 | AD97: 33293.67
A98: gfcr_ceic | B98: North Sulawesi | C98: Sulawesi Utara | D98: Sulawesi Utara | E98: 8743.1278 | F98: 9376.5091 | G98: 9942.53 | H98: 9572.3986 | I98: 10217.867 | J98: 11430.354 | K98: 13117.155 | L98: 15785.393 | M98: 18172.793 | N98: 19479.853 | O98: 20141.036 | P98: 21961.154 | Q98: 22369.519 | R98: 23331.262 | S98: 23801.172 | T98: 26067.779 | U98: 27710.484 | V98: 29718.183 | W98: 30806.129 | X98: 32653.618 | Y98: 30777.572 | Z98: 33257.803 | AA98: 34255.067 | AB98: 35137.47 | AC98: 36500.98 | AD98: 36778.14
A99: gfcr_ceic | B99: North Sumatera | C99: Sumatera Utara | D99: Sumatera Utara | E99: 45469.779 | F99: 42978.361 | G99: 51400.902 | H99: 52155.042 | I99: 55799.464 | J99: 62272.679 | K99: 70589.375 | L99: 79966.554 | M99: 88863.947 | N99: 94844.286 | O99: 99539.597 | P99: 105474.68 | Q99: 114503.16 | R99: 120436.36 | S99: 124148.57 | T99: 128952.21 | U99: 135207.98 | V99: 142013.73 | W99: 150803.37 | X99: 163244.13 | Y99: 161327.64 | Z99: 166914.74 | AA99: 173314.81 | AB99: 181084.17 | AC99: 190051.09 | AD99: 191108.51
A100: gfcr_ceic | B100: Papua | C100: Papua | D100: Papua | E100: 11513.49 | F100: 12427.424 | G100: 9171.4074 | H100: 9870.0564 | I100: 10844.365 | J100: 11786.864 | K100: 15120.964 | L100: 18164.089 | M100: 20543.125 | N100: 22782.92 | O100: 25009.776 | P100: 27037.629 | Q100: 28882.225 | R100: 30778.247 | S100: 33168.026 | T100: 35524.778 | U100: 37824.227 | V100: 39870.096 | W100: 42576.324 | X100: 44058.797 | Y100: 43396.204 | Z100: 47620.329 | AA100: 48650.252 | AB100: 50154.74 | AC100: 18267.38 | AD100: 18554.34
...

Sheet WIDE_CEIC
A1: prov | B1: prov_name | C1: indicator | D1: 2000 | E1: 2001 | F1: 2002 | G1: 2003 | H1: 2004 | I1: 2005 | J1: 2006 | K1: 2007 | L1: 2008 | M1: 2009 | N1: 2010 | O1: 2011 | P1: 2012 | Q1: 2013 | R1: 2014 | S1: 2015 | T1: 2016 | U1: 2017 | V1: 2018 | W1: 2019 | X1: 2020 | Y1: 2021 | Z1: 2022 | AA1: 2023 | AB1: 2024 | AC1: 2025
A2: =VLOOKUP(B2,Legend!$C$32:$D$66,2,FALSE) -> 11 | B2: Aceh | C2: agrr_ceic | D2: 21575.61 | E2: 20882.8 | F2: 21327.97 | G2: 22025.17 | H2: 23356.22 | I2: 22447.34 | J2: 22788.31 | K2: 23612.76 | L2: 23803.54 | M2: 24412.68 | N2: 25579.57 | O2: 26515.48 | P2: 27685.11 | Q2: 28980.43 | R2: 29690.56 | S2: 31186.38 | T2: 32355.09 | U2: 34052.85 | V2: 35426.16 | W2: 36626.71 | X2: 37899.52 | Y2: 37768.08 | Z2: 39005.09 | AA2: 41626.32 | AB2: 42121.38 | AC2: 43637.59
A3: =VLOOKUP(B3,Legend!$C$32:$D$66,2,FALSE) -> 12 | B3: Sumatera Utara | C3: agrr_ceic | D3: 57864.17 | E3: 60061.78 | F3: 61584.13 | G3: 63131.37 | H3: 65499.04 | I3: 67713.98 | J3: 69340.93 | K3: 72794.06 | L3: 77201.71 | M3: 80943.58 | N3: 85561.14 | O3: 90592.55 | P3: 95405.42 | Q3: 99894.57 | R3: 104262.83 | S3: 110066 | T3: 115179.69 | U3: 121300.04 | V3: 127202.65 | W3: 133726.02 | X3: 136327.03 | Y3: 141601.18 | Z3: 148721.97 | AA3: 153246.71 | AB3: 158940.62 | AC3: 166702.96
A4: =VLOOKUP(B4,Legend!$C$32:$D$66,2,FALSE) -> 13 | B4: Sumatera Barat | C4: agrr_ceic | D4: 16086.3 | E4: 16870.1 | F4: 18196.02 | G4: 19586.71 | H4: 20720.73 | I4: 21784.17 | J4: 22874.96 | K4: 24011.55 | L4: 25325.98 | M4: 26205.69 | N4: 27277.72 | O4: 28535.02 | P4: 29284.9 | Q4: 30372.99 | R4: 32151.49 | S4: 33546.76 | T4: 34222.56 | U4: 35394.69 | V4: 36639.6 | W4: 37549.46 | X4: 37993.39 | Y4: 38820.71 | Z4: 40188.63 | AA4: 41612.83 | AB4: 42467.73 | AC4: 44227.28
A5: =VLOOKUP(B5,Legend!$C$32:$D$66,2,FALSE) -> 14 | B5: Riau | C5: agrr_ceic | D5: 59133.63 | E5: 62824.44 | F5: 66608.53 | G5: 63611.7 | H5: 68065.58 | I5: 72673.07 | J5: 77010.89 | K5: 80739.72 | L5: 84607.9 | M5: 87757.75 | N5: 91152.77 | O5: 94307.4 | P5: 97910.95 | Q5: 102216.74 | R5: 108498.09 | S5: 108969.04 | T5: 113287.59 | U5: 119281.64 | V5: 124547.86 | W5: 129690.41 | X5: 135124.21 | Y5: 140717.74 | Z5: 144691.04 | AA5: 149361.11 | AB5: 152698.4 | AC5: 160178.56
A6: =VLOOKUP(B6,Legend!$C$32:$D$66,2,FALSE) -> 15 | B6: Jambi | C6: agrr_ceic | D6: 13821.41 | E6: 14334.5 | F6: 15029.5 | G6: 15563.87 | H6: 16354.9 | I6: 17108.3 | J6: 19047.67 | K6: 19917.72 | L6: 21056.68 | M6: 22458.21 | N6: 23627.24 | O6: 24744.88 | P6: 26429.05 | Q6: 28070.96 | R6: 31145.43 | S6: 32846.19 | T6: 34933.69 | U6: 36809.09 | V6: 38041.61 | W6: 39160.08 | X6: 39751.94 | Y6: 41209.13 | Z6: 43268.38 | AA6: 45698.37 | AB6: 47643.01 | AC6: 50259.68
A7: =VLOOKUP(B7,Legend!$C$32:$D$66,2,FALSE) -> 16 | B7: Sumatera Selatan | C7: agrr_ceic | D7: 23259.1 | E7: 24246.67 | F7: 25345.81 | G7: 26609.16 | H7: 28243.27 | I7: 29902.61 | J7: 31828.85 | K7: 33891.45 | L7: 35276.2 | M7: 36371.82 | N7: 38067.01 | O7: 40120.77 | P7: 42557.3 | Q7: 44794.97 | R7: 46612.03 | S7: 48287.68 | T7: 48942.64 | U7: 49518.88 | V7: 50674.28 | W7: 52366.83 | X7: 53281.53 | Y7: 54834.53 | Z7: 56926.73 | AA7: 58154.46 | AB7: 59555.29 | AC7: 63001.27
A8: =VLOOKUP(B8,Legend!$C$32:$D$66,2,FALSE) -> 17 | B8: Bengkulu | C8: agrr_ceic | D8: 5728.65 | E8: 5937.16 | F8: 6202.04 | G8: 6565.87 | H8: 6928.19 | I8: 7331.42 | J8: 7751.37 | K8: 8189.66 | L8: 8643.42 | M8: 9119.25 | N8: 9343.96 | O8: 9734.67 | P8: 10272.89 | Q8: 10687.21 | R8: 10950.44 | S8: 11197.98 | T8: 11551.54 | U8: 11929.47 | V8: 12309.49 | W8: 12747.26 | X8: 12795.99 | Y8: 13109.72 | Z8: 13699.33 | AA8: 13981.69 | AB8: 14341.27 | AC8: 14930.39
A9: =VLOOKUP(B9,Legend!$C$32:$D$66,2,FALSE) -> 18 | B9: Lampung | C9: agrr_ceic | D9: 36401.86 | E9: 37589.5 | F9: 38093.11 | G9: 39660.9 | H9: 41879.08 | I9: 43834.02 | J9: 46198.15 | K9: 48747.48 | L9: 50168.11 | M9: 51486.83 | N9: 52038.77 | O9: 54841.03 | P9: 56997.47 | Q9: 59636.49 | R9: 61595.15 | S9: 63745.49 | T9: 65730.54 | U9: 66297.14 | V9: 66941.02 | W9: 67848.65 | X9: 68312.25 | Y9: 67969.86 | Z9: 69317.66 | AA9: 69697.99 | AB9: 68339.77 | AC9: 72381.45
A10: =VLOOKUP(B10,Legend!$C$32:$D$66,2,FALSE) -> 19 | B10: Kep. Bangka Belitung | C10: agrr_ceic | D10: 3798.22 | E10: 4111.44 | F10: 4317.44 | G10: 4410.78 | H10: 4606.99 | I10: 4824.45 | J10: 5090.6 | K10: 5244.62 | L10: 5457.99 | M10: 5658.28 | N10: 6097.69 | O10: 6642.8 | P10: 7072.89 | Q10: 7557.66 | R10: 8254.34 | S10: 8743.51 | T10: 9123.19 | U10: 9095.69 | V10: 9589.72 | W10: 9862.83 | X10: 10666.36 | Y10: 10768.72 | Z10: 10875.68 | AA10: 11281.88 | AB10: 11634.94 | AC10: 12003.87
A11: =VLOOKUP(B11,Legend!$C$32:$D$66,2,FALSE) -> 21 | B11: Kep. Riau | C11: agrr_ceic | G11: 3288.86 | H11: 3476.17 | I11: 3663.79 | J11: 3862.14 | K11: 4105.26 | L11: 4261.11 | M11: 4324.91 | N11: 4506.56 | O11: 4683.47 | P11: 4794.17 | Q11: 5000.01 | R11: 5378.15 | S11: 5689.22 | T11: 6018.41 | U11: 5945.61 | V11: 5757.78 | W11: 5717.73 | X11: 5466.78 | Y11: 5322.05 | Z11: 5601.86 | AA11: 5687.64 | AB11: 5720.17 | AC11: 5919.88
A12: =VLOOKUP(B12,Legend!$C$32:$D$66,2,FALSE) -> 31 | B12: DKI Jakarta | C12: agrr_ceic | D12: 1640.57 | E12: 1594.77 | F12: 1448.79 | G12: 1221.17 | H12: 1205.61 | I12: 1218.29 | J12: 1232.01 | K12: 1251.06 | L12: 1260.72 | M12: 1265.06 | N12: 1275.63 | O12: 1277.28 | P12: 1319.31 | Q12: 1353.56 | R12: 1359.95 | S12: 1375.42 | T12: 1387.53 | U12: 1391.53 | V12: 1394.05 | W12: 1398.22 | X12: 1405.1 | Y12: 1463.34 | Z12: 1501.26 | AA12: 1443.04 | AB12: 1516.95 | AC12: 1561.67
A13: =VLOOKUP(B13,Legend!$C$32:$D$66,2,FALSE) -> 32 | B13: Jawa Barat | C13: agrr_ceic | D13: 60856.34 | E13: 67181.71 | F13: 66846.15 | G13: 68505.57 | H13: 72851.48 | I13: 73875.4 | J13: 73621.7 | K13: 75451.5 | L13: 78522.4 | M13: 88209.99 | N13: 89088.26 | O13: 88386.51 | P13: 88409.46 | Q13: 92390.13 | R13: 92653.58 | S13: 92802.8 | T13: 98096.58 | U13: 99669.37 | V13: 101752.2 | W13: 104596.75 | X13: 107000.79 | Y13: 108406.55 | Z13: 113186.39 | AA13: 113308.41 | AB13: 115104.77 | AC13: 126696.51
A14: =VLOOKUP(B14,Legend!$C$32:$D$66,2,FALSE) -> 33 | B14: Jawa Tengah | C14: agrr_ceic | D14: 74414.1 | E14: 75249.33 | F14: 78974.16 | G14: 77357.68 | H14: 81484.1 | I14: 85239.54 | J14: 88308.93 | K14: 90760.04 | L14: 93659.82 | M14: 97136.21 | N14: 99572.44 | O14: 103389.33 | P14: 106536.7 | Q14: 108832.11 | R14: 107793.38 | S14: 113826.3 | T14: 116331.12 | U14: 118450.17 | V14: 121554.48 | W14: 123150.02 | X14: 126111.76 | Y14: 127065.84 | Z14: 130762.52 | AA14: 131330.54 | AB14: 133162.54 | AC14: 139530.4
A15: =VLOOKUP(B15,Legend!$C$32:$D$66,2,FALSE) -> 34 | B15: DI Yogyakarta | C15: agrr_ceic | D15: 5533.2 | E15: 5759.8 | F15: 5860.64 | G15: 5886.44 | H15: 6095.14 | I15: 6360.34 | J15: 6602.23 | K15: 6655.05 | L15: 7035.5 | M15: 7272.59 | N15: 7252.6 | O15: 7134.68 | P15: 7500.73 | Q15: 7670.03 | R15: 7508.98 | S15: 7667.6 | T15: 7779.8 | U15: 7930.31 | V15: 8101.23 | W15: 8184.19 | X15: 8534.64 | Y15: 8638.19 | Z15: 9077.78 | AA15: 9194.03 | AB15: 9206.5 | AC15: 9791.84
A16: =VLOOKUP(B16,Legend!$C$32:$D$66,2,FALSE) -> 35 | B16: Jawa Timur | C16: agrr_ceic | D16: 104112.98 | E16: 105425.77 | F16: 107560.12 | G16: 109612.12 | H16: 112702.18 | I16: 116264.13 | J16: 118147.24 | K16: 121859.06 | L16: 125664.22 | M16: 130589.82 | N16: 133504.56 | O16: 138870.09 | P16: 146002.57 | Q16: 150463.72 | R16: 155783.96 | S16: 160889.4 | T16: 164762.91 | U16: 167360.57 | V16: 163799.94 | W16: 165951.23 | X16: 167631.24 | Y16: 170556.77 | Z16: 173747.56 | AA16: 177668.37 | AB16: 177809.47 | AC16: 186662.71
A17: =VLOOKUP(B17,Legend!$C$32:$D$66,2,FALSE) -> 36 | B17: Banten | C17: agrr_ceic | D17: 10985.99 | E17: 11506.54 | F17: 11692.12 | G17: 12037.69 | H17: 12287.14 | I17: 12614.58 | J17: 12535.72 | K17: 14118.95 | L17: 14569.42 | M17: 15354.49 | N17: 16737.61 | O17: 17242.08 | P17: 17793.38 | Q17: 18990.92 | R17: 19456.95 | S17: 20743.47 | T17: 22108.75 | U17: 23055.55 | V17: 23880.77 | W17: 24408.33 | X17: 25275.08 | Y17: 25416.58 | Z17: 26490.53 | AA17: 26531.3 | AB17: 26703.35 | AC17: 29266.23
A18: =VLOOKUP(B18,Legend!$C$32:$D$66,2,FALSE) -> 51 | B18: Bali | C18: agrr_ceic | D18: 10487.44 | E18: 11082.48 | F18: 11488.73 | G18: 11905.69 | H18: 12341.19 | I18: 12858.93 | J18: 13386.6 | K18: 14618.96 | L18: 14963.8 | M18: 15813.19 | N18: 16092.72 | O18: 16258.74 | P18: 16969.88 | Q18: 17343.29 | R18: 18151.21 | S18: 18637.35 | T18: 19295.7 | U18: 19821.71 | V18: 20760.22 | W18: 21479.55 | X18: 21269.19 | Y18: 21338.45 | Z18: 21157.3 | AA18: 21058.7 | AB18: 21586.55 | AC18: 21954.29
A19: =VLOOKUP(B19,Legend!$C$32:$D$66,2,FALSE) -> 52 | B19: Nusa Tenggara Barat | C19: agrr_ceic | D19: 11680.7 | E19: 11610.91 | F19: 11756.51 | G19: 12301.62 | H19: 12624.99 | I19: 12746.37 | J19: 13113.49 | K19: 13493.58 | L19: 14239.44 | M19: 14743.1 | N19: 14939.02 | O19: 15691.91 | P19: 16407.44 | Q19: 16946.74 | R19: 17702.37 | S19: 18964.88 | T19: 19564.75 | U19: 20843.23 | V19: 21262.43 | W19: 21555.36 | X19: 21466.1 | Y19: 21712.18 | Z19: 22187.32 | AA19: 22642.74 | AB19: 22992.48 | AC19: 24150
A20: =VLOOKUP(B20,Legend!$C$32:$D$66,2,FALSE) -> 53 | B20: Nusa Tenggara Timur | C20: agrr_ceic | D20: 10469.09 | E20: 10799.67 | F20: 11205.53 | G20: 11435.39 | H20: 11835.1 | I20: 11949.36 | J20: 12540.98 | K20: 12884.94 | L20: 13379.21 | M20: 13684.3 | N20: 13963.14 | O20: 14244.98 | P20: 14669.95 | Q20: 15069.63 | R20: 15613.95 | S20: 16123.17 | T20: 16512.69 | U20: 17328.87 | V20: 17837.81 | W20: 18496.01 | X20: 18680.64 | Y20: 19601.9 | Z20: 20341.73 | AA20: 20842.3 | AB20: 21224.74 | AC20: 21967.56
A21: =VLOOKUP(B21,Legend!$C$32:$D$66,2,FALSE) -> 61 | B21: Kalimantan Barat | C21: agrr_ceic | D21: 14734.24 | E21: 14333.19 | F21: 15365.42 | G21: 15834.1 | H21: 16210.1 | I21: 16964.12 | J21: 17869.57 | K21: 18740.84 | L21: 19820.43 | M21: 20610.8 | N21: 21485.41 | O21: 22292.71 | P21: 23201.41 | Q21: 24401.6 | R21: 24967.38 | S21: 25571.67 | T21: 26618.92 | U21: 28357.68 | V21: 30209.4 | W21: 31956.43 | X21: 32371.35 | Y21: 33811.57 | Z21: 34547.57 | AA21: 35108.57 | AB21: 36150.73 | AC21: 36926.67
A22: =VLOOKUP(B22,Legend!$C$32:$D$66,2,FALSE) -> 62 | B22: Kalimantan Tengah | C22: agrr_ceic | D22: 11342.89 | E22: 11846.56 | F22: 11594.9 | G22: 12535.97 | H22: 12561.59 | I22: 12695.63 | J22: 13122.8 | K22: 13175.81 | L22: 13118.8 | M22: 13541.43 | N22: 13935.36 | O22: 14165.41 | P22: 14536.58 | Q22: 15028.38 | R22: 16080.17 | S22: 17031.88 | T22: 17686.42 | U22: 18514.01 | V22: 19824.58 | W22: 21250.83 | X22: 21304.92 | Y22: 22073.16 | Z22: 22834.25 | AA22: 23830.77 | AB22: 24138.62 | AC22: 25090.12
A23: =VLOOKUP(B23,Legend!$C$32:$D$66,2,FALSE) -> 63 | B23: Kalimantan Selatan | C23: agrr_ceic | D23: 8386.9 | E23: 9058.77 | F23: 9309.45 | G23: 9585.57 | H23: 10161.95 | I23: 10680.79 | J23: 11182.38 | K23: 11822.1 | L23: 12618.34 | M23: 13419.22 | N23: 13701.55 | O23: 14052.46 | P23: 14490.15 | Q23: 14967.33 | R23: 15636.19 | S23: 16013.3 | T23: 16600.74 | U23: 17280.42 | V23: 17925.11 | W23: 18568.23 | X23: 18399.41 | Y23: 18614.34 | Z23: 18911.08 | AA23: 19537.28 | AB23: 20350.73 | AC23: 21717.59
A24: =VLOOKUP(B24,Legend!$C$32:$D$66,2,FALSE) -> 64 | B24: Kalimantan Timur | C24: agrr_ceic | D24: 16282.68 | E24: 16580.67 | F24: 17030 | G24: 17214.66 | H24: 17708.7 | I24: 18161.03 | J24: 18806.2 | K24: 19141.98 | L24: 19698.74 | M24: 19993.01 | N24: 21167.77 | O24: 22292.61 | P24: 23991.79 | Q24: 25535.67 | R24: 27267.2 | S24: 28506.91 | T24: 28639.4 | U24: 30261.4 | V24: 32140.16 | W24: 33355.19 | X24: 33026.69 | Y24: 33003.9 | Z24: 33712.58 | AA24: 34551.18 | AB24: 35368.75 | AC24: 38094.43
A25: =VLOOKUP(B25,Legend!$C$32:$D$66,2,FALSE) -> 65 | B25: Kalimantan Utara | C25: agrr_ceic | N25: 6235.36 | O25: 6676.56 | P25: 7130 | Q25: 7496.93 | R25: 8021.34 | S25: 8574.02 | T25: 9022 | U25: 9423 | V25: 9941.19 | W25: 10475.64 | X25: 10925.64 | Y25: 11300.51 | Z25: 11723.08 | AA25: 12229.92 | AB25: 12444.24 | AC25: 12767.3
A26: =VLOOKUP(B26,Legend!$C$32:$D$66,2,FALSE) -> 71 | B26: Sulawesi Utara | C26: agrr_ceic | D26: 7667.12 | E26: 7964.89 | F26: 8320.34 | G26: 8392.96 | H26: 8947.76 | I26: 9497.69 | J26: 9740.67 | K26: 10479.52 | L26: 11089.02 | M26: 11318.59 | N26: 12281.01 | O26: 12154.19 | P26: 12918.08 | Q26: 13765.3 | R26: 14243.12 | S26: 14605.52 | T26: 15141.89 | U26: 15814.32 | V26: 16367.26 | W26: 17320.48 | X26: 17705.45 | Y26: 18040.14 | Z26: 19187.16 | AA26: 20036.33 | AB26: 21113.98 | AC26: 22337.2
A27: =VLOOKUP(B27,Legend!$C$32:$D$66,2,FALSE) -> 72 | B27: Sulawesi Tengah | C27: agrr_ceic | D27: 10450.93 | E27: 11123.93 | F27: 11885.49 | G27: 12772.13 | H27: 13766.84 | I27: 14650.9 | J27: 15448.99 | K27: 16550.24 | L27: 17312.7 | M27: 18419.21 | N27: 19523.49 | O27: 20711.36 | P27: 21923.49 | Q27: 23163.93 | R27: 24728.72 | S27: 26297.82 | T27: 26929.49 | U27: 28131.33 | V27: 29340.85 | W27: 29995.99 | X27: 29593.65 | Y27: 30793.12 | Z27: 31639.57 | AA27: 32224.74 | AB27: 32848.02 | AC27: 34309.75
A28: =VLOOKUP(B28,Legend!$C$32:$D$66,2,FALSE) -> 73 | B28: Sulawesi Selatan | C28: agrr_ceic | D28: 33353.51 | E28: 33671.01 | F28: 35218.73 | G28: 35478.6 | H28: 35240.91 | I28: 32427.95 | J28: 33757.98 | K28: 34842.74 | L28: 36963.89 | M28: 38695.1 | N28: 39598.91 | O28: 42325.57 | P28: 44263.48 | Q28: 46446.73 | R28: 51101.68 | S28: 54099.1 | T28: 58351.27 | U28: 61597.2 | V28: 64815.46 | W28: 66615.94 | X28: 66139.9 | Y28: 70357.8 | Z28: 72162.73 | AA28: 72226.31 | AB28: 75166.74 | AC28: 80474.87
A29: =VLOOKUP(B29,Legend!$C$32:$D$66,2,FALSE) -> 74 | B29: Sulawesi Tenggara | C29: agrr_ceic | D29: 8231.62 | E29: 8673.44 | F29: 9302.72 | G29: 9875.04 | H29: 10649.04 | I29: 11385.14 | J29: 11905.93 | K29: 12572.51 | L29: 13205.9 | M29: 13566.97 | N29: 13741.14 | O29: 14007.46 | P29: 14625.41 | Q29: 15508.22 | R29: 16952.31 | S29: 16970.46 | T29: 18270.18 | U29: 19323.26 | V29: 20554.63 | W29: 21581.03 | X29: 21728.37 | Y29: 22247.11 | Z29: 23754.98 | AA29: 24779.74 | AB29: 25734.91 | AC29: 26698.67
A30: =VLOOKUP(B30,Legend!$C$32:$D$66,2,FALSE) -> 75 | B30: Gorontalo | C30: agrr_ceic | D30: 3287.79 | E30: 3519.47 | F30: 3826.86 | G30: 3998.73 | H30: 4125.14 | I30: 4432.57 | J30: 4784.47 | K30: 5134.78 | L30: 5548.66 | M30: 5742.5 | N30: 5977.73 | O30: 6321.23 | P30: 6763.85 | Q30: 7232.59 | R30: 7698.32 | S30: 8024.61 | T30: 8540.36 | U30: 9314.37 | V30: 10019.05 | W30: 10652.83 | X30: 10478.78 | Y30: 10663.64 | Z30: 10907.95 | AA30: 11365.5 | AB30: 11719.48 | AC30: 12205.24
A31: =VLOOKUP(B31,Legend!$C$32:$D$66,2,FALSE) -> 76 | B31: Sulawesi Barat | C31: agrr_ceic | H31: 5507.7224 | I31: 5684.53 | J31: 5934.41 | K31: 6146.94 | L31: 6338.3 | M31: 6535.66 | N31: 7486.61 | O31: 8115.11 | P31: 8709.5 | Q31: 9207.15 | R31: 9753.26 | S31: 10313.54 | T31: 10734.08 | U31: 11433.15 | V31: 12131.88 | W31: 12692.97 | X31: 12761.98 | Y31: 12910.29 | Z31: 13342.96 | AA31: 13878.49 | AB31: 14541.57 | AC31: 15421.69
A32: =VLOOKUP(B32,Legend!$C$32:$D$66,2,FALSE) -> 81 | B32: Maluku | C32: agrr_ceic | D32: 3670.3 | E32: 3627.36 | F32: 3663.05 | G32: 3734.53 | H32: 3839.09 | I32: 3978.62 | J32: 4096.73 | K32: 4265.79 | L32: 4388.96 | M32: 4567.08 | N32: 4825.72 | O32: 4972.6 | P32: 5282.61 | Q32: 5500.92 | R32: 5835.44 | S32: 5908.36 | T32: 6188.01 | U32: 6558.6 | V32: 6858.55 | W32: 7230.24 | X32: 7353.71 | Y32: 7409.16 | Z32: 7833.24 | AA32: 8276.73 | AB32: 8557.59 | AC32: 9106.61
A33: =VLOOKUP(B33,Legend!$C$32:$D$66,2,FALSE) -> 82 | B33: Maluku Utara | C33: agrr_ceic | D33: 2514.56 | E33: 2562.49 | F33: 2645.37 | G33: 2768.44 | H33: 2848.76 | I33: 2974.86 | J33: 3116.28 | K33: 4102.26 | L33: 3936.69 | M33: 3739.01 | N33: 3936.69 | O33: 4105.56 | P33: 4371.36 | Q33: 4525.96 | R33: 4662.5 | S33: 4742.55 | T33: 4943.91 | U33: 5100.39 | V33: 5305.88 | W33: 5518.06 | X33: 5594.84 | Y33: 5727.23 | Z33: 5911.57 | AA33: 6162.71 | AB33: 6440.92 | AC33: 6646.89
A34: =VLOOKUP(B34,Legend!$C$32:$D$66,2,FALSE) -> 91 | B34: Papua Barat | C34: agrr_ceic | F34: 3429.79 | G34: 3603.52 | H34: 3744.32 | I34: 3821.22 | J34: 3946.88 | K34: 4152.88 | L34: 4439.14 | M34: 4609.14 | N34: 4889.56 | O34: 4583.19 | P34: 4785.62 | Q34: 5090.42 | R34: 5343.52 | S34: 5482.57 | T34: 5598.84 | U34: 5926.64 | V34: 6058.67 | W34: 6273.1 | X34: 6122.47 | Y34: 6182.41 | Z34: 6199.07 | AA34: 6138.58 | AB34: 6159.84 | AC34: 6351.07
A35: =VLOOKUP(B35,Legend!$C$32:$D$66,2,FALSE) -> 94 | B35: Papua | C35: agrr_ceic | D35: 11391.95 | E35: 12512.43 | F35: 8854.27 | G35: 9280.62 | H35: 9223.47 | I35: 9668.39 | J35: 10171.16 | K35: 10309.74 | L35: 10793.27 | M35: 11248.9 | N35: 11681.13 | O35: 12133.26 | P35: 12883.7 | Q35: 13661.8 | R35: 14432.99 | S35: 15192.6 | T35: 15461.69 | U35: 16070.49 | V35: 16602.56 | W35: 16608.11 | X35: 16490.61 | Y35: 16755.83 | Z35: 27384.44 | AA35: 17526.16 | AB35: 17793.55 | AC35: 18502.6
A36: =VLOOKUP(B36,Legend!$C$32:$D$66,2,FALSE) -> 11 | B36: Aceh | C36: expr_ceic | D36: 126799.83 | E36: 120175.9 | F36: 136014.13 | G36: 139803.4 | H36: 113537.39 | I36: 79008.045 | J36: 68539.979 | K36: 70084.721 | L36: 66412.571 | M36: 52053.677 | N36: 48794.255 | O36: 48189.041 | P36: 49148.162 | Q36: 48786.604 | R36: 47198.272 | S36: 45570.602 | T36: 46196.343 | U36: 50893.467 | V36: 52747.141 | W36: 52517.086 | X36: 52072.394 | Y36: 54937.198 | Z36: 68395.63 | AA36: 76810.85 | AB36: 81753.39 | AC36: 88632.84
A37: =VLOOKUP(B37,Legend!$C$32:$D$66,2,FALSE) -> 12 | B37: Sumatera Utara | C37: expr_ceic | D37: 66631.127 | E37: 75113.063 | F37: 76998.672 | G37: 80887.252 | H37: 99141.187 | I37: 105554.94 | J37: 101650.59 | K37: 111052.67 | L37: 122585.85 | M37: 121424.19 | N37: 133920.53 | O37: 155912.64 | P37: 159278.56 | Q37: 178463.32 | R37: 191872.58 | S37: 189848.62 | T37: 194929.51 | U37: 208689.48 | V37: 222718.56 | W37: 218152.13 | X37: 195680.31 | Y37: 223930.56 | Z37: 249627.87 | AA37: 248219.13 | AB37: 276532.14
A38: =VLOOKUP(B38,Legend!$C$32:$D$66,2,FALSE) -> 13 | B38: Sumatera Barat | C38: expr_ceic | D38: 14680.411 | E38: 15000.74 | F38: 17739.328 | G38: 20748.064 | H38: 26849.193 | I38: 32540.888 | J38: 38468.564 | K38: 49587.429 | L38: 60625.807 | M38: 61706.852 | N38: 72018.538 | O38: 81016.293 | P38: 132872.01 | Q38: 58747.116 | R38: 98028.053 | S38: 91332.179 | T38: 92501.782 | U38: 99153.079 | V38: 104226.87 | W38: 106852.6 | X38: 88163.434 | Y38: 92692.873 | Z38: 98839.35 | AA38: 106870.42 | AB38: 122494.07
A39: =VLOOKUP(B39,Legend!$C$32:$D$66,2,FALSE) -> 14 | B39: Riau | C39: expr_ceic | D39: 227774.34 | E39: 335229.79 | F39: 289578.7 | G39: 186245.16 | H39: 189927.1 | I39: 199143.25 | J39: 207868.62 | K39: 220898.35 | L39: 235674.78 | M39: 226771.24 | N39: 229801.07 | O39: 268075.13 | P39: 293195.74 | Q39: 285085.39 | R39: 242929.36 | S39: 200076.98 | T39: 179832.76 | U39: 205304.96 | V39: 209526.11 | W39: 213493.49 | X39: 225753.45 | Y39: 289376.88 | Z39: 336936.21 | AA39: 347466.91 | AB39: 353960.03
A40: =VLOOKUP(B40,Legend!$C$32:$D$66,2,FALSE) -> 15 | B40: Jambi | C40: expr_ceic | D40: 27406.778 | E40: 29184.503 | F40: 29208.938 | G40: 28964.155 | H40: 30716.31 | I40: 34709.889 | J40: 39551.498 | K40: 47189.309 | L40: 48943.841 | M40: 54293.165 | N40: 73721.858 | O40: 76468.471 | P40: 72869.868 | Q40: 76358.625 | R40: 80931.574 | S40: 88473.649 | T40: 91157.01 | U40: 100551.44 | V40: 108691.61 | W40: 112297.08 | X40: 101607.31 | Y40: 106352.4 | Z40: 110836.94 | AA40: 108965.38 | AB40: 112821.18
A41: =VLOOKUP(B41,Legend!$C$32:$D$66,2,FALSE) -> 16 | B41: Sumatera Selatan | C41: expr_ceic | D41: 34231.627 | E41: 34146.461 | F41: 35268.803 | G41: 39248.781 | H41: 44821.638 | I41: 41426.047 | J41: 52423.004 | K41: 50406.647 | L41: 54324.535 | M41: 48176.64 | N41: 56902.827 | O41: 69140.277 | P41: 74861.1 | Q41: 85500.814 | R41: 93579.506 | S41: 91237.103 | T41: 90043.733 | U41: 115180.71 | V41: 128760.37 | W41: 105887.33 | X41: 91964.279 | Y41: 98675.655 | Z41: 137914.62 | AA41: 133754.2 | AB41: 124021.01
A42: =VLOOKUP(B42,Legend!$C$32:$D$66,2,FALSE) -> 17 | B42: Bengkulu | C42: expr_ceic | D42: 5885.5718 | E42: 5981.9601 | F42: 6210.9182 | G42: 6509.234 | H42: 7186.6414 | I42: 7544.7096 | J42: 7913.6746 | K42: 8332.0208 | L42: 9006.269 | M42: 8968.986 | N42: 10010.582 | O42: 11639.894 | P42: 13078.846 | Q42: 12820.114 | R42: 12751.372 | S42: 13793.957 | T42: 14552.437 | U42: 15960.521 | V42: 16197.879 | W42: 16544.333 | X42: 16114.69 | Y42: 17164.758 | Z42: 17640.592 | AA42: 18201.558 | AB42: 18005.315
A43: =VLOOKUP(B43,Legend!$C$32:$D$66,2,FALSE) -> 18 | B43: Lampung | C43: expr_ceic | D43: 33560.177 | E43: 29077.251 | F43: 31302.198 | G43: 38605.178 | H43: 35413.89 | I43: 41744.98 | J43: 46511.223 | K43: 46447.257 | L43: 68386.425 | M43: 61676.058 | N43: 58516.351 | O43: 66929.745 | P43: 88912.712 | Q43: 88292.004 | R43: 91988.581 | S43: 87104.122 | T43: 84860.15 | U43: 89754.319 | V43: 100202.05 | W43: 105181.84 | X43: 100669.15 | Y43: 117991.61 | Z43: 125813.01 | AA43: 133226.67 | AB43: 149412.72 | AC43: 61878.04
A44: =VLOOKUP(B44,Legend!$C$32:$D$66,2,FALSE) -> 19 | B44: Kep. Bangka Belitung | C44: expr_ceic | D44: 10255.207 | E44: 12369.517 | F44: 10231.109 | G44: 10262.634 | H44: 20617.083 | I44: 21642.067 | J44: 21470.094 | K44: 21682.443 | L44: 21635.24 | M44: 21410.866 | N44: 21755.362 | O44: 30265.464 | P44: 27941.951 | Q44: 30238.287 | R44: 35019.116 | S44: 28501.762 | T44: 25174.565 | U44: 30894.843 | V44: 30845.017 | W44: 25775.369 | X44: 23895.469 | Y44: 34704.363 | Z44: 34244.873 | AA44: 28171.039 | AB44: 23604.979
A45: =VLOOKUP(B45,Legend!$C$32:$D$66,2,FALSE) -> 21 | B45: Kep. Riau | C45: expr_ceic | G45: 115779.23 | H45: 120324.17 | I45: 128656.15 | J45: 127610.91 | K45: 153583.17 | L45: 157960.13 | M45: 154815.04 | N45: 166131.49 | O45: 244113.02 | P45: 207201.07 | Q45: 234453.59 | R45: 237440.03 | S45: 249780.28 | T45: 260019.03 | U45: 257905.68 | V45: 263907.83 | W45: 275718.74 | X45: 269000.8 | Y45: 292037.37 | Z45: 324436.08 | AA45: 316214.44 | AB45: 328150.97 | AC45: 267698.68
A46: =VLOOKUP(B46,Legend!$C$32:$D$66,2,FALSE) -> 31 | B46: DKI Jakarta | C46: expr_ceic | D46: 244095.98 | E46: 234876.96 | F46: 254639.93 | G46: 295410.75 | H46: 343153.47 | I46: 381932.26 | J46: 398128.25 | K46: 420937.69 | L46: 440312.4 | M46: 441353.39 | N46: 473891.32 | O46: 584876.79 | P46: 576970.6 | Q46: 541272.49 | R46: 551708.76 | S46: 553924.18 | T46: 576458.93 | U46: 756531.28 | V46: 1001227.3 | W46: 983214.58 | X46: 887825.88 | Y46: 988640.33 | Z46: 1113108.9 | AA46: 1199015 | AB46: 1314627.6
A47: =VLOOKUP(B47,Legend!$C$32:$D$66,2,FALSE) -> 32 | B47: Jawa Barat | C47: expr_ceic | D47: 183165.5 | E47: 202234.99 | F47: 290497.99 | G47: 303665.71 | H47: 314393.74 | I47: 325579.78 | J47: 309041.84 | K47: 297457.92 | L47: 269030.58 | M47: 281800.18 | N47: 316311.7 | O47: 380679.95 | P47: 423333.82 | Q47: 379154.22 | R47: 400530.84 | S47: 423152.22 | T47: 435541.82 | U47: 493916.58 | V47: 550805.25 | W47: 591685.34 | X47: 558716.78 | Y47: 681316.21 | Z47: 756452.62 | AA47: 850488.05 | AB47: 953340.82
A48: =VLOOKUP(B48,Legend!$C$32:$D$66,2,FALSE) -> 33 | B48: Jawa Tengah | C48: expr_ceic | D48: 35420.345 | E48: 35510.639 | F48: 33178.113 | G48: 38280.347 | H48: 40515.391 | I48: 39749.425 | J48: 38578.953 | K48: 40716.537 | L48: 41238.36 | M48: 39396.975 | N48: 43652.54 | O48: 49680.05 | P48: 53707.48 | Q48: 61923.62 | R48: 68523.198 | S48: 68716.856 | T48: 66644.885 | U48: 75670.848 | V48: 84592.902 | W48: 88909.097 | X48: 85535.252 | Y48: 104222.2 | Z48: 115030.49 | AA48: 104053.81 | AB48: 117267.52 | AC48: 133212.43
A49: =VLOOKUP(B49,Legend!$C$32:$D$66,2,FALSE) -> 34 | B49: DI Yogyakarta | C49: expr_ceic | D49: 1628.5232 | E49: 1767.4508 | F49: 1903.5744 | G49: 2033.584 | H49: 2133.5795 | I49: 2268.757 | J49: 2226.2326 | K49: 2336.6401 | L49: 2477.2759 | M49: 2555.1555 | N49: 2719.3946 | O49: 2543.2615 | P49: 2933.9539 | Q49: 3541.6402 | R49: 4278.2479 | S49: 4416.2521 | T49: 4400.889 | U49: 4808.5274 | V49: 5424.8027 | W49: 5413.1309 | X49: 4714.7278 | Y49: 5736.9344 | Z49: 6213.754 | AA49: 5265.2602 | AB49: 5983.5242 | AC49: 6461
A50: =VLOOKUP(B50,Legend!$C$32:$D$66,2,FALSE) -> 35 | B50: Jawa Timur | C50: expr_ceic | D50: 235331.66 | E50: 237926.09 | F50: 221612.66 | G50: 231802.27 | H50: 244331.6 | I50: 270529.03 | J50: 294431.81 | K50: 311001.45 | L50: 329225.76 | M50: 319391.06 | N50: 348456.1 | O50: 431205.4 | P50: 496215.45 | Q50: 515981.67 | R50: 575459.31 | S50: 592478.23 | T50: 671096.85 | U50: 749400.18 | V50: 817740.56 | W50: 845287.79 | X50: 817057.63 | Y50: 902139.84 | Z50: 985733.75 | AA50: 1002438.7 | AB50: 1093502.8 | AC50: 1166044.8
A51: =VLOOKUP(B51,Legend!$C$32:$D$66,2,FALSE) -> 36 | B51: Banten | C51: expr_ceic | D51: 72858.227 | E51: 71490.491 | F51: 74361.576 | G51: 79587.487 | H51: 87397.471 | I51: 94241.662 | J51: 104918.24 | K51: 208859.15 | L51: 219942.32 | M51: 201828.89 | N51: 225820.84 | O51: 244595.48 | P51: 269522.32 | Q51: 266070.52 | R51: 281606 | S51: 293912.58 | T51: 300740.57 | U51: 332512.6 | V51: 340890.02 | W51: 336892.96 | X51: 318894.27 | Y51: 351228.89 | Z51: 379728.39 | AA51: 384298.13 | AB51: 419119.83 | AC51: 432045.42
A52: =VLOOKUP(B52,Legend!$C$32:$D$66,2,FALSE) -> 51 | B52: Bali | C52: expr_ceic | D52: 11814.153 | E52: 12448.631 | F52: 12936.624 | G52: 13710.565 | H52: 15318.109 | I52: 15772.045 | J52: 17707.32 | K52: 20082.917 | L52: 23492.397 | M52: 26183.858 | N52: 30918.016 | O52: 31862.949 | P52: 33174.014 | Q52: 37069.63 | R52: 43139.801 | S52: 45736.99 | T52: 52314.23 | U52: 56024.959 | V52: 59447.661 | W52: 59187.152 | X52: 14121.597 | Y52: 4340.0661 | Z52: 28410.212 | AA52: 57666.17 | AB52: 66949.35 | AC52: 72452.11
A53: =VLOOKUP(B53,Legend!$C$32:$D$66,2,FALSE) -> 52 | B53: Nusa Tenggara Barat | C53: expr_ceic | D53: 27536.294 | E53: 30570.023 | F53: 32475.543 | G53: 29550.736 | H53: 31133.599 | I53: 30103.184 | J53: 27646.232 | K53: 27306.309 | L53: 24705.73 | M53: 29402.985 | N53: 32859.298 | O53: 25912.107 | P53: 17349.745 | Q53: 15088.569 | R53: 11455.385 | S53: 23089 | T53: 26167.999 | U53: 24100.24 | V53: 19620.68 | W53: 23536.144 | X53: 25504.198 | Y53: 28073.111 | Z53: 40832.865 | AA53: 36425.221 | AB53: 38526.69 | AC53: 34357.12
A54: =VLOOKUP(B54,Legend!$C$32:$D$66,2,FALSE) -> 53 | B54: Nusa Tenggara Timur | C54: expr_ceic | D54: 1371.6527 | E54: 1898.9188 | F54: 2106.8238 | G54: 2232.2149 | H54: 2270.8257 | I54: 2473.1715 | J54: 2739.5862 | K54: 2994.0368 | L54: 3074.341 | M54: 3114.7682 | N54: 3152.7413 | O54: 5481.6007 | P54: 7750.0073 | Q54: 4708.8683 | R54: 5347.4405 | S54: 10490.511 | T54: 5746.0346 | U54: 5540.1921 | V54: 6474.4411 | W54: 6217.0265 | X54: 4057.9702 | Y54: 3426.4636 | Z54: 3757.3608 | AA54: 4509.5679 | AB54: 4330.1326
A55: =VLOOKUP(B55,Legend!$C$32:$D$66,2,FALSE) -> 61 | B55: Kalimantan Barat | C55: expr_ceic | D55: 9210.6129 | E55: 9385.0231 | F55: 8495.8595 | G55: 8798.5835 | H55: 8830.5587 | I55: 9382.3889 | J55: 10832.205 | K55: 10657.667 | L55: 11452.95 | M55: 10708.727 | N55: 11531.072 | O55: 19992.977 | P55: 16077.199 | Q55: 18475.303 | R55: 9882.0681 | S55: 9501.4304 | T55: 10797.309 | U55: 14336.101 | V55: 17152.376 | W55: 19122.576 | X55: 20605.587 | Y55: 25287.066 | Z55: 34492.54 | AA55: 26132.97 | AB55: 33307.19
A56: =VLOOKUP(B56,Legend!$C$32:$D$66,2,FALSE) -> 62 | B56: Kalimantan Tengah | C56: expr_ceic | D56: 10039.659 | E56: 9637.8133 | F56: 9796.6666 | G56: 10695.267 | H56: 11180.687 | I56: 11794.117 | J56: 13107.875 | K56: 13295.736 | L56: 15755.681 | M56: 19012.108 | N56: 23886.645 | O56: 25677.581 | P56: 27975.125 | Q56: 31494.949 | R56: 32006.5 | S56: 34498.6 | T56: 38054.827 | U56: 42464.7 | V56: 46881.9 | W56: 48925 | X56: 45881.2 | Y56: 48326.2 | Z56: 57134.6 | AA56: 56841 | AB56: 56590 | AC56: 62629.3
A57: =VLOOKUP(B57,Legend!$C$32:$D$66,2,FALSE) -> 63 | B57: Kalimantan Selatan | C57: expr_ceic | D57: 35203.608 | E57: 33911.202 | F57: 37927.895 | G57: 41102.021 | H57: 42271.57 | I57: 55563.064 | J57: 51455.886 | K57: 57892.453 | L57: 66609.746 | M57: 67112.634 | N57: 74947.786 | O57: 91457.943 | P57: 91807.107 | Q57: 91706.847 | R57: 91123.191 | S57: 84548.668 | T57: 84859.057 | U57: 92462.024 | V57: 97980.972 | W57: 100100.73 | X57: 88918.22 | Y57: 105442.21 | Z57: 119455.94 | AA57: 128461.84 | AB57: 134831.74 | AC57: 127289.45
A58: =VLOOKUP(B58,Legend!$C$32:$D$66,2,FALSE) -> 64 | B58: Kalimantan Timur | C58: expr_ceic | D58: 291350.95 | E58: 304457.51 | F58: 301062.71 | G58: 307203.72 | H58: 328304.36 | I58: 351845.87 | J58: 371611.13 | K58: 380265.2 | L58: 399930.62 | M58: 378007.94 | N58: 408291.06 | O58: 430355.79 | P58: 454195.06 | Q58: 467041.12 | R58: 475151.61 | S58: 473419.87 | T58: 481739.01 | U58: 502223.35 | V58: 513208.17 | W58: 539516.96 | X58: 519613.4 | Y58: 537033.35 | Z58: 556463.45 | AA58: 589664.61 | AB58: 631016.87 | AC58: 669089.9
A59: =VLOOKUP(B59,Legend!$C$32:$D$66,2,FALSE) -> 65 | B59: Kalimantan Utara | C59: expr_ceic | N59: 28553.736 | O59: 31390.055 | P59: 34402.426 | Q59: 37225.75 | R59: 41345.536 | S59: 42093.105 | T59: 44096.759 | U59: 48029.822 | V59: 51249.329 | W59: 57140.194 | X59: 57834.85 | Y59: 66189.414 | Z59: 70918.925 | AA59: 72137.949 | AB59: 73589.006 | AC59: 75781.568
A60: =VLOOKUP(B60,Legend!$C$32:$D$66,2,FALSE) -> 71 | B60: Sulawesi Utara | C60: expr_ceic | D60: 5821.1532 | E60: 3730.6072 | F60: 3736.6581 | G60: 4764.2213 | H60: 6742.4752 | I60: 7576.5816 | J60: 7447.4314 | K60: 8202.2227 | L60: 9995.678 | M60: 10402.383 | N60: 11844.726 | O60: 18579.839 | P60: 24554.471 | Q60: 19319.593 | R60: 22959.623 | S60: 18123.275 | T60: 20406.113 | U60: 20527.698 | V60: 23275.491 | W60: 23521.512 | X60: 22975.227 | Y60: 24936.158 | Z60: 25347.287 | AA60: 26448.298 | AB60: 26904.414
A61: =VLOOKUP(B61,Legend!$C$32:$D$66,2,FALSE) -> 72 | B61: Sulawesi Tengah | C61: expr_ceic | D61: 7500.7863 | E61: 7892.6755 | F61: 8274.6381 | G61: 8578.9083 | H61: 8890.5097 | I61: 9332.371 | J61: 9878.0313 | K61: 10825.611 | L61: 11881.273 | M61: 12491.711 | N61: 13951.023 | O61: 17033.437 | P61: 22073.64 | Q61: 19843.542 | R61: 19644.772 | S61: 25067.743 | T61: 40319.446 | U61: 44537.492 | V61: 97813.048 | W61: 112407.85 | X61: 143629.45 | Y61: 158796.11 | Z61: 194754.67 | AA61: 231589.54 | AB61: 275299.86
A62: =VLOOKUP(B62,Legend!$C$32:$D$66,2,FALSE) -> 73 | B62: Sulawesi Selatan | C62: expr_ceic | D62: 20078.856 | E62: 19696.224 | F62: 19091.462 | G62: 19498.865 | H62: 32039.312 | I62: 37357.709 | J62: 38875.315 | K62: 49716.895 | L62: 44586.759 | M62: 38940.123 | N62: 58537.975 | O62: 52855.571 | P62: 51218.349 | Q62: 52363.205 | R62: 60314.079 | S62: 54053.188 | T62: 35861.16 | U62: 31475.01 | V62: 32261.5 | W62: 31671.47 | X62: 31936.54 | Y62: 35722.05 | Z62: 49176.72 | AA62: 48785.62 | AB62: 49903.7
A63: =VLOOKUP(B63,Legend!$C$32:$D$66,2,FALSE) -> 74 | B63: Sulawesi Tenggara | C63: expr_ceic | D63: 3020.2063 | E63: 3103.3616 | F63: 3184.1752 | G63: 3614.7663 | H63: 4383.1032 | I63: 4818.745 | J63: 8809.7065 | K63: 9239.9707 | L63: 9035.9383 | M63: 9541.931 | N63: 10965.377 | O63: 15382.386 | P63: 18720.096 | Q63: 19229.506 | R63: 14910.239 | S63: 7880.9197 | T63: 7141.7824 | U63: 8795.4008 | V63: 17736.51 | W63: 25638.775 | X63: 37223.046 | Y63: 59643.399 | Z63: 70128.497 | AA63: 58497.317 | AB63: 55123.116
A64: =VLOOKUP(B64,Legend!$C$32:$D$66,2,FALSE) -> 75 | B64: Gorontalo | C64: expr_ceic | D64: 595.6125 | E64: 871.07981 | F64: 1078.3719 | G64: 1344.2817 | H64: 1617.7154 | I64: 1948.9089 | J64: 2340.9748 | K64: 2882.7792 | L64: 3132.9693 | M64: 3069.588 | N64: 3226.69 | O64: 3799.53 | P64: 4775.88 | Q64: 4812.59 | R64: 5175.65 | S64: 5327.66 | T64: 5083.93 | U64: 5383.49 | V64: 6135.94 | W64: 6254.89 | X64: 6102.36 | Y64: 6776.3 | Z64: 7259.77 | AA64: 7737.11 | AB64: 8409.63
A65: =VLOOKUP(B65,Legend!$C$32:$D$66,2,FALSE) -> 76 | B65: Sulawesi Barat | C65: expr_ceic | H65: 4765.8997 | I65: 5011.6542 | J65: 5344.2541 | K65: 5948.2817 | L65: 6966.1856 | M65: 7980.3165 | N65: 9422.2478 | O65: 11066.665 | P65: 12400.48 | Q65: 12055.168 | R65: 12379.137 | S65: 13333.211 | T65: 13594.558 | U65: 13663.555 | V65: 14816.326 | W65: 15513.337 | X65: 14480.492 | Y65: 14668.585 | Z65: 14218.983 | AA65: 14710.17 | AB65: 15175
A66: =VLOOKUP(B66,Legend!$C$32:$D$66,2,FALSE) -> 81 | B66: Maluku | C66: expr_ceic | D66: 3103.2197 | E66: 2823.7779 | F66: 2842.2348 | G66: 2994.8259 | H66: 3118.1104 | I66: 3233.5156 | J66: 3453.509 | K66: 3773.0307 | L66: 3960.2072 | M66: 4062.4627 | N66: 4533.9193 | O66: 4417.166 | P66: 5376.0405 | Q66: 5835.6939 | R66: 5189.1782 | S66: 5183.5488 | T66: 5403.5587 | U66: 5347.3848 | V66: 4771.4345 | W66: 3985.1772 | X66: 2791.8852 | Y66: 4043.7156 | Z66: 4787.5938 | AA66: 4128.3144 | AB66: 145.72
A67: =VLOOKUP(B67,Legend!$C$32:$D$66,2,FALSE) -> 82 | B67: Maluku Utara | C67: expr_ceic | D67: 2493.0024 | E67: 1961.3184 | F67: 2186.9361 | G67: 2120.6719 | H67: 2568.0849 | I67: 2803.7553 | J67: 3121.1066 | K67: 3424.3148 | L67: 3783.5269 | M67: 4246.9348 | N67: 4828.1704 | O67: 8253.7244 | P67: 8503.7841 | Q67: 11056.889 | R67: 12921.494 | S67: 17340.156 | T67: 19673.827 | U67: 21690.299 | V67: 16573.869 | W67: 17924.384 | X67: 23485.47 | Y67: 59454.28 | Z67: 100079.95 | AA67: 128777.79 | AB67: 143150.74 | AC67: 200764.13
A68: =VLOOKUP(B68,Legend!$C$32:$D$66,2,FALSE) -> 91 | B68: Papua Barat | C68: expr_ceic | F68: 16685.047 | G68: 16598.481 | H68: 15862.05 | I68: 19525.481 | J68: 21680.56 | K68: 21718.53 | L68: 20201.975 | M68: 17709.775 | N68: 31529.454 | O68: 24562.901 | P68: 30602.478 | Q68: 30182.355 | R68: 35334.415 | S68: 40438.386 | T68: 39446.298 | U68: 42688.117 | V68: 49488.554 | W68: 47314.462 | X68: 45934.783 | Y68: 41019.721 | Z68: 54213.34 | AA68: 43371.21 | AB68: 50068.61 | AC68: 555.32
A69: =VLOOKUP(B69,Legend!$C$32:$D$66,2,FALSE) -> 94 | B69: Papua | C69: expr_ceic | D69: 56393.053 | E69: 57343.511 | F69: 51548.662 | G69: 58350.256 | H69: 45225.489 | I69: 50917.074 | J69: 52849.599 | K69: 47522.113 | L69: 43592.815 | M69: 51590.985 | N69: 46999.047 | O69: 33910.146 | P69: 24281.055 | Q69: 32143.119 | R69: 17091.171 | S69: 23736.758 | T69: 25377.054 | U69: 24016.292 | V69: 33517.563 | W69: 10533.486 | X69: 15901.656 | Y69: 28341.609 | Z69: 106054.73 | AA69: 108861.63 | AB69: 134900.36
A70: =VLOOKUP(B70,Legend!$C$32:$D$66,2,FALSE) -> 11 | B70: Aceh | C70: gfcr_ceic | D70: 9862.5385 | E70: 12692.951 | F70: 22373.815 | G70: 14328.231 | H70: 14641.356 | I70: 27776.415 | J70: 26035.113 | K70: 28495.075 | L70: 29222.293 | M70: 28706.885 | N70: 29766.574 | O70: 32980.776 | P70: 34901.819 | Q70: 34736.027 | R70: 36571.543 | S70: 37892.086 | T70: 40598.055 | U70: 39421.958 | V70: 40769.451 | W70: 43513.914 | X70: 45045.625 | Y70: 45438.248 | Z70: 45103.704 | AA70: 47746.94 | AB70: 49982.89 | AC70: 49237.05
A71: =VLOOKUP(B71,Legend!$C$32:$D$66,2,FALSE) -> 12 | B71: Sumatera Utara | C71: gfcr_ceic | D71: 45469.779 | E71: 42978.361 | F71: 51400.902 | G71: 52155.042 | H71: 55799.464 | I71: 62272.679 | J71: 70589.375 | K71: 79966.554 | L71: 88863.947 | M71: 94844.286 | N71: 99539.597 | O71: 105474.68 | P71: 114503.16 | Q71: 120436.36 | R71: 124148.57 | S71: 128952.21 | T71: 135207.98 | U71: 142013.73 | V71: 150803.37 | W71: 163244.13 | X71: 161327.64 | Y71: 166914.74 | Z71: 173314.81 | AA71: 181084.17 | AB71: 190051.09 | AC71: 191108.51
A72: =VLOOKUP(B72,Legend!$C$32:$D$66,2,FALSE) -> 13 | B72: Sumatera Barat | C72: gfcr_ceic | D72: 20087.019 | E72: 20301.949 | F72: 20513.729 | G72: 21151.322 | H72: 21823.934 | I72: 23096.815 | J72: 24024.914 | K72: 24966.371 | L72: 26285.003 | M72: 27588.058 | N72: 30696.805 | O72: 34097.669 | P72: 36280.81 | Q72: 37957.416 | R72: 39883.15 | S72: 41609.412 | T72: 44221.669 | U72: 46182.467 | V72: 47807.313 | W72: 50275.295 | X72: 48919.506 | Y72: 49492.171 | Z72: 51368.567 | AA72: 55330.81 | AB72: 57300.53 | AC72: 56249.97
A73: =VLOOKUP(B73,Legend!$C$32:$D$66,2,FALSE) -> 14 | B73: Riau | C73: gfcr_ceic | D73: 59963.012 | E73: 72856.368 | F73: 85717.341 | G73: 56675.238 | H73: 62274.081 | I73: 65989.331 | J73: 68895.796 | K73: 73356.531 | L73: 80490.367 | M73: 87748.893 | N73: 95152.513 | O73: 110722.02 | P73: 120978.86 | Q73: 127338.48 | R73: 129639.73 | S73: 134850.26 | T73: 139706.39 | U73: 141710.52 | V73: 147050.84 | W73: 150885.03 | X73: 148133.67 | Y73: 153996.37 | Z73: 163041.33 | AA73: 171020.32 | AB73: 176944.01 | AC73: 181244.59
A74: =VLOOKUP(B74,Legend!$C$32:$D$66,2,FALSE) -> 15 | B74: Jambi | C74: gfcr_ceic | D74: 10436.526 | E74: 12341.134 | F74: 12658.359 | G74: 13706.5 | H74: 15128.463 | I74: 14564.563 | J74: 16754.176 | K74: 18015.186 | L74: 19579.076 | M74: 20212.383 | N74: 21601.723 | O74: 21571.04 | P74: 25926.188 | Q74: 28266.692 | R74: 28117.165 | S74: 27834.649 | T74: 29038.987 | U74: 30127.534 | V74: 30777.992 | W74: 31894.296 | X74: 32226.99 | Y74: 35215.518 | Z74: 36100.051 | AA74: 39667.38 | AB74: 42357.57 | AC74: 42622.42
A75: =VLOOKUP(B75,Legend!$C$32:$D$66,2,FALSE) -> 16 | B75: Sumatera Selatan | C75: gfcr_ceic | D75: 38878.513 | E75: 40499.742 | F75: 42354.551 | G75: 45433.729 | H75: 50136.12 | I75: 53450.116 | J75: 56768.101 | K75: 62362.289 | L75: 66583.984 | M75: 70223.294 | N75: 76364.639 | O75: 80495.866 | P75: 85219.895 | Q75: 89260.413 | R75: 93404.414 | S75: 93638.158 | T75: 101309.9 | U75: 107287.54 | V75: 111301.18 | W75: 113186.34 | X75: 114605.19 | Y75: 111007.1 | Z75: 108306.92 | AA75: 110986.58 | AB75: 115875.99 | AC75: 119081.6
A76: =VLOOKUP(B76,Legend!$C$32:$D$66,2,FALSE) -> 17 | B76: Bengkulu | C76: gfcr_ceic | D76: 5064.7566 | E76: 5189.0037 | F76: 5401.8964 | G76: 5617.7067 | H76: 5981.0416 | I76: 6675.2537 | J76: 7086.1244 | K76: 9524.1011 | L76: 10401.271 | M76: 10934.94 | N76: 11578.477 | O76: 12596.437 | P76: 13674.63 | Q76: 14819.652 | R76: 16014.028 | S76: 16572.904 | T76: 17404.345 | U76: 18463.147 | V76: 19497.272 | W76: 20471.499 | X76: 20134.107 | Y76: 20964.697 | Z76: 21695.686 | AA76: 22383.1 | AB76: 23024.5 | AC76: 23827.83
A77: =VLOOKUP(B77,Legend!$C$32:$D$66,2,FALSE) -> 18 | B77: Lampung | C77: gfcr_ceic | D77: 30448.188 | E77: 29075.817 | F77: 32799.966 | G77: 32653.291 | H77: 31681.198 | I77: 34925.95 | J77: 35793.165 | K77: 37697.675 | L77: 39515.497 | M77: 41024.424 | N77: 43927.327 | O77: 49058.861 | P77: 53646.824 | Q77: 55690.805 | R77: 58841.761 | S77: 62035.82 | T77: 67779.396 | U77: 72861.898 | V77: 79145.389 | W77: 82804.963 | X77: 78790.293 | Y77: 81913.308 | Z77: 83896.771 | AA77: 87373.16 | AB77: 88928.18 | AC77: 93620.1
A78: =VLOOKUP(B78,Legend!$C$32:$D$66,2,FALSE) -> 19 | B78: Kep. Bangka Belitung | C78: gfcr_ceic | D78: 2700.3037 | E78: 3045.8728 | F78: 3035.568 | G78: 3709.7513 | H78: 5460.1554 | I78: 5801.4512 | J78: 5331.4283 | K78: 6188.6977 | L78: 6899.442 | M78: 7141.4458 | N78: 7515.7223 | O78: 8147.134 | P78: 8550.0619 | Q78: 8970.0596 | R78: 9408.0275 | S78: 9823.5326 | T78: 10450.945 | U78: 11111.34 | V78: 11779.865 | W78: 12453.338 | X78: 11633.484 | Y78: 12013.636 | Z78: 12412.528 | AA78: 13018.46 | AB78: 12916.29 | AC78: 12871.75
A79: =VLOOKUP(B79,Legend!$C$32:$D$66,2,FALSE) -> 21 | B79: Kep. Riau | C79: gfcr_ceic | G79: 36857.377 | H79: 37873.57 | I79: 16728.61 | J79: 19716.683 | K79: 25039.858 | L79: 32395.718 | M79: 37301.547 | N79: 45350.313 | O79: 48421.858 | P79: 52069.671 | Q79: 55515.328 | R79: 58731.612 | S79: 60637.959 | T79: 62584.78 | U79: 63509.216 | V79: 69262.924 | W79: 73447.469 | X79: 69792.412 | Y79: 72042.69 | Z79: 74944.81 | AA79: 81476.94 | AB79: 86579.47 | AC79: 92478.32
A80: =VLOOKUP(B80,Legend!$C$32:$D$66,2,FALSE) -> 31 | B80: DKI Jakarta | C80: gfcr_ceic | D80: 291773.7 | E80: 287741.52 | F80: 289361.64 | G80: 291885.58 | H80: 332478.73 | I80: 364173.27 | J80: 379684.9 | K80: 405198.47 | L80: 439598.24 | M80: 451735.75 | N80: 491549.15 | O80: 533589.46 | P80: 585571.05 | Q80: 618800.67 | R80: 637777.7 | S80: 654605.16 | T80: 664738.69 | U80: 704826.29 | V80: 737769.03 | W80: 747263.48 | X80: 695137.42 | Y80: 702452.35 | Z80: 734191.61 | AA80: 762885.9 | AB80: 802516.25 | AC80: 840775.58
A81: =VLOOKUP(B81,Legend!$C$32:$D$66,2,FALSE) -> 32 | B81: Jawa Barat | C81: gfcr_ceic | D81: 121931.97 | E81: 126796.14 | F81: 129957.8 | G81: 136648.01 | H81: 150757.63 | I81: 168804.9 | J81: 174280.4 | K81: 190544.36 | L81: 199641.54 | M81: 209493.86 | N81: 221524.24 | O81: 245323.57 | P81: 271070.8 | Q81: 268318.28 | R81: 287389.55 | S81: 299342.64 | T81: 313083.7 | U81: 332750.61 | V81: 352312.42 | W81: 366760.22 | X81: 336213.72 | Y81: 357977.88 | Z81: 359006.1 | AA81: 386751.79 | AB81: 413661.87 | AC81: 435547.55
A82: =VLOOKUP(B82,Legend!$C$32:$D$66,2,FALSE) -> 33 | B82: Jawa Tengah | C82: gfcr_ceic | D82: 98899.754 | E82: 87537.342 | F82: 90772.436 | G82: 97419.272 | H82: 110537.14 | I82: 120563.08 | J82: 136111.19 | K82: 143826.42 | L82: 153453.68 | M82: 162080.34 | N82: 175032.48 | O82: 187096.82 | P82: 202328.21 | Q82: 211220.47 | R82: 220772.87 | S82: 232335.2 | T82: 246247.09 | U82: 264716.11 | V82: 285045.11 | W82: 298877.27 | X82: 278024.57 | Y82: 297028.56 | Z82: 302949.27 | AA82: 315755.79 | AB82: 336453.49 | AC82: 359214.21
A83: =VLOOKUP(B83,Legend!$C$32:$D$66,2,FALSE) -> 34 | B83: DI Yogyakarta | C83: gfcr_ceic | D83: 10523.5 | E83: 10764.034 | F83: 12060.315 | G83: 13149.825 | H83: 13171.438 | I83: 14055.42 | J83: 15279.734 | K83: 15697.935 | L83: 16368.303 | M83: 16894.106 | N83: 17470.045 | O83: 18245.345 | P83: 19207.89 | Q83: 20190.81 | R83: 21358.622 | S83: 22286.615 | T83: 23616.948 | U83: 24791.862 | V83: 27327.862 | W83: 30021.484 | X83: 25995.231 | Y83: 28127.239 | Z83: 29774.647 | AA83: 31709.04 | AB83: 34215.01 | AC83: 37034.57
A84: =VLOOKUP(B84,Legend!$C$32:$D$66,2,FALSE) -> 35 | B84: Jawa Timur | C84: gfcr_ceic | D84: 166351.68 | E84: 176382.03 | F84: 182086.33 | G84: 185202 | H84: 191693.08 | I84: 207710.89 | J84: 222713.76 | K84: 228741.68 | L84: 242151.06 | M84: 254796.76 | N84: 272954.03 | O84: 289641.72 | P84: 314921.95 | Q84: 330280.83 | R84: 344715.56 | S84: 364831.01 | T84: 386709.4 | U84: 407185.35 | V84: 431922.41 | W84: 453188.7 | X84: 433893.01 | Y84: 438579.17 | Z84: 462312.49 | AA84: 487230.49 | AB84: 513996.18 | AC84: 542456.78
A85: =VLOOKUP(B85,Legend!$C$32:$D$66,2,FALSE) -> 36 | B85: Banten | C85: gfcr_ceic | D85: 49834.592 | E85: 53816.102 | F85: 57240.649 | G85: 61387.988 | H85: 67895.276 | I85: 73816.37 | J85: 79006.75 | K85: 64597.024 | L85: 72363.076 | M85: 75786.709 | N85: 81506.594 | O85: 88786.94 | P85: 96635.331 | Q85: 100195.82 | R85: 103115.31 | S85: 109012.81 | T85: 115877.26 | U85: 126304.24 | V85: 135049 | W85: 143667.51 | X85: 143572.83 | Y85: 149908.85 | Z85: 155430.59 | AA85: 160769.55 | AB85: 164999.07 | AC85: 173496.76
A86: =VLOOKUP(B86,Legend!$C$32:$D$66,2,FALSE) -> 51 | B86: Bali | C86: gfcr_ceic | D86: 9875.9022 | E86: 9813.0488 | F86: 10041.721 | G86: 10170.889 | H86: 10895.335 | I86: 11190.482 | J86: 11411.082 | K86: 18751.318 | L86: 23093.932 | M86: 24925.271 | N86: 29142.201 | O86: 33290.009 | P86: 36322.554 | Q86: 38111.983 | R86: 38800.143 | S86: 41397.444 | T86: 45030.742 | U86: 46623.268 | V86: 51076.077 | W86: 52755.13 | X86: 46598.906 | Y86: 44547.839 | Z86: 45712.963 | AA86: 47091.11 | AB86: 49708.02 | AC86: 52704.12
A87: =VLOOKUP(B87,Legend!$C$32:$D$66,2,FALSE) -> 52 | B87: Nusa Tenggara Barat | C87: gfcr_ceic | D87: 9303.3225 | E87: 9854.3978 | F87: 10258.287 | G87: 10728.275 | H87: 11554.903 | I87: 12061.632 | J87: 12749.021 | K87: 13871.918 | L87: 15623.25 | M87: 17850.244 | N87: 19005.303 | O87: 20052.85 | P87: 22001.26 | Q87: 22213.426 | R87: 22950.229 | S87: 25615.716 | T87: 27709.645 | U87: 28526.821 | V87: 30007.146 | W87: 32163.88 | X87: 30386.396 | Y87: 31589.131 | Z87: 30968.087 | AA87: 33748.53 | AB87: 34798.33 | AC87: 35456.15
A88: =VLOOKUP(B88,Legend!$C$32:$D$66,2,FALSE) -> 53 | B88: Nusa Tenggara Timur | C88: gfcr_ceic | D88: 12449.221 | E88: 13205.173 | F88: 13872.855 | G88: 9204.8727 | H88: 9586.4304 | I88: 9914.3702 | J88: 10414.004 | K88: 10715.169 | L88: 11026.361 | M88: 12768.918 | N88: 14015.892 | O88: 14723.677 | P88: 15844.365 | Q88: 17614.838 | R88: 22195.978 | S88: 24832.317 | T88: 28741.681 | U88: 30527.237 | V88: 32035.755 | W88: 33794.457 | X88: 30989.782 | Y88: 32473.642 | Z88: 32304.85 | AA88: 34294.47 | AB88: 34892.83 | AC88: 34757.11
A89: =VLOOKUP(B89,Legend!$C$32:$D$66,2,FALSE) -> 61 | B89: Kalimantan Barat | C89: gfcr_ceic | D89: 18948.815 | E89: 19006.487 | F89: 19758.41 | G89: 20821.34 | H89: 22047.717 | I89: 22735.606 | J89: 23654.477 | K89: 23133.069 | L89: 24062.697 | M89: 25179.143 | N89: 26708.74 | O89: 30026.171 | P89: 32320.292 | Q89: 33044.477 | R89: 36145.685 | S89: 38205.249 | T89: 38402.217 | U89: 39297.728 | V89: 40474.31 | W89: 41406.838 | X89: 40785.949 | Y89: 41890.787 | Z89: 43172.702 | AA89: 46518.96 | AB89: 49921.81 | AC89: 53270.79
A90: =VLOOKUP(B90,Legend!$C$32:$D$66,2,FALSE) -> 62 | B90: Kalimantan Tengah | C90: gfcr_ceic | D90: 13224.255 | E90: 13217.453 | F90: 13322.449 | G90: 13959.054 | H90: 14609.268 | I90: 15984.375 | J90: 18083.517 | K90: 19959.592 | L90: 21645.309 | M90: 22118.524 | N90: 24129.344 | O90: 26770.39 | P90: 28652.114 | Q90: 29743.665 | R90: 31910.246 | S90: 34049.499 | T90: 35835.84 | U90: 37275.022 | V90: 39378.103 | W90: 40449.76 | X90: 39286.655 | Y90: 40539.276 | Z90: 40002.449 | AA90: 42264.5 | AB90: 44449.54 | AC90: 44905.95
A91: =VLOOKUP(B91,Legend!$C$32:$D$66,2,FALSE) -> 63 | B91: Kalimantan Selatan | C91: gfcr_ceic | D91: 8061.8553 | E91: 7335.5853 | F91: 7187.1779 | G91: 7426.8219 | H91: 7508.5977 | I91: 7689.1369 | J91: 8596.048 | K91: 11873.461 | L91: 14606.349 | M91: 16843.575 | N91: 18914.905 | O91: 19894.863 | P91: 20911.08 | Q91: 22112.484 | R91: 23375.035 | S91: 24622.972 | T91: 25455.834 | U91: 26551.068 | V91: 28677.559 | W91: 30503.556 | X91: 30092.964 | Y91: 30346.148 | Z91: 31935.778 | AA91: 33588.68 | AB91: 35259.02 | AC91: 37168.94
A92: =VLOOKUP(B92,Legend!$C$32:$D$66,2,FALSE) -> 64 | B92: Kalimantan Timur | C92: gfcr_ceic | D92: 46055.27 | E92: 54898.704 | F92: 59884.901 | G92: 65025.345 | H92: 67301.45 | I92: 71371.799 | J92: 77281.913 | K92: 81435.441 | L92: 88928.972 | M92: 92460.169 | N92: 97159.066 | O92: 105497.5 | P92: 110334.68 | Q92: 111846.99 | R92: 117106.16 | S92: 115380.24 | T92: 108405.55 | U92: 111386.67 | V92: 119779.85 | W92: 125537.61 | X92: 124207.97 | Y92: 133824.11 | Z92: 141346.17 | AA92: 157598.52 | AB92: 170659.77 | AC92: 174089.88
A93: =VLOOKUP(B93,Legend!$C$32:$D$66,2,FALSE) -> 65 | B93: Kalimantan Utara | C93: gfcr_ceic | N93: 11346.012 | O93: 11649.507 | P93: 12389.875 | Q93: 13122.172 | R93: 14043.441 | S93: 15246.053 | T93: 16317.819 | U93: 16969.655 | V93: 17840.023 | W93: 19068.549 | X93: 18489.758 | Y93: 18609.925 | Z93: 19050.233 | AA93: 20788.96 | AB93: 22210.3 | AC93: 23203.48
A94: =VLOOKUP(B94,Legend!$C$32:$D$66,2,FALSE) -> 71 | B94: Sulawesi Utara | C94: gfcr_ceic | D94: 8743.1278 | E94: 9376.5091 | F94: 9942.53 | G94: 9572.3986 | H94: 10217.867 | I94: 11430.354 | J94: 13117.155 | K94: 15785.393 | L94: 18172.793 | M94: 19479.853 | N94: 20141.036 | O94: 21961.154 | P94: 22369.519 | Q94: 23331.262 | R94: 23801.172 | S94: 26067.779 | T94: 27710.484 | U94: 29718.183 | V94: 30806.129 | W94: 32653.618 | X94: 30777.572 | Y94: 33257.803 | Z94: 34255.067 | AA94: 35137.47 | AB94: 36500.98 | AC94: 36778.14
A95: =VLOOKUP(B95,Legend!$C$32:$D$66,2,FALSE) -> 72 | B95: Sulawesi Tengah | C95: gfcr_ceic | D95: 8221.5867 | E95: 8682.3114 | F95: 9083.9372 | G95: 9624.3495 | H95: 10272.543 | I95: 11025.128 | J95: 11903.962 | K95: 14523.57 | L95: 15825.836 | M95: 17114.878 | N95: 18388.284 | O95: 21262.487 | P95: 24156.746 | Q95: 26670.476 | R95: 30720.125 | S95: 35082.328 | T95: 39964.673 | U95: 41366.809 | V95: 42083.727 | W95: 50649.309 | X95: 46703.437 | Y95: 69263.217 | Z95: 85345.313 | AA95: 86318.5 | AB95: 89253.94 | AC95: 90611.61
A96: =VLOOKUP(B96,Legend!$C$32:$D$66,2,FALSE) -> 73 | B96: Sulawesi Selatan | C96: gfcr_ceic | D96: 24682.444 | E96: 30263.687 | F96: 29621.337 | G96: 29995.857 | H96: 31411.369 | I96: 31698.713 | J96: 32394.9 | K96: 35834.386 | L96: 43237.879 | M96: 50276.952 | N96: 57259.193 | O96: 64561.919 | P96: 74678.047 | Q96: 82975.854 | R96: 89710.7 | S96: 96963.272 | T96: 103857.19 | U96: 112387.27 | V96: 118819.8 | W96: 125557.71 | X96: 127770.24 | Y96: 134600.87 | Z96: 139015.41 | AA96: 145390.79 | AB96: 148819.07 | AC96: 155438.36
A97: =VLOOKUP(B97,Legend!$C$32:$D$66,2,FALSE) -> 74 | B97: Sulawesi Tenggara | C97: gfcr_ceic | D97: 7295.7706 | E97: 7461.0895 | F97: 8065.7487 | G97: 8722.301 | H97: 9793.9398 | I97: 11414.771 | J97: 12416.546 | K97: 13965.383 | L97: 16057.951 | M97: 18101.73 | N97: 21023.366 | O97: 22317.69 | P97: 23366.566 | Q97: 24807.787 | R97: 28742.49 | S97: 29956.179 | T97: 32248.519 | U97: 34826.403 | V97: 36804.904 | W97: 38755.857 | X97: 37940.57 | Y97: 40239.516 | Z97: 40498.19 | AA97: 41654.63 | AB97: 42526.17 | AC97: 43781.48
A98: =VLOOKUP(B98,Legend!$C$32:$D$66,2,FALSE) -> 75 | B98: Gorontalo | C98: gfcr_ceic | D98: 1205.7433 | E98: 1579.4396 | F98: 1640.5429 | G98: 2332.3526 | H98: 3244.8034 | I98: 3540.2468 | J98: 3820.2192 | K98: 4179.1231 | L98: 4398.2527 | M98: 4622.9581 | N98: 4863.9703 | O98: 5288.3445 | P98: 5726.685 | Q98: 6188.2754 | R98: 6722.0788 | S98: 7317.3801 | T98: 7721.2895 | U98: 7956.7846 | V98: 8285.5089 | W98: 8559.357 | X98: 8474.6846 | Y98: 8714.4374 | Z98: 8873.4931 | AA98: 9187.36 | AB98: 9516.55 | AC98: 10056.98
A99: =VLOOKUP(B99,Legend!$C$32:$D$66,2,FALSE) -> 76 | B99: Sulawesi Barat | C99: gfcr_ceic | H99: 1976.3936 | I99: 2107.6154 | J99: 2336.747 | K99: 3074.4073 | L99: 4335.61 | M99: 4679.6044 | N99: 4548.8902 | O99: 5223.6168 | P99: 5599.7066 | Q99: 6253.9067 | R99: 6726.5982 | S99: 7182.8682 | T99: 7984.3762 | U99: 8617.0169 | V99: 9082.9728 | W99: 9630.5443 | X99: 8810.6789 | Y99: 9465.9805 | Z99: 9455.2691 | AA99: 9643.53 | AB99: 10046.21 | AC99: 9949.83
A100: =VLOOKUP(B100,Legend!$C$32:$D$66,2,FALSE) -> 81 | B100: Maluku | C100: gfcr_ceic | D100: 1742.3354 | E100: 1769.0585 | F100: 2082.1101 | G100: 2304.8482 | H100: 2455.8915 | I100: 2599.0699 | J100: 2787.2492 | K100: 3144.9704 | L100: 3534.3433 | M100: 3776.0009 | N100: 4385.6166 | O100: 5173.8677 | P100: 6281.1712 | Q100: 6968.0082 | R100: 7344.1757 | S100: 7619.5878 | T100: 8177.0124 | U100: 8679.3595 | V100: 9427.7486 | W100: 9999.0578 | X100: 9790.4211 | Y100: 10075.803 | Z100: 10178.451 | AA100: 10273.04 | AB100: 10481.14 | AC100: 10578.07
...

Sheet WIDE_IDD
A1: provname | B1: indicator | C1: 2000 | D1: 2001 | E1: 2002 | F1: 2003 | G1: 2004 | H1: 2005 | I1: 2006 | J1: 2007 | K1: 2008 | L1: 2009 | M1: 2010 | N1: 2011 | O1: 2012 | P1: 2013
A2: Aceh | B2: gdpn_idd | C2: 76927900 | D2: 73661657 | E2: 84860808 | F2: 94463588 | G2: 98324161 | H2: 107169006 | I2: 127277138 | J2: 132952788 | K2: 142309062 | L2: 141927835 | M2: 153993638 | N2: 158088777 | O2: 173424078 | P2: 85019450
A3: Bali | B3: gdpn_idd | C3: 33392042 | D3: 38848782 | E3: 45342118 | F3: 49868057 | G3: 55366698 | H3: 64940206 | I3: 71584693 | J3: 80972447 | K3: 95345888 | L3: 110340124 | M3: 124787185 | N3: 140401198 | O3: 158653244 | P3: 82879460
A4: Banten | B4: gdpn_idd | C4: 93053281 | D4: 106774418 | E4: 123289889 | F4: 136402054 | G4: 151188431 | H4: 173062572 | I4: 199167110 | J4: 220137615 | K4: 251336567 | L4: 283101307 | M4: 319123729 | N4: 383103940 | O4: 425656580 | P4: 241930320
A5: Bengkulu | B5: gdpn_idd | C5: 9737712 | D5: 10997303 | E5: 12524790 | F5: 14438085 | G5: 16109577 | H5: 20006638 | I5: 22520232 | J5: 25287103 | K5: 29143435 | L5: 31457669 | M5: 35464174 | N5: 40884468 | O5: 46261802 | P5: 24967840
A6: DI Yogyakarta | B6: gdpn_idd | C6: 27040431 | D6: 30627237 | E6: 35059556 | F6: 39262183 | G6: 43965765 | H6: 50583928 | I6: 58599125 | J6: 65443030 | K6: 75312922 | L6: 81939970 | M6: 90262920 | N6: 101060360 | O6: 111459733 | P6: 61361580
A7: DKI Jakarta | B7: gdpn_idd | C7: 455893455 | D7: 526315985 | E7: 598534894 | F7: 668891340 | G7: 752089786 | H7: 867058392 | I7: 998836906 | J7: 1137022999 | K7: 1358898596 | L7: 1516371414 | M7: 1720819681 | N7: 1954534869 | O7: 2198069942 | P7: 1246043880
A8: Gorontalo | B8: gdpn_idd | C8: 2950048 | D8: 3628484 | E8: 4333744 | F8: 4974964 | G8: 5616090 | H8: 6699786 | I8: 7761824 | J8: 9081042 | K8: 11235068 | L8: 13504394 | M8: 15439083 | N8: 17554979 | O8: 19933660 | P8: 10851960
A9: Jambi | B9: gdpn_idd | C9: 19066013 | D9: 22883691 | E9: 27462722 | F9: 32070335 | G9: 37384606 | H9: 44782524 | I9: 51943454 | J9: 62637380 | K9: 78770902 | L9: 87447756 | M9: 104972203 | N9: 112145094 | O9: 128887105 | P9: 65781080
A10: Jawa Barat | B10: gdpn_idd | C10: 383184616 | D10: 432406312 | E10: 484987430 | F10: 545148335 | G10: 611328267 | H10: 759340367 | I10: 912479126 | J10: 1024543911 | K10: 1206158051 | L10: 1320636434 | M10: 1479582025 | N10: 1616789512 | O10: 1783170551 | P10: 949518710
A11: Jawa Tengah | B11: gdpn_idd | C11: 221642824 | D11: 258621105 | E11: 297722756 | F11: 334652104 | G11: 373918059 | H11: 455833821 | I11: 538281577 | J11: 595907520 | K11: 698043649 | L11: 756174884 | M11: 842622258 | N11: 880683604 | O11: 980069682 | P11: 474109480
A12: Jawa Timur | B12: gdpn_idd | C12: 396109803 | D12: 453373953 | E12: 513473583 | F12: 576991767 | G12: 653793451 | H12: 775113615 | I12: 901653910 | J12: 1024648174 | K12: 1216193713 | L12: 1350533088 | M12: 1535135402 | N12: 1730001376 | O12: 1959479709 | P12: 1094387400
... A50: Kalimantan Timur | B50: gfcn_idd | C50: 8906808 | D50: 11718497 | E50: 13751361 | F50: 16362774 | G50: 18487192 | H50: 20886840 | I50: 24429058 | J50: 28331856 | K50: 35639764 | L50: 39242630 | M50: 44923631 | N50: 51476523 | O50: 60678389 | P50: 67488858
A51: Kalimantan Utara | B51: gfcn_idd
A52: Kep. Bangka Belitung | B52: gfcn_idd | C52: 948340 | D52: 1221073 | E52: 1320397 | F52: 1679193 | G52: 2706302 | H52: 3533109 | I52: 3793831 | J52: 4474760 | K52: 5588608 | L52: 6135023 | M52: 6826796 | N52: 7811270 | O52: 9235284 | P52: 10519079
A53: Kep. Riau | B53: gfcn_idd | C53: 11508795 | D53: 21345819 | E53: 26514246 | F53: 17781370 | G53: 18271618 | H53: 10470060 | I53: 13249338 | J53: 18464500 | K53: 28630934 | L53: 38169644 | M53: 51149983 | N53: 60223260 | O53: 72974470 | P53: 84252083
A54: Lampung | B54: gfcn_idd | C54: 4279942 | D54: 4553366 | E54: 4969997 | F54: 5323225 | G54: 5807551 | H54: 7379052 | I54: 8586097 | J54: 10127981 | K54: 13548673 | L54: 16299817 | M54: 18667584 | N54: 22130674 | O54: 25656641 | P54: 28983843
A55: Maluku | B55: gfcn_idd | C55: 76088 | D55: 86020 | E55: 144446 | F55: 160598 | G55: 192439 | H55: 209535 | I55: 244851 | J55: 326074 | K55: 380001 | L55: 421152 | M55: 509177 | N55: 625025 | O55: 818723 | P55: 937987
A56: Maluku Utara | B56: gfcn_idd | C56: 56155 | D56: 73955 | E56: 88988 | F56: 75126 | G56: 84301 | H56: 135748 | I56: 186402 | J56: 230930 | K56: 323630 | L56: 447619 | M56: 507019 | N56: 592832 | O56: 697330 | P56: 788003
A57: Nusa Tenggara Barat | B57: gfcn_idd | C57: 2858397 | D57: 3319583 | E57: 3713772 | F57: 4087296 | G57: 4601038 | H57: 5246875 | I57: 6070618 | J57: 7535111 | K57: 8845079 | L57: 11056066 | M57: 10809511 | N57: 12137547 | O57: 15370638 | P57: 16406323
A58: Nusa Tenggara Timur | B58: gfcn_idd | C58: 1616969 | D58: 1760479 | E58: 1876279 | F58: 1279469 | G58: 1681351 | H58: 1631425 | I58: 2466224 | J58: 2672400 | K58: 2905363 | L58: 3702522 | M58: 4568456 | N58: 5488722 | O58: 6765611 | P58: 8068143
A59: Papua | B59: gfcn_idd | C59: 2067425 | D59: 2812365 | E59: 4166789 | F59: 5060131 | G59: 6484486 | H59: 7536927 | I59: 10397056 | J59: 13801150 | K59: 17231782 | L59: 20809024 | M59: 24592564 | N59: 27783953 | O59: 30980533 | P59: 34869111
A60: Papua Barat | B60: gfcn_idd | C60: 2191890 | D60: 2787255 | E60: 2003830 | F60: 2372554 | G60: 2674027 | H60: 2942651 | I60: 3159414 | J60: 3469303 | K60: 4609113 | L60: 5624236 | M60: 6590543 | N60: 7914283 | O60: 10051777 | P60: 12538321
A61: Riau | B61: gfcn_idd | C61: 5627211 | D61: 9590933 | E61: 10916734 | F61: 24468044 | G61: 30835472 | H61: 34875392 | I61: 39192964 | J61: 48317380 | K61: 61464688 | L61: 72806510 | M61: 88613094 | N61: 101465266 | O61: 114773158 | P61: 129263751
A62: Sulawesi Barat | B62: gfcn_idd | C62: 245855 | D62: 287429 | E62: 346995 | F62: 363255 | G62: 392308 | H62: 444784 | I62: 546300 | J62: 853979 | K62: 1365252 | L62: 1494343 | M62: 1517598 | N62: 1589846 | O62: 1726512 | P62: 1968919
A63: Sulawesi Selatan | B63: gfcn_idd | C63: 4557358 | D63: 5456679 | E63: 6750138 | F63: 7244877 | G63: 8418816 | H63: 9109993 | I63: 10165991 | J63: 11983114 | K63: 17239192 | L63: 22274612 | M63: 27581958 | N63: 32502998 | O63: 44038575 | P63: 54940101
... A84: Kalimantan Timur | B84: expn_idd | C84: 91914888 | D84: 101605368 | E84: 97320072 | F84: 107421056 | G84: 138844560 | H84: 193360064 | I84: 220474960 | J84: 241420400 | K84: 336501536 | L84: 3.056442e+08 | M84: 3.525494e+08 | N84: 4.3218672e+08 | O84: 5.0043534e+08 | P84: 5.4552355e+08
A85: Kalimantan Utara | B85: expn_idd
A86: Kep. Bangka Belitung | B86: expn_idd | C86: 3077644 | D86: 3813274 | E86: 3364406 | F86: 3599161 | G86: 10737583 | H86: 13407583 | I86: 15217583 | J86: 16637174 | K86: 16953858 | L86: 16738629 | M86: 17738993 | N86: 18475266 | O86: 19438957 | P86: 21255982
A87: Kep. Riau | B87: expn_idd | C87: 41242120 | D87: 66695588 | E87: 56752457 | F87: 35557860 | G87: 38727024 | H87: 40597552 | I87: 43274652 | J87: 55241580 | K87: 60169288 | L87: 69484347 | M87: 81410818 | N87: 87602390 | O87: 1.008829e+08 | P87: 1.0959931e+08
A88: Lampung | B88: expn_idd | C88: 10308459 | D88: 9532442 | E88: 10947700 | F88: 12870669 | G88: 12836383 | H88: 16965478 | I88: 19699202 | J88: 23779604 | K88: 39910244 | L88: 38809589 | M88: 45457305 | N88: 54606538 | O88: 64941271 | P88: 69508570
A89: Maluku | B89: expn_idd | C89: 412431 | D89: 652194 | E89: 686523 | F89: 1082970 | G89: 1172972 | H89: 1260248 | I89: 1414782 | J89: 1609053 | K89: 1855563 | L89: 1934959.4 | M89: 2230059 | N89: 2458562.3 | O89: 2668356.4 | P89: 2873586.6
A90: Maluku Utara | B90: expn_idd | C90: 658379 | D90: 789073 | E90: 981565 | F90: 862467 | G90: 954785 | H90: 1051455 | I90: 1128431 | J90: 1330225 | K90: 1387048 | L90: 1359942.1 | M90: 1559669.2 | N90: 1627655.8 | O90: 1752671.7 | P90: 1895614.4
A91: Nusa Tenggara Barat | B91: expn_idd | C91: 4805512 | D91: 6695589 | E91: 6920011 | F91: 6637653 | G91: 10167133 | H91: 13449020 | I91: 13603797 | J91: 14111164 | K91: 11423354 | L91: 14450410 | M91: 17951412 | N91: 15785017 | O91: 13576922 | P91: 11945317
A92: Nusa Tenggara Timur | B92: expn_idd | C92: 1617720 | D92: 2467679 | E92: 2851853 | F92: 3078702 | G92: 2461273 | H92: 2651697 | I92: 4059393 | J92: 4119844 | K92: 4530480 | L92: 4887824.1 | M92: 5331313.6 | N92: 5855950.1 | O92: 6423290 | P92: 7269478.5
A93: Papua | B93: expn_idd | C93: 14022876 | D93: 16954659 | E93: 16321562 | F93: 17147306 | G93: 14358633 | H93: 29027882 | I93: 41710688 | J93: 40886732 | K93: 46326028 | L93: 54357577 | M93: 61351510 | N93: 48494233 | O93: 36669410 | P93: 45104664
A94: Papua Barat | B94: expn_idd | C94: 2842261.6 | D94: 3436497.2 | E94: 3022451 | F94: 2801496 | G94: 3252552 | H94: 4862876 | I94: 6181914 | J94: 6416179 | K94: 6787165 | L94: 6683435.5 | M94: 12243061 | N94: 19217910 | O94: 20638458 | P94: 26304998
A95: Riau | B95: expn_idd | C95: 13151920 | D95: 23596668 | E95: 22167231 | F95: 50828184 | G95: 62127136 | H95: 83217728 | I95: 93095352 | J95: 115487320 | K95: 167078240 | L95: 1.4882099e+08 | M95: 1.585081e+08 | N95: 1.9952979e+08 | O95: 2.1934707e+08 | P95: 2.2532227e+08
A96: Sulawesi Barat | B96: expn_idd | C96: 295893.04 | D96: 335832.16 | E96: 302691.98 | F96: 329803.6 | G96: 561925 | H96: 600189 | I96: 692559 | J96: 879728 | K96: 1161544 | L96: 1385534.4 | M96: 1690288.7 | N96: 2415943.5 | O96: 2632658 | P96: 3006632.7
A97: Sulawesi Selatan | B97: expn_idd | C97: 7776898 | D97: 8826609.8 | E97: 7955593 | F97: 8668162.4 | G97: 15052630 | H97: 18712936 | I97: 23539140 | J97: 32895836 | K97: 32153468 | L97: 28582418 | M97: 36426093 | N97: 30148743 | O97: 31821533 | P97: 37027694
... A118: Kalimantan Timur | B118: impn_idd | C118: 32774160 | D118: 39004416 | E118: 38408804 | F118: 42792336 | G118: 50036868 | H118: 68197648 | I118: 84885472 | J118: 91043248 | K118: 110079264 | L118: 1.1625382e+08 | M118: 1.3937412e+08 | N118: 167071565 | O118: 2.2957741e+08 | P118: 2.8884885e+08
A119: Kalimantan Utara | B119: impn_idd
A120: Kep. Bangka Belitung | B120: impn_idd | C120: 1438223 | D120: 1960669 | E120: 1849805 | F120: 2378717 | G120: 8572590 | H120: 11884590 | I120: 13949889 | J120: 15249158 | K120: 15522423 | L120: 16199635 | M120: 16610628 | N120: 17702825 | O120: 19801217 | P120: 21925325
A121: Kep. Riau | B121: impn_idd | C121: 8139250.8 | D121: 11181169 | E121: 12042159 | F121: 10586619 | G121: 16395080 | H121: 25742740 | I121: 27365448 | J121: 33986408 | K121: 45396136 | L121: 58410089 | M121: 73533595 | N121: 84659532 | O121: 90740178 | P121: 85773520
A122: Lampung | B122: impn_idd | C122: 8510354 | D122: 9242737 | E122: 10241831 | F122: 10823595 | G122: 9240983 | H122: 11516196 | I122: 14476925 | J122: 18946684 | K122: 33014218 | L122: 30282244 | M122: 25291955 | N122: 29498053 | O122: 38294240 | P122: 39873191
A123: Maluku | B123: impn_idd | C123: 374324 | D123: 862301 | E123: 949239 | F123: 1390047 | G123: 1474375 | H123: 1513290 | I123: 1727327 | J123: 2154295 | K123: 2448202 | L123: 2712617.2 | M123: 3111193.9 | N123: 3615276.2 | O123: 4492186.2 | P123: 5671916.3
A124: Maluku Utara | B124: impn_idd | C124: 451646 | D124: 447722 | E124: 506177 | F124: 511775 | G124: 515887 | H124: 653798 | I124: 745904 | J124: 845217 | K124: 942277 | L124: 1110050.1 | M124: 1354717.2 | N124: 1467939.1 | O124: 1718032.8 | P124: 1991269.5
A125: Nusa Tenggara Barat | B125: impn_idd | C125: 2766413 | D125: 3263752 | E125: 3315214 | F125: 3491632 | G125: 4084447 | H125: 5400761 | I125: 6180280 | J125: 7094899 | K125: 7573286 | L125: 9028761.9 | M125: 9114167.1 | N125: 11431731 | O125: 12168348 | P125: 13002521
A126: Nusa Tenggara Timur | B126: impn_idd | C126: 2966409 | D126: 3959488 | E126: 4551634 | F126: 4548429 | G126: 3723003 | H126: 3789699 | I126: 6401369 | J126: 6917927 | K126: 8308123 | L126: 9089186.6 | M126: 10862814 | N126: 13198760 | O126: 13556119 | P126: 16451179
A127: Papua | B127: impn_idd | C127: 7150345 | D127: 8923228 | E127: 10683034 | F127: 12154821 | G127: 13771918 | H127: 18776304 | I127: 24229896 | J127: 25285566 | K127: 34302752 | L127: 39422170 | M127: 46981257 | N127: 47151382 | O127: 49439911 | P127: 54823604
A128: Papua Barat | B128: impn_idd | C128: 4037299 | D128: 5038323 | E128: 4551967 | F128: 4333624 | G128: 4962927 | H128: 6439579 | I128: 8285290 | J128: 8529464 | K128: 9506931 | L128: 8523592.2 | M128: 9421284.6 | N128: 11004795 | O128: 14261988 | P128: 17997038
A129: Riau | B129: impn_idd | C129: 14288985 | D129: 14564097 | E129: 11770787 | F129: 18344640 | G129: 21441156 | H129: 26814380 | I129: 31948012 | J129: 37549804 | K129: 48370308 | L129: 46138459 | M129: 53219518 | N129: 59246404 | O129: 62981733 | P129: 67230911
A130: Sulawesi Barat | B130: impn_idd | C130: 319488.49 | D130: 427857.29 | E130: 461423.59 | F130: 505932.78 | G130: 648722 | H130: 687909 | I130: 921763 | J130: 1250068 | K130: 1876594 | L130: 2151039.9 | M130: 2471770.3 | N130: 3137629 | O130: 3520152.9 | P130: 3701271.9
A131: Sulawesi Selatan | B131: impn_idd | C131: 4793604.5 | D131: 6419569.7 | E131: 6923198.4 | F131: 7591014.2 | G131: 12235156 | H131: 15721574 | I131: 18558592 | J131: 27797634 | K131: 28224750 | L131: 27315825 | M131: 39642954 | N131: 35360593 | O131: 46492603 | P131: 60284258
... A137: Sumatera Utara | B137: impn_idd | C137: 2955321 | D137: 2779630 | E137: 2842433 | F137: 3023450 | G137: 4456682 | H137: 4817180 | I137: 5700687 | J137: 8607205 | K137: 12808914 | L137: 14437879 | M137: 17695374 | N137: 17756984 | O137: 20215394 | P137: 20624368
